Workbook
Name AutomationOptions: Lists!$C$2:$C$4
Name CheckOptions: Lists!$D$2:$D$3
Name DecisionOptions: Lists!$H$2:$H$5
Name DefectStatusOptions: Lists!$F$2:$F$6
Name PriorityOptions: Lists!$B$2:$B$5
Name RetestOptions: Lists!$E$2:$E$6
Name ScopeOptions: Lists!$I$2:$I$3
Name SeverityOptions: Lists!$G$2:$G$5
Name StatusOptions: Lists!$A$2:$A$7
Name TestTypeOptions: Lists!$J$2:$J$10

Sheet V4 SQA Report
A1: Robotics Programming Lab - v4 SQA Verification Report
A3: Release | B3: v4 Classroom Security Candidate | C3: Branch | D3: staging main | E3: Test Date | F3: 46238
A4: Commit | B4: Initial staging candidate; SHA recorded in Git/GitHub | C4: Frontend | D4: https://robotics-programming-lab.vercel.app/ | E4: Backend | F4: https://robotics-programming-lab-api.onrender.com
A5: Scope | B5: Verified local staging workflow plus classroom-security implementation. Private staging repository created; production repository remains unchanged. Hosted staging CI and live sandbox deployment remain open.
A7: Total Checks | B7: =COUNTA(A13:A58) -> 46 | C7: Passed | D7: =COUNTIF(C13:C58,"Pass") -> 36 | E7: Non-Pass / Open | F7: =B7-D7 -> 10
A8: Pass Rate | B8: =IF(B7=0,0,D7/B7) -> 0.7826087 | C8: Blocked | D8: =COUNTIF(C13:C58,"Blocked") -> 0 | E8: Not Run / Deferred | F8: =COUNTIF(C13:C58,"Not Run")+COUNTIF(C13:C58,"Deferred") -> 5
A9: Decision | B9: =IF(COUNTIF(C13:C58,"Fail")>0,"DO NOT RELEASE",IF(COUNTIF(C13:C58,"Blocked")>0,"DO NOT RELEASE",IF(COUNTIF(C13:C58,"Not Run")+COUNTIF(C13:C58,"Partial")>0,"CLASSROOM CANDIDATE - LIVE GATES OPEN","READY"))) -> CLASSROOM CANDIDATE - LIVE GATES OPEN
A12: Check ID | B12: Area / Feature | C12: Result | D12: Environment | E12: Evidence | F12: Limitation / Next Step
A13: V4-SQA-001 | B13: Source and tracked-secret audit | C13: Pass | D13: Local repository | E13: Clean tracked source; venv ignored; one synthetic migration URL scanner match. | F13: No real credential detected in tracked files.
A14: V4-SQA-002 | B14: Backend automated tests | C14: Pass | D14: Local | E14: 76 pytest checks passed in 27.38 seconds. | F14: Includes auth, assignment, grader, migration, rate-limit, remote-sandbox, and sandbox-service tests.
A15: V4-SQA-003 | B15: Python dependency integrity | C15: Pass | D15: Local | E15: pip check: no broken requirements. | F15: Fresh Python 3.11 venv created from backend requirements.
A16: V4-SQA-004 | B16: Python compilation | C16: Pass | D16: Local | E16: compileall completed without error. | F16: Backend modules compile.
A17: V4-SQA-005 | B17: Flutter static analysis | C17: Pass | D17: Local | E17: flutter analyze: no issues found. | F17: Current v4 source.
A18: V4-SQA-006 | B18: Flutter automated tests | C18: Pass | D18: Local | E18: 33 tests passed. | F18: Includes login entry, session policy, responsive UI, progress, execution state, and secure-grader loading.
A19: V4-SQA-007 | B19: Flutter release web build | C19: Pass | D19: Local | E19: Production web build completed in .flutter_build/web. | F19: Built with the live Render API URL.
A20: V4-SQA-008 | B20: Hosted CI and deployment | C20: Pass | D20: GitHub/Vercel | E20: Latest v4 verification and Vercel deployment succeeded. | F20: Existing hosted baseline passed; new classroom-security working tree is not yet pushed or deployed.
A21: V4-SQA-009 | B21: Live health and exact-origin CORS | C21: Pass | D21: Render | E21: Health API 4.0.0; exact Vercel origin allowed. | F21: Live API checks passed.
A22: V4-SQA-010 | B22: Login-first shared URL | C22: Pass | D22: Live Chrome | E22: Public root displayed login despite prior saved session. | F22: Demo credentials were not shown on the page.
A23: V4-SQA-011 | B23: Invalid login handling | C23: Pass | D23: Live Chrome/API | E23: Invalid credential returned a clear error and remained on login. | F23: No endless spinner or crash.
... A58: V4-SQA-046 | B58: Hosted staging CI | C58: Not Run | D58: GitHub Actions | E58: CI now includes repository safety, PostgreSQL migration, backend, Flutter, and sandbox Docker image smoke jobs. | F58: Run and verify after the initial staging main push.

Sheet Release Dashboard
A1: Robotics Programming Lab - SQA Release Dashboard
A2: Complete the Master Checklist for every release. Attach evidence, link defects, retest fixes, and obtain sign-off before publishing.
A4: Release / Version | B4: v4 Classroom Security Candidate | C4: Branch | D4: v4-live | E4: Commit | F4: Working tree - not committed | G4: Test Date | H4: 46238
A5: SQA Owner | B5: Codex SQA | C5: Environment | D5: Local security + retained live baseline | E5: Backend URL | F5: https://robotics-programming-lab-api.onrender.com | G5: Frontend Target | H5: Chrome / Flutter Web
A6: Scope Notes | B6: Dedicated sandbox implementation passes locally. Live sandbox image/deploy, Neon restart/restore, destructive production mutations, independent accessibility, and AI-on remain open.
A8: Release Readiness
A9: Metric | B9: Value | C9: Metric | D9: Value | E9: Metric | F9: Value | G9: Metric | H9: Value
A10: Total Checks | B10: =COUNTA('Master Checklist'!B2:B204) -> 203 | C10: Current Scope | D10: =COUNTIF('Master Checklist'!C2:C204,"Current") -> 191 | E10: Passed | F10: =COUNTIF('Master Checklist'!M2:M204,"Pass") -> 134 | G10: Failed | H10: =COUNTIF('Master Checklist'!M2:M204,"Fail") -> 0
A11: Blocked | B11: =COUNTIF('Master Checklist'!M2:M204,"Blocked") -> 0 | C11: Not Run | D11: =COUNTIF('Master Checklist'!M2:M204,"Not Run") -> 46 | E11: Deferred | F11: =COUNTIF('Master Checklist'!M2:M204,"Deferred") -> 14 | G11: N/A | H11: =COUNTIF('Master Checklist'!M2:M204,"N/A") -> 5
A12: Completion | B12: =IF(D10=0,0,(F10+H10+B11+H11)/D10) -> 0.72774869 | C12: Pass Rate | D12: =IF((F10+H10)=0,0,F10/(F10+H10)) -> 1 | E12: Release Gate Fail/Blocked | F12: =COUNTIFS('Master Checklist'!I2:I204,"Release Gate",'Master Checklist'!M2:M204,"Fail")+COUNTIFS('Master Checklist'!I2:I204,"Release Gate",'Master Checklist'!M2:M204,"Blocked") -> 0 | G12: Decision | H12: =IF(F12>0,"DO NOT RELEASE",IF(D11>0,"TESTING INCOMPLETE","READY FOR SIGN-OFF")) -> TESTING INCOMPLETE
A14: Category Coverage
A15: Category | B15: Total | C15: Pass | D15: Fail | E15: Blocked | F15: Not Run | G15: N/A | H15: Progress
A16: Environment & Startup | B16: =COUNTIF('Master Checklist'!D2:D204,A16) -> 11 | C16: =COUNTIFS('Master Checklist'!D2:D204,A16,'Master Checklist'!M2:M204,"Pass") -> 8 | D16: =COUNTIFS('Master Checklist'!D2:D204,A16,'Master Checklist'!M2:M204,"Fail") -> 0 | E16: =COUNTIFS('Master Checklist'!D2:D204,A16,'Master Checklist'!M2:M204,"Blocked") -> 0 | F16: =COUNTIFS('Master Checklist'!D2:D204,A16,'Master Checklist'!M2:M204,"Not Run") -> 3 | G16: =COUNTIFS('Master Checklist'!D2:D204,A16,'Master Checklist'!M2:M204,"N/A") -> 0 | H16: =IF(B16=0,0,(C16+D16+E16+G16)/B16) -> 0.72727273
A17: Health & Public API | B17: =COUNTIF('Master Checklist'!D2:D204,A17) -> 11 | C17: =COUNTIFS('Master Checklist'!D2:D204,A17,'Master Checklist'!M2:M204,"Pass") -> 9 | D17: =COUNTIFS('Master Checklist'!D2:D204,A17,'Master Checklist'!M2:M204,"Fail") -> 0 | E17: =COUNTIFS('Master Checklist'!D2:D204,A17,'Master Checklist'!M2:M204,"Blocked") -> 0 | F17: =COUNTIFS('Master Checklist'!D2:D204,A17,'Master Checklist'!M2:M204,"Not Run") -> 1 | G17: =COUNTIFS('Master Checklist'!D2:D204,A17,'Master Checklist'!M2:M204,"N/A") -> 1 | H17: =IF(B17=0,0,(C17+D17+E17+G17)/B17) -> 0.90909091
A18: Student Catalog & Navigation | B18: =COUNTIF('Master Checklist'!D2:D204,A18) -> 10 | C18: =COUNTIFS('Master Checklist'!D2:D204,A18,'Master Checklist'!M2:M204,"Pass") -> 10 | D18: =COUNTIFS('Master Checklist'!D2:D204,A18,'Master Checklist'!M2:M204,"Fail") -> 0 | E18: =COUNTIFS('Master Checklist'!D2:D204,A18,'Master Checklist'!M2:M204,"Blocked") -> 0 | F18: =COUNTIFS('Master Checklist'!D2:D204,A18,'Master Checklist'!M2:M204,"Not Run") -> 0 | G18: =COUNTIFS('Master Checklist'!D2:D204,A18,'Master Checklist'!M2:M204,"N/A") -> 0 | H18: =IF(B18=0,0,(C18+D18+E18+G18)/B18) -> 1
A19: Assignment Workspace & Editor | B19: =COUNTIF('Master Checklist'!D2:D204,A19) -> 16 | C19: =COUNTIFS('Master Checklist'!D2:D204,A19,'Master Checklist'!M2:M204,"Pass") -> 11 | D19: =COUNTIFS('Master Checklist'!D2:D204,A19,'Master Checklist'!M2:M204,"Fail") -> 0 | E19: =COUNTIFS('Master Checklist'!D2:D204,A19,'Master Checklist'!M2:M204,"Blocked") -> 0 | F19: =COUNTIFS('Master Checklist'!D2:D204,A19,'Master Checklist'!M2:M204,"Not Run") -> 5 | G19: =COUNTIFS('Master Checklist'!D2:D204,A19,'Master Checklist'!M2:M204,"N/A") -> 0 | H19: =IF(B19=0,0,(C19+D19+E19+G19)/B19) -> 0.6875
A20: Grading & Execution | B20: =COUNTIF('Master Checklist'!D2:D204,A20) -> 18 | C20: =COUNTIFS('Master Checklist'!D2:D204,A20,'Master Checklist'!M2:M204,"Pass") -> 18 | D20: =COUNTIFS('Master Checklist'!D2:D204,A20,'Master Checklist'!M2:M204,"Fail") -> 0 | E20: =COUNTIFS('Master Checklist'!D2:D204,A20,'Master Checklist'!M2:M204,"Blocked") -> 0 | F20: =COUNTIFS('Master Checklist'!D2:D204,A20,'Master Checklist'!M2:M204,"Not Run") -> 0 | G20: =COUNTIFS('Master Checklist'!D2:D204,A20,'Master Checklist'!M2:M204,"N/A") -> 0 | H20: =IF(B20=0,0,(C20+D20+E20+G20)/B20) -> 1
A21: Sandbox, Security & Privacy | B21: =COUNTIF('Master Checklist'!D2:D204,A21) -> 15 | C21: =COUNTIFS('Master Checklist'!D2:D204,A21,'Master Checklist'!M2:M204,"Pass") -> 8 | D21: =COUNTIFS('Master Checklist'!D2:D204,A21,'Master Checklist'!M2:M204,"Fail") -> 0 | E21: =COUNTIFS('Master Checklist'!D2:D204,A21,'Master Checklist'!M2:M204,"Blocked") -> 0 | F21: =COUNTIFS('Master Checklist'!D2:D204,A21,'Master Checklist'!M2:M204,"Not Run") -> 3 | G21: =COUNTIFS('Master Checklist'!D2:D204,A21,'Master Checklist'!M2:M204,"N/A") -> 0 | H21: =IF(B21=0,0,(C21+D21+E21+G21)/B21) -> 0.53333333
A22: Feedback & Tutoring | B22: =COUNTIF('Master Checklist'!D2:D204,A22) -> 13 | C22: =COUNTIFS('Master Checklist'!D2:D204,A22,'Master Checklist'!M2:M204,"Pass") -> 9 | D22: =COUNTIFS('Master Checklist'!D2:D204,A22,'Master Checklist'!M2:M204,"Fail") -> 0 | E22: =COUNTIFS('Master Checklist'!D2:D204,A22,'Master Checklist'!M2:M204,"Blocked") -> 0 | F22: =COUNTIFS('Master Checklist'!D2:D204,A22,'Master Checklist'!M2:M204,"Not Run") -> 2 | G22: =COUNTIFS('Master Checklist'!D2:D204,A22,'Master Checklist'!M2:M204,"N/A") -> 0 | H22: =IF(B22=0,0,(C22+D22+E22+G22)/B22) -> 0.69230769
A23: Solutions & Learning Progress | B23: =COUNTIF('Master Checklist'!D2:D204,A23) -> 12 | C23: =COUNTIFS('Master Checklist'!D2:D204,A23,'Master Checklist'!M2:M204,"Pass") -> 8 | D23: =COUNTIFS('Master Checklist'!D2:D204,A23,'Master Checklist'!M2:M204,"Fail") -> 0 | E23: =COUNTIFS('Master Checklist'!D2:D204,A23,'Master Checklist'!M2:M204,"Blocked") -> 0 | F23: =COUNTIFS('Master Checklist'!D2:D204,A23,'Master Checklist'!M2:M204,"Not Run") -> 4 | G23: =COUNTIFS('Master Checklist'!D2:D204,A23,'Master Checklist'!M2:M204,"N/A") -> 0 | H23: =IF(B23=0,0,(C23+D23+E23+G23)/B23) -> 0.66666667
A24: Instructor Assignment Studio | B24: =COUNTIF('Master Checklist'!D2:D204,A24) -> 17 | C24: =COUNTIFS('Master Checklist'!D2:D204,A24,'Master Checklist'!M2:M204,"Pass") -> 8 | D24: =COUNTIFS('Master Checklist'!D2:D204,A24,'Master Checklist'!M2:M204,"Fail") -> 0 | E24: =COUNTIFS('Master Checklist'!D2:D204,A24,'Master Checklist'!M2:M204,"Blocked") -> 0 | F24: =COUNTIFS('Master Checklist'!D2:D204,A24,'Master Checklist'!M2:M204,"Not Run") -> 9 | G24: =COUNTIFS('Master Checklist'!D2:D204,A24,'Master Checklist'!M2:M204,"N/A") -> 0 | H24: =IF(B24=0,0,(C24+D24+E24+G24)/B24) -> 0.47058824
A25: Authentication & Account Management | B25: =COUNTIF('Master Checklist'!D2:D204,A25) -> 22 | C25: =COUNTIFS('Master Checklist'!D2:D204,A25,'Master Checklist'!M2:M204,"Pass") -> 18 | D25: =COUNTIFS('Master Checklist'!D2:D204,A25,'Master Checklist'!M2:M204,"Fail") -> 0 | E25: =COUNTIFS('Master Checklist'!D2:D204,A25,'Master Checklist'!M2:M204,"Blocked") -> 0 | F25: =COUNTIFS('Master Checklist'!D2:D204,A25,'Master Checklist'!M2:M204,"Not Run") -> 1 | G25: =COUNTIFS('Master Checklist'!D2:D204,A25,'Master Checklist'!M2:M204,"N/A") -> 3 | H25: =IF(B25=0,0,(C25+D25+E25+G25)/B25) -> 0.95454545
A26: Assignment Content & Pedagogy | B26: =COUNTIF('Master Checklist'!D2:D204,A26) -> 10 | C26: =COUNTIFS('Master Checklist'!D2:D204,A26,'Master Checklist'!M2:M204,"Pass") -> 6 | D26: =COUNTIFS('Master Checklist'!D2:D204,A26,'Master Checklist'!M2:M204,"Fail") -> 0 | E26: =COUNTIFS('Master Checklist'!D2:D204,A26,'Master Checklist'!M2:M204,"Blocked") -> 0 | F26: =COUNTIFS('Master Checklist'!D2:D204,A26,'Master Checklist'!M2:M204,"Not Run") -> 4 | G26: =COUNTIFS('Master Checklist'!D2:D204,A26,'Master Checklist'!M2:M204,"N/A") -> 0 | H26: =IF(B26=0,0,(C26+D26+E26+G26)/B26) -> 0.6
A27: Responsive, Accessibility & Usability | B27: =COUNTIF('Master Checklist'!D2:D204,A27) -> 10 | C27: =COUNTIFS('Master Checklist'!D2:D204,A27,'Master Checklist'!M2:M204,"Pass") -> 6 | D27: =COUNTIFS('Master Checklist'!D2:D204,A27,'Master Checklist'!M2:M204,"Fail") -> 0 | E27: =COUNTIFS('Master Checklist'!D2:D204,A27,'Master Checklist'!M2:M204,"Blocked") -> 0 | F27: =COUNTIFS('Master Checklist'!D2:D204,A27,'Master Checklist'!M2:M204,"Not Run") -> 4 | G27: =COUNTIFS('Master Checklist'!D2:D204,A27,'Master Checklist'!M2:M204,"N/A") -> 0 | H27: =IF(B27=0,0,(C27+D27+E27+G27)/B27) -> 0.6
A28: Data, Infrastructure & Deployment | B28: =COUNTIF('Master Checklist'!D2:D204,A28) -> 14 | C28: =COUNTIFS('Master Checklist'!D2:D204,A28,'Master Checklist'!M2:M204,"Pass") -> 5 | D28: =COUNTIFS('Master Checklist'!D2:D204,A28,'Master Checklist'!M2:M204,"Fail") -> 0 | E28: =COUNTIFS('Master Checklist'!D2:D204,A28,'Master Checklist'!M2:M204,"Blocked") -> 0 | F28: =COUNTIFS('Master Checklist'!D2:D204,A28,'Master Checklist'!M2:M204,"Not Run") -> 8 | G28: =COUNTIFS('Master Checklist'!D2:D204,A28,'Master Checklist'!M2:M204,"N/A") -> 1 | H28: =IF(B28=0,0,(C28+D28+E28+G28)/B28) -> 0.42857143
A29: Automated Quality & Release | B29: =COUNTIF('Master Checklist'!D2:D204,A29) -> 12 | C29: =COUNTIFS('Master Checklist'!D2:D204,A29,'Master Checklist'!M2:M204,"Pass") -> 10 | D29: =COUNTIFS('Master Checklist'!D2:D204,A29,'Master Checklist'!M2:M204,"Fail") -> 0 | E29: =COUNTIFS('Master Checklist'!D2:D204,A29,'Master Checklist'!M2:M204,"Blocked") -> 0 | F29: =COUNTIFS('Master Checklist'!D2:D204,A29,'Master Checklist'!M2:M204,"Not Run") -> 2 | G29: =COUNTIFS('Master Checklist'!D2:D204,A29,'Master Checklist'!M2:M204,"N/A") -> 0 | H29: =IF(B29=0,0,(C29+D29+E29+G29)/B29) -> 0.83333333
A32: Open product/architecture plan

Sheet Master Checklist
A1: Checked? | B1: Check ID | C1: Scope | D1: Category | E1: Feature / Requirement | F1: Preconditions | G1: Test Steps | H1: Expected Result | I1: Priority | J1: Test Type | K1: Platform | L1: Automated? | M1: Status | N1: Defect ID | O1: Actual Result / Evidence | P1: Tester | Q1: Test Date | R1: Retest Status | S1: Notes
A2: [x] | B2: ENV-001 | C2: Current | D2: Environment & Startup | E2: Repository clone contains required source and configuration files | F2: Application dependencies are installed and the target environment is available. | G2: Clone the repository; verify backend, frontend, assignments, course_materials, Dockerfiles, Compose, README, and plan artifacts are present. | H2: Required project structure is complete and no required imported source file is missing. | I2: Release Gate | J2: Inspection | K2: Repository | L2: Partial | M2: Pass | O2: Fresh v4 local setup/install plus Flutter analyzer, 33 tests, and release web build passed on 2026-08-04. | P2: Codex SQA | Q2: 46238 | R2: Not Required
A3: [x] | B3: ENV-002 | C3: Current | D3: Environment & Startup | E3: Secrets are not committed | F3: Application dependencies are installed and the target environment is available. | G3: Run Git secret and tracked-file checks; inspect .gitignore and tracked files for .env, API keys, admin tokens, databases, and credentials. | H3: No secret, backend/.env, database, or credential value is tracked. | I3: Release Gate | J3: Security | K3: Repository | L3: Partial | M3: Pass | O3: Fresh v4 local setup/install plus Flutter analyzer, 33 tests, and release web build passed on 2026-08-04. | P3: Codex SQA | Q3: 46238 | R3: Not Required
A4: [x] | B4: ENV-003 | C4: Current | D4: Environment & Startup | E4: Python virtual environment can be created | F4: Application dependencies are installed and the target environment is available. | G4: Run python -m venv venv in a clean checkout. | H4: Virtual environment is created without errors. | I4: P1 | J4: Installation | K4: Windows | L4: No | M4: Pass | O4: Fresh v4 local setup/install plus Flutter analyzer, 33 tests, and release web build passed on 2026-08-04. | P4: Codex SQA | Q4: 46238 | R4: Not Required
A5: [x] | B5: ENV-004 | C5: Current | D5: Environment & Startup | E5: Backend dependencies install | F5: Application dependencies are installed and the target environment is available. | G5: Run .\venv\Scripts\python.exe -m pip install -r .\backend\requirements.txt. | H5: All required packages install successfully. | I5: Release Gate | J5: Installation | K5: Windows | L5: No | M5: Pass | O5: Fresh v4 local setup/install plus Flutter analyzer, 33 tests, and release web build passed on 2026-08-04. | P5: Codex SQA | Q5: 46238 | R5: Not Required
A6: [x] | B6: ENV-005 | C6: Current | D6: Environment & Startup | E6: Python dependency integrity | F6: Application dependencies are installed and the target environment is available. | G6: Run .\venv\Scripts\python.exe -m pip check. | H6: Command reports no broken requirements. | I6: Release Gate | J6: Automated | K6: Backend | L6: Yes | M6: Pass | O6: Fresh v4 local setup/install plus Flutter analyzer, 33 tests, and release web build passed on 2026-08-04. | P6: Codex SQA | Q6: 46238 | R6: Not Required
A7: [x] | B7: ENV-006 | C7: Current | D7: Environment & Startup | E7: Flutter dependencies resolve | F7: Application dependencies are installed and the target environment is available. | G7: From frontend run flutter pub get. | H7: Flutter resolves dependencies without errors. | I7: Release Gate | J7: Installation | K7: Flutter | L7: No | M7: Pass | O7: Fresh v4 local setup/install plus Flutter analyzer, 33 tests, and release web build passed on 2026-08-04. | P7: Codex SQA | Q7: 46238 | R7: Not Required
A8: [ ] | B8: ENV-007 | C8: Current | D8: Environment & Startup | E8: Backend starts locally | F8: Application dependencies are installed and the target environment is available. | G8: Run .\venv\Scripts\python.exe .\backend\run.py and observe startup. | H8: FastAPI starts on the configured host/port and remains stable. | I8: Release Gate | J8: Smoke | K8: Backend | L8: No | M8: Not Run | R8: Not Required
A9: [ ] | B9: ENV-008 | C9: Current | D9: Environment & Startup | E9: Frontend starts in Chrome | F9: Application dependencies are installed and the target environment is available. | G9: Keep backend running; from frontend run flutter run -d chrome --dart-define=API_BASE_URL=http://127.0.0.1:5000. | H9: Chrome opens the application and the catalog loads. | I9: Release Gate | J9: Smoke | K9: Web | L9: No | M9: Not Run | R9: Not Required
A10: [x] | B10: ENV-009 | C10: Current | D10: Environment & Startup | E10: OneDrive-safe Flutter build output | F10: Application dependencies are installed and the target environment is available. | G10: Build or run from the OneDrive checkout using the configured .flutter_build path. | H10: Flutter creates assets without directory deletion or shader write failures. | I10: P1 | J10: Regression | K10: Windows/Web | L10: Partial | M10: Pass | O10: Fresh v4 local setup/install plus Flutter analyzer, 33 tests, and release web build passed on 2026-08-04. | P10: Codex SQA | Q10: 46238 | R10: Not Required
A11: [x] | B11: ENV-010 | C11: Current | D11: Environment & Startup | E11: Backend URL is configurable | F11: Application dependencies are installed and the target environment is available. | G11: Build/run with a nondefault API_BASE_URL and inspect requests. | H11: Frontend sends requests to the supplied URL, including image URLs and Monaco configuration. | I11: P1 | J11: Configuration | K11: Flutter | L11: Partial | M11: Pass | O11: Fresh v4 local setup/install plus Flutter analyzer, 33 tests, and release web build passed on 2026-08-04. | P11: Codex SQA | Q11: 46238 | R11: Not Required
A12: [ ] | B12: ENV-011 | C12: Current | D12: Environment & Startup | E12: Backend environment file loads | F12: Application dependencies are installed and the target environment is available. | G12: Place nonsecret test configuration in backend/.env; restart backend; inspect /health and relevant behavior. | H12: Settings load from backend/.env while the file remains ignored. | I12: P1 | J12: Configuration | K12: Backend | L12: Partial | M12: Not Run | R12: Not Required
A13: [x] | B13: API-001 | C13: Current | D13: Health & Public API | E13: Health endpoint responds | F13: Application dependencies are installed and the target environment is available. | G13: GET /health. | H13: HTTP 200 returns status ok, API version, database type, and sandbox type. | I13: Release Gate | J13: API | K13: Backend | L13: Yes | M13: Pass | O13: 76 backend tests passed; live API health/auth/CORS/assignment/image checks passed 13/13. | P13: Codex SQA | Q13: 46238 | R13: Not Required
A14: [x] | B14: API-002 | C14: Current | D14: Health & Public API | E14: OpenAPI documentation loads | F14: Application dependencies are installed and the target environment is available. | G14: Open /docs. | H14: Interactive FastAPI documentation loads and lists supported public/admin endpoints. | I14: P1 | J14: API | K14: Backend | L14: No | M14: N/A | O14: Intentionally disabled or unnecessary for the controlled v4 professor demo. | P14: Codex SQA | Q14: 46238 | R14: Not Required | S14: Preserved for a future broader study release where applicable.
A15: [x] | B15: API-003 | C15: Current | D15: Health & Public API | E15: Assignment list endpoint | F15: Application dependencies are installed and the target environment is available. | G15: GET /assignments and GET /assignments/. | H15: HTTP 200 returns four published assignments in numeric order. | I15: Release Gate | J15: API | K15: Backend | L15: Yes | M15: Pass | O15: 76 backend tests passed; live API health/auth/CORS/assignment/image checks passed 13/13. | P15: Codex SQA | Q15: 46238 | R15: Not Required
A16: [x] | B16: API-004 | C16: Current | D16: Health & Public API | E16: Assignment detail endpoint | F16: Application dependencies are installed and the target environment is available. | G16: GET /assignments/{id} for IDs 1 through 4. | H16: Each response contains student-visible assignment data and correct stable ID/version. | I16: Release Gate | J16: API | K16: Backend | L16: Yes | M16: Pass | O16: 76 backend tests passed; live API health/auth/CORS/assignment/image checks passed 13/13. | P16: Codex SQA | Q16: 46238 | R16: Not Required
A17: [x] | B17: API-005 | C17: Current | D17: Health & Public API | E17: Unknown assignment returns JSON 404 | F17: Application dependencies are installed and the target environment is available. | G17: GET /assignments/999. | H17: HTTP 404 returns the documented JSON error. | I17: P1 | J17: Negative API | K17: Backend | L17: Yes | M17: Pass | O17: 76 backend tests passed; live API health/auth/CORS/assignment/image checks passed 13/13. | P17: Codex SQA | Q17: 46238 | R17: Not Required
A18: [x] | B18: API-006 | C18: Current | D18: Health & Public API | E18: Assignment image endpoint | F18: Application dependencies are installed and the target environment is available. | G18: GET /images/1 and inspect content type/signature. | H18: HTTP 200 returns the expected PNG image. | I18: P1 | J18: API | K18: Backend | L18: Yes | M18: Pass | O18: 76 backend tests passed; live API health/auth/CORS/assignment/image checks passed 13/13. | P18: Codex SQA | Q18: 46238 | R18: Not Required
A19: [x] | B19: API-007 | C19: Current | D19: Health & Public API | E19: Unknown image returns JSON 404 | F19: Application dependencies are installed and the target environment is available. | G19: GET /images/999. | H19: HTTP 404 returns the documented JSON error. | I19: P2 | J19: Negative API | K19: Backend | L19: Yes | M19: Pass | O19: 76 backend tests passed; live API health/auth/CORS/assignment/image checks passed 13/13. | P19: Codex SQA | Q19: 46238 | R19: Not Required
A20: [x] | B20: API-008 | C20: Current | D20: Health & Public API | E20: Legacy grading compatibility | F20: Application dependencies are installed and the target environment is available. | G20: POST valid code to /grade/{id}. | H20: Legacy route returns the current structured grading contract. | I20: P1 | J20: Compatibility | K20: Backend | L20: Yes | M20: Pass | O20: 76 backend tests passed; live API health/auth/CORS/assignment/image checks passed 13/13. | P20: Codex SQA | Q20: 46238 | R20: Not Required
A21: [x] | B21: API-009 | C21: Current | D21: Health & Public API | E21: CORS permits configured frontend | F21: Application dependencies are installed and the target environment is available. | G21: Run frontend from the allowed origin and call public endpoints. | H21: Browser requests succeed without CORS errors; unapproved origins follow configured policy. | I21: P1 | J21: Integration | K21: Web/Backend | L21: Partial | M21: Pass | O21: 76 backend tests passed; live API health/auth/CORS/assignment/image checks passed 13/13. | P21: Codex SQA | Q21: 46238 | R21: Not Required
A22: [x] | B22: API-010 | C22: Current | D22: Health & Public API | E22: Malformed JSON is rejected | F22: Application dependencies are installed and the target environment is available. | G22: POST malformed JSON to a submission endpoint. | H22: Request returns controlled HTTP 400 without server crash or stack-trace leakage. | I22: P1 | J22: Negative API | K22: Backend | L22: Yes | M22: Pass | O22: 76 backend tests passed; live API health/auth/CORS/assignment/image checks passed 13/13. | P22: Codex SQA | Q22: 46238 | R22: Not Required
A23: [ ] | B23: API-011 | C23: Current | D23: Health & Public API | E23: Request timeout behavior is bounded | F23: Application dependencies are installed and the target environment is available. | G23: Simulate an unavailable or nonresponsive backend. | H23: Frontend leaves loading state within configured timeout and shows a recovery action. | I23: P1 | J23: Resilience | K23: Flutter | L23: Partial | M23: Not Run | R23: Not Required
A24: [x] | B24: CAT-001 | C24: Current | D24: Student Catalog & Navigation | E24: Catalog header and identity | F24: Application dependencies are installed and the target environment is available. | G24: Open the landing page. | H24: Robotics Programming Lab identity and subtitle render correctly. | I24: P2 | J24: UI | K24: Web/Mobile | L24: Yes | M24: Pass | O24: 32 Flutter tests passed; live Chrome student catalog showed four ordered assignments. | P24: Codex SQA | Q24: 46238 | R24: Not Required
A25: [x] | B25: CAT-002 | C25: Current | D25: Student Catalog & Navigation | E25: Four assignment cards render | F25: Application dependencies are installed and the target environment is available. | G25: Load the catalog. | H25: Exactly four current published assignment cards render with title, number, description, and action. | I25: Release Gate | J25: UI/API | K25: Web/Mobile | L25: Partial | M25: Pass | O25: 32 Flutter tests passed; live Chrome student catalog showed four ordered assignments. | P25: Codex SQA | Q25: 46238 | R25: Not Required
A26: [x] | B26: CAT-003 | C26: Current | D26: Student Catalog & Navigation | E26: Assignment ordering | F26: Application dependencies are installed and the target environment is available. | G26: Inspect catalog order. | H26: Assignments are ordered 1, 2, 3, 4. | I26: P1 | J26: UI | K26: Web/Mobile | L26: Yes | M26: Pass | O26: 32 Flutter tests passed; live Chrome student catalog showed four ordered assignments. | P26: Codex SQA | Q26: 46238 | R26: Not Required
A27: [x] | B27: CAT-004 | C27: Current | D27: Student Catalog & Navigation | E27: Progress summary default | F27: Application dependencies are installed and the target environment is available. | G27: Open with cleared local progress. | H27: Summary shows 0 of 4 completed and 0 percent. | I27: P1 | J27: State | K27: Web/Mobile | L27: Yes | M27: Pass | O27: 32 Flutter tests passed; live Chrome student catalog showed four ordered assignments. | P27: Codex SQA | Q27: 46238 | R27: Not Required
A28: [x] | B28: CAT-005 | C28: Current | D28: Student Catalog & Navigation | E28: Progress badges | F28: Application dependencies are installed and the target environment is available. | G28: Record attempts, completion, and solution reveal; return to catalog. | H28: Cards distinguish Not started, Attempted, Completed, last score, and Solution viewed states. | I28: P1 | J28: State | K28: Web/Mobile | L28: Yes | M28: Pass | O28: 32 Flutter tests passed; live Chrome student catalog showed four ordered assignments. | P28: Codex SQA | Q28: 46238 | R28: Not Required
A29: [x] | B29: CAT-006 | C29: Current | D29: Student Catalog & Navigation | E29: Open assignment | F29: Application dependencies are installed and the target environment is available. | G29: Select Start assignment on each card. | H29: Correct assignment workspace opens without losing assignment identity. | I29: Release Gate | J29: Navigation | K29: Web/Mobile | L29: Partial | M29: Pass | O29: 32 Flutter tests passed; live Chrome student catalog showed four ordered assignments. | P29: Codex SQA | Q29: 46238 | R29: Not Required
A30: [x] | B30: CAT-007 | C30: Current | D30: Student Catalog & Navigation | E30: Return to catalog | F30: Application dependencies are installed and the target environment is available. | G30: Open an assignment and use Home/back navigation. | H30: Catalog returns and refreshed progress is visible. | I30: P1 | J30: Navigation | K30: Web/Mobile | L30: Yes | M30: Pass | O30: 32 Flutter tests passed; live Chrome student catalog showed four ordered assignments. | P30: Codex SQA | Q30: 46238 | R30: Not Required
A31: [x] | B31: CAT-008 | C31: Current | D31: Student Catalog & Navigation | E31: Catalog loading state | F31: Application dependencies are installed and the target environment is available. | G31: Throttle assignment-list response. | H31: Skeleton/loading state renders without layout breakage. | I31: P2 | J31: UI/Resilience | K31: Web/Mobile | L31: Yes | M31: Pass | O31: 32 Flutter tests passed; live Chrome student catalog showed four ordered assignments. | P31: Codex SQA | Q31: 46238 | R31: Not Required
A32: [x] | B32: CAT-009 | C32: Current | D32: Student Catalog & Navigation | E32: Catalog error and retry | F32: Application dependencies are installed and the target environment is available. | G32: Stop backend, load catalog, restart backend, select retry. | H32: Actionable error appears and retry reloads assignments successfully. | I32: P1 | J32: Resilience | K32: Web/Mobile | L32: Yes | M32: Pass | O32: 32 Flutter tests passed; live Chrome student catalog showed four ordered assignments. | P32: Codex SQA | Q32: 46238 | R32: Not Required
A33: [x] | B33: CAT-010 | C33: Current | D33: Student Catalog & Navigation | E33: Instructor entry point | F33: Application dependencies are installed and the target environment is available. | G33: Select the instructor shield icon. | H33: Instructor assignment studio opens; student progress remains unaffected. | I33: P1 | J33: Navigation | K33: Web/Mobile | L33: Partial | M33: Pass | O33: 32 Flutter tests passed; live Chrome student catalog showed four ordered assignments. | P33: Codex SQA | Q33: 46238 | R33: Not Required
A34: [x] | B34: WRK-001 | C34: Current | D34: Assignment Workspace & Editor | E34: Correct assignment header | F34: Application dependencies are installed and the target environment is available. | G34: Open every assignment. | H34: Header shows assignment number, title, progress state, Home action, and AI toggle. | I34: P1 | J34: UI | K34: Web/Mobile | L34: Partial | M34: Pass | O34: Flutter tests passed; live Assignment 1 workspace, starter code, instructions, image, and results rendered. | P34: Codex SQA | Q34: 46238 | R34: Not Required
A35: [x] | B35: WRK-002 | C35: Current | D35: Assignment Workspace & Editor | E35: Starter code loads | F35: Application dependencies are installed and the target environment is available. | G35: Open a fresh assignment with no saved draft. | H35: Version-correct starter code populates the editor. | I35: Release Gate | J35: Integration | K35: Web/Mobile | L35: Partial | M35: Pass | O35: Flutter tests passed; live Assignment 1 workspace, starter code, instructions, image, and results rendered. | P35: Codex SQA | Q35: 46238 | R35: Not Required
A36: [x] | B36: WRK-003 | C36: Current | D36: Assignment Workspace & Editor | E36: Starter code is syntactically executable | F36: Application dependencies are installed and the target environment is available. | G36: Compile and submit starter code for assignments 1 through 4. | H36: Each starter runs without unintended SyntaxError or IndentationError. | I36: Release Gate | J36: Regression | K36: Backend | L36: Yes | M36: Pass | O36: Flutter tests passed; live Assignment 1 workspace, starter code, instructions, image, and results rendered. | P36: Codex SQA | Q36: 46238 | R36: Not Required
A37: [ ] | B37: WRK-004 | C37: Current | D37: Assignment Workspace & Editor | E37: Code editing | F37: Application dependencies are installed and the target environment is available. | G37: Type, delete, paste, and indent Python code. | H37: Editor accurately reflects edits and retains Python formatting. | I37: P1 | J37: UI | K37: Web | L37: No | M37: Not Run | R37: Not Required
A38: [x] | B38: WRK-005 | C38: Current | D38: Assignment Workspace & Editor | E38: Keyboard test execution | F38: Application dependencies are installed and the target environment is available. | G38: Press Ctrl+Enter while the editor is active. | H38: Exactly one test run starts. | I38: P1 | J38: Keyboard | K38: Web/Desktop | L38: Yes | M38: Pass | O38: Flutter tests passed; live Assignment 1 workspace, starter code, instructions, image, and results rendered. | P38: Codex SQA | Q38: 46238 | R38: Not Required
A39: [x] | B39: WRK-006 | C39: Current | D39: Assignment Workspace & Editor | E39: Run button execution | F39: Application dependencies are installed and the target environment is available. | G39: Select Run tests. | H39: Button enters running state, blocks duplicate execution, then returns to enabled state. | I39: Release Gate | J39: UI/Integration | K39: Web/Mobile | L39: Yes | M39: Pass | O39: Flutter tests passed; live Assignment 1 workspace, starter code, instructions, image, and results rendered. | P39: Codex SQA | Q39: 46238 | R39: Not Required
A40: [ ] | B40: WRK-007 | C40: Current | D40: Assignment Workspace & Editor | E40: Draft autosave | F40: Application dependencies are installed and the target environment is available. | G40: Edit code; wait for debounce; leave assignment. | H40: Draft is persisted for the assignment. | I40: P1 | J40: State | K40: Web/Mobile | L40: Partial | M40: Not Run | R40: Not Required
A41: [x] | B41: WRK-008 | C41: Current | D41: Assignment Workspace & Editor | E41: Draft restore | F41: Application dependencies are installed and the target environment is available. | G41: Reopen an assignment after saving a draft. | H41: Saved draft replaces starter code only for that assignment. | I41: P1 | J41: State | K41: Web/Mobile | L41: Yes | M41: Pass | O41: Flutter tests passed; live Assignment 1 workspace, starter code, instructions, image, and results rendered. | P41: Codex SQA | Q41: 46238 | R41: Not Required
A42: [x] | B42: WRK-009 | C42: Current | D42: Assignment Workspace & Editor | E42: Independent assignment drafts | F42: Application dependencies are installed and the target environment is available. | G42: Save different code in two assignments and reopen both. | H42: Each assignment restores only its own draft. | I42: P1 | J42: State | K42: Web/Mobile | L42: Yes | M42: Pass | O42: Flutter tests passed; live Assignment 1 workspace, starter code, instructions, image, and results rendered. | P42: Codex SQA | Q42: 46238 | R42: Not Required
A43: [x] | B43: WRK-010 | C43: Current | D43: Assignment Workspace & Editor | E43: Scenario section | F43: Application dependencies are installed and the target environment is available. | G43: Inspect instructions for every assignment. | H43: Scenario content is present, readable, and belongs to the correct assignment. | I43: Release Gate | J43: Content/UI | K43: Web/Mobile | L43: Partial | M43: Pass | O43: Flutter tests passed; live Assignment 1 workspace, starter code, instructions, image, and results rendered. | P43: Codex SQA | Q43: 46238 | R43: Not Required
A44: [ ] | B44: WRK-011 | C44: Current | D44: Assignment Workspace & Editor | E44: Task and hints sections | F44: Application dependencies are installed and the target environment is available. | G44: Inspect instruction structure. | H44: Task/question and hints are organized without exposing the solution. | I44: Release Gate | J44: Content/Security | K44: Web/Mobile | L44: Partial | M44: Not Run | R44: Not Required
A45: [x] | B45: WRK-012 | C45: Current | D45: Assignment Workspace & Editor | E45: Assignment image rewriting | F45: Application dependencies are installed and the target environment is available. | G45: Run against nondefault API_BASE_URL and open assignment 1. | H45: Image URL uses the configured backend and loads successfully. | I45: P1 | J45: Integration | K45: Web/Mobile | L45: Partial | M45: Pass | O45: Flutter tests passed; live Assignment 1 workspace, starter code, instructions, image, and results rendered. | P45: Codex SQA | Q45: 46238 | R45: Not Required
A46: [x] | B46: WRK-013 | C46: Current | D46: Assignment Workspace & Editor | E46: Desktop panel focus | F46: Application dependencies are installed and the target environment is available. | G46: Use focus/maximize controls for editor, instructions, and results. | H46: Selected panel expands and restores without losing state. | I46: P2 | J46: Responsive UI | K46: Web/Desktop | L46: Yes | M46: Pass | O46: Flutter tests passed; live Assignment 1 workspace, starter code, instructions, image, and results rendered. | P46: Codex SQA | Q46: 46238 | R46: Not Required
A47: [ ] | B47: WRK-014 | C47: Current | D47: Assignment Workspace & Editor | E47: Desktop resize handle | F47: Application dependencies are installed and the target environment is available. | G47: Drag the editor/instruction divider within allowed limits. | H47: Panels resize smoothly and remain usable. | I47: P2 | J47: Responsive UI | K47: Web/Desktop | L47: No | M47: Not Run | R47: Not Required
A48: [x] | B48: WRK-015 | C48: Current | D48: Assignment Workspace & Editor | E48: Mobile workspace tabs | F48: Application dependencies are installed and the target environment is available. | G48: Open at a narrow/mobile viewport and select Code, Instructions, and Results. | H48: Each tab shows the correct panel without overflow. | I48: Release Gate | J48: Responsive UI | K48: Mobile/Web | L48: Yes | M48: Pass | O48: Flutter tests passed; live Assignment 1 workspace, starter code, instructions, image, and results rendered. | P48: Codex SQA | Q48: 46238 | R48: Not Required
A49: [ ] | B49: WRK-016 | C49: Current | D49: Assignment Workspace & Editor | E49: Workspace state survives tab changes | F49: Application dependencies are installed and the target environment is available. | G49: Edit code, switch mobile tabs, and return. | H49: Code, results, hint level, and scroll-independent state are retained. | I49: P1 | J49: State/UI | K49: Mobile/Web | L49: Partial | M49: Not Run | R49: Not Required
A50: [x] | B50: GRD-001 | C50: Current | D50: Grading & Execution | E50: Public run endpoint executes code | F50: Application dependencies are installed and the target environment is available. | G50: POST code to /assignments/{id}/run. | H50: Execution result contains only public evidence and no hidden expectations. | I50: Release Gate | J50: API/Security | K50: Backend | L50: Yes | M50: Pass | O50: 76 backend tests passed, including all four official solutions; live Run tests completed with structured evidence. | P50: Codex SQA | Q50: 46238 | R50: Not Required
A51: [x] | B51: GRD-002 | C51: Current | D51: Grading & Execution | E51: Submission endpoint executes grader | F51: Application dependencies are installed and the target environment is available. | G51: POST valid code to /assignments/{id}/submit. | H51: Structured submission response includes submission ID, assignment version, score, evidence, and pass results. | I51: Release Gate | J51: API | K51: Backend | L51: Yes | M51: Pass | O51: 76 backend tests passed, including all four official solutions; live Run tests completed with structured evidence. | P51: Codex SQA | Q51: 46238 | R51: Not Required
A52: [x] | B52: GRD-003 | C52: Current | D52: Grading & Execution | E52: Assignment 1 official solution | F52: Application dependencies are installed and the target environment is available. | G52: Submit the server-controlled official solution for assignment 1. | H52: All hidden checks pass and score is 100 percent. | I52: Release Gate | J52: Regression | K52: Backend | L52: Yes | M52: Pass | O52: 76 backend tests passed, including all four official solutions; live Run tests completed with structured evidence. | P52: Codex SQA | Q52: 46238 | R52: Not Required
A53: [x] | B53: GRD-004 | C53: Current | D53: Grading & Execution | E53: Assignment 2 official solution | F53: Application dependencies are installed and the target environment is available. | G53: Submit the server-controlled official solution for assignment 2. | H53: All hidden checks pass and score is 100 percent. | I53: Release Gate | J53: Regression | K53: Backend | L53: Yes | M53: Pass | O53: 76 backend tests passed, including all four official solutions; live Run tests completed with structured evidence. | P53: Codex SQA | Q53: 46238 | R53: Not Required
A54: [x] | B54: GRD-005 | C54: Current | D54: Grading & Execution | E54: Assignment 3 official solution | F54: Application dependencies are installed and the target environment is available. | G54: Submit the server-controlled official solution for assignment 3. | H54: All hidden checks pass and score is 100 percent. | I54: Release Gate | J54: Regression | K54: Backend | L54: Yes | M54: Pass | O54: 76 backend tests passed, including all four official solutions; live Run tests completed with structured evidence. | P54: Codex SQA | Q54: 46238 | R54: Not Required
A55: [x] | B55: GRD-006 | C55: Current | D55: Grading & Execution | E55: Assignment 4 official solution | F55: Application dependencies are installed and the target environment is available. | G55: Submit the server-controlled official solution for assignment 4. | H55: All hidden checks pass and score is 100 percent. | I55: Release Gate | J55: Regression | K55: Backend | L55: Yes | M55: Pass | O55: 76 backend tests passed, including all four official solutions; live Run tests completed with structured evidence. | P55: Codex SQA | Q55: 46238 | R55: Not Required
A56: [x] | B56: GRD-007 | C56: Current | D56: Grading & Execution | E56: Incorrect code returns useful evidence | F56: Application dependencies are installed and the target environment is available. | G56: Submit code with incorrect calculated variables. | H56: Program execution and individual calculation failures are reported without expected values. | I56: Release Gate | J56: Functional | K56: Backend/UI | L56: Yes | M56: Pass | O56: 76 backend tests passed, including all four official solutions; live Run tests completed with structured evidence. | P56: Codex SQA | Q56: 46238 | R56: Not Required
A57: [x] | B57: GRD-008 | C57: Current | D57: Grading & Execution | E57: Execution error is structured | F57: Application dependencies are installed and the target environment is available. | G57: Submit code that raises a runtime exception. | H57: Response identifies execution failure safely; UI shows terminal error rather than spinning. | I57: Release Gate | J57: Negative | K57: Backend/UI | L57: Partial | M57: Pass | O57: Structured unsafe-import execution error returned through the remote sandbox; UI execution-error and bounded retry tests pass. | P57: Codex SQA | Q57: 46238 | R57: Not Required | S57: Automated and separate-process smoke evidence.
A58: [x] | B58: GRD-009 | C58: Current | D58: Grading & Execution | E58: Empty code handling | F58: Application dependencies are installed and the target environment is available. | G58: Submit empty code. | H58: Request is rejected with controlled client error and UI remains usable. | I58: P1 | J58: Negative | K58: Backend/UI | L58: Yes | M58: Pass | O58: 76 backend tests passed, including all four official solutions; live Run tests completed with structured evidence. | P58: Codex SQA | Q58: 46238 | R58: Not Required
A59: [x] | B59: GRD-010 | C59: Current | D59: Grading & Execution | E59: Unknown assignment submission | F59: Application dependencies are installed and the target environment is available. | G59: Submit code to assignment 999. | H59: HTTP 404 is returned with no execution attempt. | I59: P1 | J59: Negative API | K59: Backend | L59: Yes | M59: Pass | O59: 76 backend tests passed, including all four official solutions; live Run tests completed with structured evidence. | P59: Codex SQA | Q59: 46238 | R59: Not Required
A60: [x] | B60: GRD-011 | C60: Current | D60: Grading & Execution | E60: Score calculation | F60: Application dependencies are installed and the target environment is available. | G60: Submit combinations of passing and failing variables. | H60: Score and pass/fail counts exactly match structured boolean test outcomes. | I60: Release Gate | J60: Functional | K60: Backend/UI | L60: Yes | M60: Pass | O60: 76 backend tests passed, including all four official solutions; live Run tests completed with structured evidence. | P60: Codex SQA | Q60: 46238 | R60: Not Required
A61: [x] | B61: GRD-012 | C61: Current | D61: Grading & Execution | E61: Terminal stdout displayed | F61: Application dependencies are installed and the target environment is available. | G61: Submit code that prints output. | H61: Captured output appears in Terminal output and remains size-bounded. | I61: P1 | J61: Functional | K61: Backend/UI | L61: Partial | M61: Pass | O61: 76 backend tests passed, including all four official solutions; live Run tests completed with structured evidence. | P61: Codex SQA | Q61: 46238 | R61: Not Required
A62: [x] | B62: GRD-013 | C62: Current | D62: Grading & Execution | E62: Per-test details displayed | F62: Application dependencies are installed and the target environment is available. | G62: Submit an incorrect but executable solution. | H62: Every visible test has a Passed or Needs attention card and safe message. | I62: Release Gate | J62: UI/Integration | K62: Web/Mobile | L62: Yes | M62: Pass | O62: 76 backend tests passed, including all four official solutions; live Run tests completed with structured evidence. | P62: Codex SQA | Q62: 46238 | R62: Not Required
A63: [x] | B63: GRD-014 | C63: Current | D63: Grading & Execution | E63: No hidden expected values in response | F63: Application dependencies are installed and the target environment is available. | G63: Inspect public run, submission, hint, logs, and browser network responses. | H63: Hidden expected values, test implementation, grader config, and official solution are absent. | I63: Release Gate | J63: Security | K63: All | L63: Partial | M63: Pass | O63: 76 backend tests passed, including all four official solutions; live Run tests completed with structured evidence. | P63: Codex SQA | Q63: 46238 | R63: Not Required
A64: [x] | B64: GRD-015 | C64: Current | D64: Grading & Execution | E64: Submission version captured | F64: Application dependencies are installed and the target environment is available. | G64: Submit each assignment and inspect stored/returned assignment_version. | H64: Submission records the exact published version used. | I64: Release Gate | J64: Data Integrity | K64: Backend | L64: Yes | M64: Pass | O64: 76 backend tests passed, including all four official solutions; live Run tests completed with structured evidence. | P64: Codex SQA | Q64: 46238 | R64: Not Required
A65: [x] | B65: GRD-016 | C65: Current | D65: Grading & Execution | E65: Concurrent run protection in UI | F65: Application dependencies are installed and the target environment is available. | G65: Double-click Run tests and press Ctrl+Enter while running. | H65: Only one active request is started and progress returns to idle. | I65: P1 | J65: Resilience | K65: Web/Mobile | L65: Yes | M65: Pass | O65: 76 backend tests passed, including all four official solutions; live Run tests completed with structured evidence. | P65: Codex SQA | Q65: 46238 | R65: Not Required
A66: [x] | B66: GRD-017 | C66: Current | D66: Grading & Execution | E66: Grading request timeout | F66: Application dependencies are installed and the target environment is available. | G66: Force grading past the frontend timeout. | H66: UI stops waiting, displays grading-service recovery state, and permits retry. | I66: P1 | J66: Resilience | K66: Web/Mobile | L66: Yes | M66: Pass | O66: 76 backend tests passed, including all four official solutions; live Run tests completed with structured evidence. | P66: Codex SQA | Q66: 46238 | R66: Not Required
A67: [x] | B67: GRD-018 | C67: Current | D67: Grading & Execution | E67: Retry after backend recovery | F67: Application dependencies are installed and the target environment is available. | G67: Trigger a grading error, restore backend, and select Retry test run. | H67: New grading request completes and replaces the error state. | I67: P1 | J67: Resilience | K67: Web/Mobile | L67: Yes | M67: Pass | O67: 76 backend tests passed, including all four official solutions; live Run tests completed with structured evidence. | P67: Codex SQA | Q67: 46238 | R67: Not Required
A68: [x] | B68: SEC-001 | C68: Current | D68: Sandbox, Security & Privacy | E68: Oversized submission rejected | F68: Application dependencies are installed and the target environment is available. | G68: Submit more than the configured maximum characters. | H68: HTTP 413 is returned before execution. | I68: Release Gate | J68: Security | K68: Backend | L68: Yes | M68: Pass | O68: Backend security/authorization tests passed and live student responses excluded private grader/solution fields. | P68: Codex SQA | Q68: 46238 | R68: Not Required
A69: [x] | B69: SEC-002 | C69: Current | D69: Sandbox, Security & Privacy | E69: Infinite loop terminated | F69: Application dependencies are installed and the target environment is available. | G69: Submit an infinite loop. | H69: Execution is terminated within the configured timeout and backend remains healthy. | I69: Release Gate | J69: Security/Resilience | K69: Backend | L69: Yes | M69: Pass | O69: Backend security/authorization tests passed and live student responses excluded private grader/solution fields. | P69: Codex SQA | Q69: 46238 | R69: Not Required
... A71: [x] | B71: SEC-004 | C71: Current | D71: Sandbox, Security & Privacy | E71: Dangerous import blocked | F71: Application dependencies are installed and the target environment is available. | G71: Submit code importing os or another disallowed capability. | H71: Sandbox rejects the code or prevents unsafe capability use. | I71: Release Gate | J71: Security | K71: Backend | L71: Yes | M71: Pass | O71: Backend security/authorization tests passed and live student responses excluded private grader/solution fields. | P71: Codex SQA | Q71: 46238 | R71: Not Required
A72: [ ] | B72: SEC-005 | C72: Current | D72: Sandbox, Security & Privacy | E72: No host filesystem access | F72: Application dependencies are installed and the target environment is available. | G72: Attempt to read known host paths from production sandbox. | H72: Submission cannot access host or repository files. | I72: Release Gate | J72: Penetration | K72: Docker Sandbox | L72: No | M72: Partial | O72: Dedicated service has no repository/database/OpenAI secrets and file APIs/imports are blocked; live Docker host-path probe remains open. | P72: Codex SQA | Q72: 46238 | R72: Not Required | S72: Do not approve anonymous public execution.
A73: [ ] | B73: SEC-006 | C73: Current | D73: Sandbox, Security & Privacy | E73: No unrestricted network access | F73: Application dependencies are installed and the target environment is available. | G73: Attempt outbound network access from production sandbox. | H73: Network is denied unless explicitly allowed by assignment policy. | I73: Release Gate | J73: Penetration | K73: Docker Sandbox | L73: No | M73: Partial | O73: Socket/network imports are blocked by the assignment AST policy; OS-level egress-denial proof on the live container remains open. | P73: Codex SQA | Q73: 46238 | R73: Not Required | S73: Controlled classroom use only until live penetration evidence exists.
A74: [ ] | B74: SEC-007 | C74: Current | D74: Sandbox, Security & Privacy | E74: Container resource limits | F74: Application dependencies are installed and the target environment is available. | G74: Run CPU-, memory-, process-, and disk-intensive submissions. | H74: Configured resource limits terminate or constrain the workload. | I74: Release Gate | J74: Performance/Security | K74: Docker Sandbox | L74: No | M74: Partial | O74: Linux worker CPU/memory/file/process/output limits are implemented and capacity tests pass; Docker/live stress proof remains open. | P74: Codex SQA | Q74: 46238 | R74: Not Required | S74: Build and stress the deployed image before student distribution.
A75: [ ] | B75: SEC-008 | C75: Current | D75: Sandbox, Security & Privacy | E75: Sandbox temporary cleanup | F75: Application dependencies are installed and the target environment is available. | G75: Run successful, failed, and timed-out submissions; inspect temporary resources. | H75: Containers/workspaces are removed and no student code persists unexpectedly. | I75: P0 | J75: Security | K75: Docker Sandbox | L75: No | M75: Not Run | R75: Not Required
A76: [x] | B76: SEC-009 | C76: Current | D76: Sandbox, Security & Privacy | E76: Docker sandbox invalid response | F76: Application dependencies are installed and the target environment is available. | G76: Force malformed sandbox response. | H76: Backend returns controlled execution error without crashing. | I76: P1 | J76: Negative Integration | K76: Backend | L76: Partial | M76: Pass | O76: Malformed remote responses, authentication failures, and unavailable-service errors return controlled messages without backend crashes. | P76: Codex SQA | Q76: 46238 | R76: Not Required | S76: Remote sandbox negative tests pass.
A77: [x] | B77: SEC-010 | C77: Current | D77: Sandbox, Security & Privacy | E77: Admin endpoint requires configured token | F77: Application dependencies are installed and the target environment is available. | G77: Call /admin/assignments without a token, with an incorrect token, and when admin is unconfigured. | H77: Responses are 401 for incorrect/missing token and controlled 503 when unconfigured. | I77: Release Gate | J77: Security API | K77: Backend | L77: Yes | M77: Pass | O77: Backend security/authorization tests passed and live student responses excluded private grader/solution fields. | P77: Codex SQA | Q77: 46238 | R77: Not Required
A78: [ ] | B78: SEC-011 | C78: Current | D78: Sandbox, Security & Privacy | E78: Instructor token is not OpenAI key | F78: Application dependencies are installed and the target environment is available. | G78: Inspect instructor UI labels/help and submit the admin token. | H78: UI clearly requests ADMIN_API_TOKEN; OpenAI key is never requested from the client. | I78: P0 | J78: Security/UX | K78: Web/Mobile | L78: Partial | M78: Not Run | R78: Not Required
A79: [ ] | B79: SEC-012 | C79: Current | D79: Sandbox, Security & Privacy | E79: Admin token remains server-side/private | F79: Application dependencies are installed and the target environment is available. | G79: Inspect browser storage, logs, screenshots, and repository tracking. | H79: Token is used only for the active admin request flow and is not committed or logged. | I79: Release Gate | J79: Privacy | K79: All | L79: Partial | M79: Not Run | R79: Not Required
A80: [x] | B80: SEC-013 | C80: Current | D80: Sandbox, Security & Privacy | E80: Solution endpoint authorization | F80: Application dependencies are installed and the target environment is available. | G80: Attempt solution reveal without submission, with another assignment's submission, and with stale-version submission. | H80: Solution remains blocked with controlled errors. | I80: Release Gate | J80: Security | K80: Backend | L80: Yes | M80: Pass | O80: Backend security/authorization tests passed and live student responses excluded private grader/solution fields. | P80: Codex SQA | Q80: 46238 | R80: Not Required
A81: [x] | B81: SEC-014 | C81: Current | D81: Sandbox, Security & Privacy | E81: Student assignment payload excludes private fields | F81: Application dependencies are installed and the target environment is available. | G81: Inspect assignment list/detail JSON. | H81: Payload excludes grader_config, misconceptions policy internals where private, reference path, hidden tests, and solution body. | I81: Release Gate | J81: Security API | K81: Backend | L81: Yes | M81: Pass | O81: Backend security/authorization tests passed and live student responses excluded private grader/solution fields. | P81: Codex SQA | Q81: 46238 | R81: Not Required
A82: [ ] | B82: SEC-015 | C82: Current | D82: Sandbox, Security & Privacy | E82: Error responses do not leak stack traces or secrets | F82: Application dependencies are installed and the target environment is available. | G82: Trigger validation, sandbox, database, and tutor failures. | H82: Client receives controlled messages; logs contain no API key or admin token. | I82: Release Gate | J82: Security | K82: Backend | L82: Partial | M82: Partial | O82: Remote sandbox failures redact provider details and secret scans pass; database/tutor failure-log review remains open. | P82: Codex SQA | Q82: 46238 | R82: Not Required | S82: Complete the remaining failure classes before sign-off.
A83: [x] | B83: TUT-001 | C83: Current | D83: Feedback & Tutoring | E83: AI tutoring defaults off | F83: Application dependencies are installed and the target environment is available. | G83: Open every assignment in a clean session. | H83: AI tutoring switch is off. | I83: Release Gate | J83: UI/Configuration | K83: Web/Mobile | L83: Yes | M83: Pass | O83: AI remained off by default; deterministic no-AI execution completed; maintained tutor safety tests passed. | P83: Codex SQA | Q83: 46238 | R83: Not Required
A84: [x] | B84: TUT-002 | C84: Current | D84: Feedback & Tutoring | E84: AI-off grading remains complete | F84: Application dependencies are installed and the target environment is available. | G84: Leave AI off and run incorrect starter code. | H84: Score, terminal output, and test details appear without tutor delay. | I84: Release Gate | J84: Integration | K84: Web/Mobile | L84: Partial | M84: Pass | O84: AI remained off by default; deterministic no-AI execution completed; maintained tutor safety tests passed. | P84: Codex SQA | Q84: 46238 | R84: Not Required
A85: [x] | B85: TUT-003 | C85: Current | D85: Feedback & Tutoring | E85: AI-off request payload | F85: Application dependencies are installed and the target environment is available. | G85: Inspect submission request when toggle is off. | H85: use_ai_tutor is false and backend does not call OpenAI. | I85: P0 | J85: Integration | K85: Web/Backend | L85: Partial | M85: Pass | O85: AI remained off by default; deterministic no-AI execution completed; maintained tutor safety tests passed. | P85: Codex SQA | Q85: 46238 | R85: Not Required
A86: [x] | B86: TUT-004 | C86: Current | D86: Feedback & Tutoring | E86: Built-in tutoring fallback | F86: Application dependencies are installed and the target environment is available. | G86: Enable tutoring while OpenAI is unavailable or unconfigured; submit incorrect code. | H86: Submission completes and displays Built-in tutor hint. | I86: Release Gate | J86: Resilience | K86: Backend/UI | L86: Yes | M86: Pass | O86: AI remained off by default; deterministic no-AI execution completed; maintained tutor safety tests passed. | P86: Codex SQA | Q86: 46238 | R86: Not Required
A87: [x] | B87: TUT-005 | C87: Current | D87: Feedback & Tutoring | E87: OpenAI source label | F87: Application dependencies are installed and an authorized funded OpenAI key is configured. | G87: With a funded authorized test key, enable tutoring and submit incorrect code. | H87: Successful model response displays OpenAI tutor hint. | I87: P1 | J87: External Integration | K87: Backend/UI | L87: Partial | M87: Deferred | O87: AI provider behavior was intentionally excluded from this SQA cycle by project decision. | P87: Codex SQA | Q87: 46238 | R87: Not Required | S87: Current API quota may require this row to be Blocked with evidence.
A88: [x] | B88: TUT-006 | C88: Current | D88: Feedback & Tutoring | E88: Tutor request timeout and no endless spinner | F88: Application dependencies are installed and the target environment is available. | G88: Simulate model timeout. | H88: Backend falls back within the bounded timeout; Run tests stops loading. | I88: Release Gate | J88: Resilience | K88: Backend/UI | L88: Yes | M88: Pass | O88: AI remained off by default; deterministic no-AI execution completed; maintained tutor safety tests passed. | P88: Codex SQA | Q88: 46238 | R88: Not Required
A89: [x] | B89: TUT-007 | C89: Current | D89: Feedback & Tutoring | E89: Tutor input is sanitized | F89: Application dependencies are installed and the target environment is available. | G89: Capture mocked model request. | H89: Input contains student-visible evidence only; no hidden values/tests/config/solution. | I89: Release Gate | J89: Security | K89: Backend | L89: Yes | M89: Pass | O89: AI remained off by default; deterministic no-AI execution completed; maintained tutor safety tests passed. | P89: Codex SQA | Q89: 46238 | R89: Not Required
A90: [x] | B90: TUT-008 | C90: Current | D90: Feedback & Tutoring | E90: Tutor never reveals official solution | F90: Application dependencies are installed and the target environment is available. | G90: Exercise common prompt-injection and answer-request attempts. | H90: Feedback provides diagnosis/questions/hints without replacement solution or hidden evidence. | I90: Release Gate | J90: AI Safety | K90: Backend | L90: Partial | M90: Deferred | O90: AI provider behavior was intentionally excluded from this SQA cycle by project decision. | P90: Codex SQA | Q90: 46238 | R90: Not Required
A91: [x] | B91: TUT-009 | C91: Current | D91: Feedback & Tutoring | E91: Hint level 1 | F91: Application dependencies are installed and the target environment is available. | G91: Request initial tutor feedback. | H91: Response shows level 1 of 4 with an appropriate first-step hint. | I91: P1 | J91: Functional | K91: Backend/UI | L91: Yes | M91: Pass | O91: AI remained off by default; deterministic no-AI execution completed; maintained tutor safety tests passed. | P91: Codex SQA | Q91: 46238 | R91: Not Required
A92: [ ] | B92: TUT-010 | C92: Current | D92: Feedback & Tutoring | E92: Progressive hints levels 2 through 4 | F92: Application dependencies are installed and the target environment is available. | G92: Select Get another hint repeatedly. | H92: Levels increment once, content becomes progressively more specific, and level 4 disables further requests. | I92: P1 | J92: Functional | K92: Backend/UI | L92: Partial | M92: Not Run | R92: Not Required
A93: [x] | B93: TUT-011 | C93: Current | D93: Feedback & Tutoring | E93: Invalid hint levels rejected | F93: Application dependencies are installed and the target environment is available. | G93: Request levels 0 and 5. | H93: HTTP 400 validation error is returned. | I93: P1 | J93: Negative API | K93: Backend | L93: Yes | M93: Pass | O93: AI remained off by default; deterministic no-AI execution completed; maintained tutor safety tests passed. | P93: Codex SQA | Q93: 46238 | R93: Not Required
A94: [x] | B94: TUT-012 | C94: Current | D94: Feedback & Tutoring | E94: Cross-assignment hint request rejected | F94: Application dependencies are installed and the target environment is available. | G94: Use an assignment 2 submission ID for assignment 1 hint endpoint. | H94: HTTP 404 is returned and no hint interaction is stored. | I94: P1 | J94: Security API | K94: Backend | L94: Yes | M94: Pass | O94: AI remained off by default; deterministic no-AI execution completed; maintained tutor safety tests passed. | P94: Codex SQA | Q94: 46238 | R94: Not Required
A95: [ ] | B95: TUT-013 | C95: Current | D95: Feedback & Tutoring | E95: Hint error recovery | F95: Application dependencies are installed and the target environment is available. | G95: Make the hint endpoint unavailable and select Get another hint. | H95: Panel shows a retryable error and preserves the current hint. | I95: P2 | J95: Resilience | K95: Web/Mobile | L95: Partial | M95: Not Run | R95: Not Required
A96: [x] | B96: PRG-001 | C96: Current | D96: Solutions & Learning Progress | E96: Solution initially locked | F96: Application dependencies are installed and the target environment is available. | G96: Open a fresh assignment. | H96: Worked solution is locked until a current-version run/submission exists. | I96: Release Gate | J96: Security/UI | K96: Web/Mobile | L96: Yes | M96: Pass | O96: Flutter progress persistence/state tests and backend submission ownership/version tests passed. | P96: Codex SQA | Q96: 46238 | R96: Not Required
A97: [ ] | B97: PRG-002 | C97: Current | D97: Solutions & Learning Progress | E97: Solution reveals after attempt | F97: Application dependencies are installed and the target environment is available. | G97: Run tests, then select reveal solution and confirm. | H97: Current assignment solution loads from backend and is marked revealed. | I97: P1 | J97: Functional | K97: Backend/UI | L97: Partial | M97: Not Run | R97: Not Required
A98: [x] | B98: PRG-003 | C98: Current | D98: Solutions & Learning Progress | E98: Solution reveal persists | F98: Application dependencies are installed and the target environment is available. | G98: Reveal a solution, leave, and reopen the assignment. | H98: Solution-viewed state and protected solution reload correctly. | I98: P1 | J98: State | K98: Web/Mobile | L98: Yes | M98: Pass | O98: Flutter progress persistence/state tests and backend submission ownership/version tests passed. | P98: Codex SQA | Q98: 46238 | R98: Not Required
A99: [x] | B99: PRG-004 | C99: Current | D99: Solutions & Learning Progress | E99: Stale solution reveal invalidated | F99: Application dependencies are installed and the target environment is available. | G99: Reveal a solution, publish a newer assignment version, and reopen. | H99: Old reveal state clears; student must run the new version before reveal. | I99: Release Gate | J99: Versioning/Security | K99: Backend/UI | L99: Yes | M99: Pass | O99: Flutter progress persistence/state tests and backend submission ownership/version tests passed. | P99: Codex SQA | Q99: 46238 | R99: Not Required
A100: [x] | B100: PRG-005 | C100: Current | D100: Solutions & Learning Progress | E100: Attempt count persists | F100: Application dependencies are installed and the target environment is available. | G100: Run tests multiple times; reload application. | H100: Attempt count remains correct. | I100: P1 | J100: State | K100: Web/Mobile | L100: Yes | M100: Pass | O100: Flutter progress persistence/state tests and backend submission ownership/version tests passed. | P100: Codex SQA | Q100: 46238 | R100: Not Required
A101: [x] | B101: PRG-006 | C101: Current | D101: Solutions & Learning Progress | E101: Latest score persists | F101: Application dependencies are installed and the target environment is available. | G101: Record scores in sequence and reload. | H101: Latest score reflects the most recent graded attempt. | I101: P1 | J101: State | K101: Web/Mobile | L101: Yes | M101: Pass | O101: Flutter progress persistence/state tests and backend submission ownership/version tests passed. | P101: Codex SQA | Q101: 46238 | R101: Not Required
...

Sheet Assignment Matrix
A1: Checked? | B1: Assignment ID | C1: Stable ID | D1: Version | E1: Title | F1: Published | G1: Detail Loads | H1: Starter Compiles | I1: Starter Executes | J1: Official Solution | K1: Public Run | L1: Hidden Grading | M1: Evidence UI | N1: Solution Protection | O1: Hint Policy | P1: Simulation Config | Q1: Last Verified | R1: Evidence | S1: Notes
A2: [x] | B2: 1 | C2: robotics-assignment-1 | D2: 3 | E2: Obstacle Avoidance: Bug Algorithm Scenario 1 | F2: Pass | G2: Pass | H2: Pass | I2: Pass | J2: Pass | K2: Pass | L2: Pass | M2: Pass | N2: Pass | O2: Pass | P2: Pass | Q2: 46238 | R2: 76 backend tests; all official solutions; 32 Flutter tests; live API/browser smoke. | S2: Verify consistent Euclidean/boundary distance and no embedded solution.
A3: [x] | B3: 2 | C3: robotics-assignment-2 | D3: 2 | E3: Obstacle Avoidance: Bug Algorithm Scenario 2 | F3: Pass | G3: Pass | H3: Pass | I3: Pass | J3: Pass | K3: Pass | L3: Pass | M3: Pass | N3: Pass | O3: Pass | P3: Pass | Q3: 46238 | R3: 76 backend tests; all official solutions; 32 Flutter tests; live API/browser smoke. | S3: Verify four expected calculation variables and total path length.
A4: [x] | B4: 3 | C4: robotics-assignment-3 | D4: 3 | E4: Autonomous Robot Navigation in a Dynamic Office Environment | F4: Pass | G4: Pass | H4: Pass | I4: Pass | J4: Pass | K4: Pass | L4: Pass | M4: Pass | N4: Pass | O4: Pass | P4: Pass | Q4: 46238 | R4: 76 backend tests; all official solutions; 32 Flutter tests; live API/browser smoke. | S4: Verify movable obstacle activates the configured half-circle detour.
A5: [x] | B5: 4 | C5: robotics-assignment-4 | D5: 2 | E5: Calculating Safe Trajectory using Vector Field Histogram (VFH) | F5: Pass | G5: Pass | H5: Pass | I5: Pass | J5: Pass | K5: Pass | L5: Pass | M5: Pass | N5: Pass | O5: Pass | P5: Pass | Q5: 46238 | R5: 76 backend tests; all official solutions; 32 Flutter tests; live API/browser smoke. | S5: Verify histogram and optimal-sector calculations.

Sheet Defect Log
A1: Defect ID | B1: Title | C1: Severity | D1: Category | E1: Environment | F1: Steps to Reproduce | G1: Expected | H1: Actual | I1: Status | J1: Owner | K1: Found Date | L1: Fix Version / Commit | M1: Retest Result | N1: Retest Date | O1: Evidence Link / Path | P1: Notes
P2: Enter the first real v4 defect here. No new product defect was found in the 2026-08-04 SQA run.

Sheet Release Sign-off
A1: Release Sign-off
A2: Sign only after the Release Dashboard is complete, all Release Gate checks are resolved, and defects have retest evidence.
A4: Gate | B4: Required Evidence | C4: Status | D4: Owner | E4: Date | F4: Comments
A5: Automated backend tests | B5: pytest output | C5: Pass | D5: Codex SQA | E5: 46238 | F5: 76 pytest checks passed; pip check and compileall passed.
A6: Flutter analysis/tests/build | B6: Command output | C6: Pass | D6: Codex SQA | E6: 46238 | F6: Analyzer clean; 33 tests passed; release web build passed.
A7: All published assignments validate | B7: Validation report | C7: Pass | D7: Codex SQA | E7: 46238 | F7: Four published versioned assignments passed repository/grader validation.
A8: All official solutions pass | B8: Per-assignment evidence | C8: Pass | D8: Codex SQA | E8: 46238 | F8: Assignments 1-4 official solutions passed modular graders.
A9: Desktop/mobile critical path | B9: Screenshots or test record | C9: Partial | D9: Codex SQA | E9: 46238 | F9: Live Chrome desktop passed; responsive widget tests passed; independent device/accessibility audit remains.
A10: Sandbox security checks | B10: Timeout/import/output/resource evidence | C10: Partial | D10: Codex SQA | E10: 46238 | F10: Dedicated authenticated sandbox service passes local automated and two-process checks; Render image build and live penetration/resource evidence remain open.
A11: Instructor workflow | B11: Create/edit/validate/publish evidence | C11: Partial | D11: Codex SQA | E11: 46238 | F11: Live studio/accounts read paths passed; mutation paths passed automated tests but were not executed against production data.
A12: Authentication and account management | B12: Login, role, session, password, account, audit, and email evidence | C12: Pass | D12: Codex SQA | E12: 46238 | F12: Student/instructor/invalid/session/logout/role/admin checks passed; self-service email reset is out of scope.
A13: Secrets and source diff review | B13: Git evidence | C13: Pass | D13: Codex SQA | E13: 46238 | F13: No tracked environments or real credentials; one synthetic migration-test URL matched the scanner.
A14: Defect retest complete | B14: Defect IDs and retest evidence | C14: N/A | D14: Codex SQA | E14: 46238 | F14: No new product defect was found in this SQA cycle.
A16: Approvals
A17: Role | B17: Name | C17: Decision | D17: Date | E17: Signature / Evidence | F17: Comments
A18: SQA Lead | C18: Pending
A19: Development Lead | C19: Pending
A20: Instructor / Curriculum Owner | C20: Pending
A21: Security / Platform Reviewer | C21: Pending
A22: Product / Research Lead | C22: Pending

Sheet Runbook
A1: SQA Execution Runbook
A2: Run commands from the repository root unless a different working directory is shown. Never put API keys or instructor tokens into the workbook.
A4: Section | B4: Purpose | C4: Command / Procedure | D4: Expected Result
A5: Install | B5: Create Python environment | C5: python -m venv venv | D5: venv directory is created
A6: Install | B6: Install backend packages | C6: .\venv\Scripts\python.exe -m pip install -r .\backend\requirements.txt | D6: Installation succeeds
A7: Install | B7: Install Flutter packages | C7: Set-Location .\frontend; flutter pub get; Set-Location .. | D7: Dependency resolution succeeds
A8: Run | B8: Start backend (Terminal 1) | C8: .\venv\Scripts\python.exe .\backend\run.py | D8: Backend remains running at http://127.0.0.1:5000
A9: Run | B9: Start frontend (Terminal 2) | C9: Set-Location .\frontend; flutter run -d chrome --dart-define=API_BASE_URL=http://127.0.0.1:5000 | D9: Chrome opens the catalog
A10: Backend QA | B10: Run backend tests | C10: Set-Location .\backend; ..\venv\Scripts\python.exe -m pytest -q | D10: All maintained tests pass
A11: Backend QA | B11: Check package integrity | C11: Set-Location .\backend; ..\venv\Scripts\python.exe -m pip check | D11: No broken requirements
A12: Backend QA | B12: Compile Python modules | C12: Set-Location .\backend; ..\venv\Scripts\python.exe -m compileall -q . | D12: No compilation errors
A13: Frontend QA | B13: Static analysis | C13: Set-Location .\frontend; flutter analyze | D13: No issues found
A14: Frontend QA | B14: Widget/state tests | C14: Set-Location .\frontend; flutter test | D14: All tests pass
A15: Frontend QA | B15: Release web build | C15: Set-Location .\frontend; flutter build web --dart-define=API_BASE_URL=http://127.0.0.1:5000 | D15: Build succeeds in .flutter_build\web
... A43: Production | B43: Promote an approved immutable release | C43: .\scripts\promote-release.ps1 -ReleaseTag v4.0.0 -ConfirmProduction | D43: After explicit approval, the exact staging SHA and tag reach production atomically
A44: Severity and Status Definitions
A45: Value | B45: Meaning | C45: Release Effect | D45: Required Action
A46: Critical | B46: Security compromise, data loss, unsafe execution, or platform unavailable | C46: Immediate stop | D46: Fix before any release
A47: High | B47: Critical workflow incorrect or inaccessible with no acceptable workaround | C47: Blocks release | D47: Fix and retest
A48: Medium | B48: Important behavior incorrect with limited workaround | C48: Risk decision required | D48: Plan fix and document
A49: Low | B49: Minor presentation, usability, or documentation issue | C49: Usually does not block | D49: Track and prioritize
A50: Not Run | B50: Test has not been executed | C50: Release incomplete for current scope | D50: Execute or justify N/A
A51: Pass | B51: Actual result matches expected result | C51: Contributes to readiness | D51: Attach evidence
A52: Fail | B52: Actual result does not match expected result | C52: Release Gate failures block | D52: Create defect and fix
A53: Blocked | B53: External/environment condition prevents execution | C53: Release Gate blocks unless explicitly waived | D53: Document blocker and owner
A54: N/A | B54: Test does not apply to this release/environment | C54: Excluded with justification | D54: Explain in Notes
A55: Deferred | B55: Planned future capability not in current release | C55: Excluded from current completion | D55: Review during planning

Sheet Lists
A1: Status | B1: Priority | C1: Automation | D1: Check | E1: Retest | F1: Defect Status | G1: Severity | H1: Decision | I1: Scope | J1: Test Type
A2: Not Run | B2: Release Gate | C2: Yes | D2: [ ] | E2: Not Required | F2: Open | G2: Critical | H2: Pending | I2: Current | J2: Automated
A3: Pass | B3: P0 | C3: Partial | D3: [x] | E3: Pass | F3: In Progress | G3: High | H3: Approved | I3: Future | J3: API
A4: Fail | B4: P1 | C4: No | E4: Fail | F4: Fixed | G4: Medium | H4: Rejected | J4: Integration
A5: Blocked | B5: P2 | E5: Blocked | F5: Closed | G5: Low | H5: Conditional | J5: Manual
A6: N/A | E6: Not Run | F6: Deferred | J6: Security
A7: Deferred | J7: Accessibility
J8: Performance
J9: Content Review
J10: Process
