Workbook
Name AutomationOptions: Lists!$C$2:$C$4
Name CheckOptions: Lists!$D$2:$D$3
Name DecisionOptions: Lists!$H$2:$H$5
Name DefectStatusOptions: Lists!$F$2:$F$6
Name PriorityOptions: Lists!$B$2:$B$5
Name RetestOptions: Lists!$E$2:$E$6
Name ScopeOptions: Lists!$I$2:$I$3
Name SeverityOptions: Lists!$G$2:$G$5
Name StatusOptions: Lists!$A$2:$A$7
Name TestTypeOptions: Lists!$J$2:$J$10

Sheet V4 SQA Report
A1: Robotics Programming Lab - v4 SQA Verification Report
A3: Release | B3: v4 Local Classroom-Ready Candidate | C3: Branch | D3: staging main - local only | E3: Test Date | F3: 46239
A4: Commit | B4: Working tree; not pushed | C4: Frontend | D4: http://localhost:8080 | E4: Backend | F4: http://127.0.0.1:5000
A5: Scope | B5: Local-only classroom-readiness verification. No live repository push or production deployment was performed. Render restart, production PostgreSQL rollback, and another physical computer/network remain external live gates.
A7: Total Checks | B7: 60 | C7: Passed | D7: 47 | E7: Non-Pass / Open | F7: 13
A8: Pass Rate | B8: 0.78333333 | C8: Blocked | D8: 0 | E8: Not Run / Deferred | F8: 6
A9: Decision | B9: LOCAL GATE PASSED - LIVE EXTERNAL GATES OPEN
A12: Check ID | B12: Area / Feature | C12: Result | D12: Environment | E12: Evidence | F12: Limitation / Next Step
A13: V4-SQA-001 | B13: Source and tracked-secret audit | C13: Pass | D13: Local repository | E13: Clean tracked source; venv ignored; one synthetic migration URL scanner match. | F13: No real credential detected in tracked files.
A14: V4-SQA-002 | B14: 87 backend tests passed in the final local gate. | C14: Pass | D14: Local | E14: 87 pytest checks passed, including classroom error paths, restart persistence, manual accounts, and rollback rehearsal. | F14: Includes auth, assignment, grader, migration, rate-limit, remote-sandbox, and sandbox-service tests.
A15: V4-SQA-003 | B15: Python dependency integrity | C15: Pass | D15: Local | E15: pip check: no broken requirements. | F15: Fresh Python 3.11 venv created from backend requirements.
A16: V4-SQA-004 | B16: Python compilation | C16: Pass | D16: Local | E16: compileall completed without error. | F16: Backend modules compile.
A17: V4-SQA-005 | B17: Flutter static analysis | C17: Pass | D17: Local | E17: flutter analyze: no issues found. | F17: Current v4 source.
A18: V4-SQA-006 | B18: Flutter automated tests | C18: Pass | D18: Local | E18: 33 Flutter tests passed, including 390x844 layout and Ctrl+Enter keyboard execution. | F18: Includes login entry, session policy, responsive UI, progress, execution state, and secure-grader loading.
A19: V4-SQA-007 | B19: Flutter release web build | C19: Pass | D19: Local | E19: Production web build completed in .flutter_build/web. | F19: Built with the live Render API URL.
A20: V4-SQA-008 | B20: Hosted CI and deployment | C20: Pass | D20: GitHub/Vercel | E20: Latest v4 verification and Vercel deployment succeeded. | F20: Existing hosted baseline passed; new classroom-security working tree is not yet pushed or deployed.
A21: V4-SQA-009 | B21: Live health and exact-origin CORS | C21: Pass | D21: Render | E21: Health API 4.0.0; exact Vercel origin allowed. | F21: Live API checks passed.
A22: V4-SQA-010 | B22: Login-first shared URL | C22: Pass | D22: Live Chrome | E22: Public root displayed login despite prior saved session. | F22: Demo credentials were not shown on the page.
A23: V4-SQA-011 | B23: Invalid login handling | C23: Pass | D23: Live Chrome/API | E23: Invalid credential returned a clear error and remained on login. | F23: No endless spinner or crash.
... A72: V4-SQA-060 | B72: Manual Python answers for Assignments 1-4 | C72: Pass | D72: Local API/automated | E72: Four private-repository answer files independently scored 100%; classroom tests load these files as their regression source. | F72: The application and student APIs do not serve this folder or hidden tests.

Sheet Release Dashboard
A1: Robotics Programming Lab - SQA Release Dashboard
A2: Complete the Master Checklist for every release. Attach evidence, link defects, retest fixes, and obtain sign-off before publishing.
A4: Release / Version | B4: v4 Local Classroom-Ready Candidate | C4: Branch | D4: staging main - local only | E4: Commit | F4: Working tree - not pushed | G4: Test Date | H4: 46239
A5: SQA Owner | B5: Codex SQA | C5: Environment | D5: Local full stack + browser | E5: Backend URL | F5: http://127.0.0.1:5000 | G5: Frontend Target | H5: Chrome / Flutter Web / 390x844 test
A6: Scope Notes | B6: All executable local gates passed. Actual Render/Neon restart, production PostgreSQL rollback/restore, second-device/network test, and full accessibility audit remain open before live classroom release.
A8: Release Readiness
A9: Metric | B9: Value | C9: Metric | D9: Value | E9: Metric | F9: Value | G9: Metric | H9: Value
A10: Total Checks | B10: =COUNTA('Master Checklist'!B2:B204) | C10: Current Scope | D10: =COUNTIF('Master Checklist'!C2:C204,"Current") | E10: Passed | F10: =COUNTIF('Master Checklist'!M2:M204,"Pass") | G10: Failed | H10: =COUNTIF('Master Checklist'!M2:M204,"Fail")
A11: Blocked | B11: =COUNTIF('Master Checklist'!M2:M204,"Blocked") | C11: Not Run | D11: =COUNTIF('Master Checklist'!M2:M204,"Not Run") | E11: Deferred | F11: =COUNTIF('Master Checklist'!M2:M204,"Deferred") | G11: N/A | H11: =COUNTIF('Master Checklist'!M2:M204,"N/A")
A12: Completion | B12: =IF(D10=0,0,(F10+H10+B11+H11)/D10) | C12: Pass Rate | D12: =IF((F10+H10)=0,0,F10/(F10+H10)) | E12: Release Gate Fail/Blocked | F12: =COUNTIFS('Master Checklist'!I2:I204,"Release Gate",'Master Checklist'!M2:M204,"Fail")+COUNTIFS('Master Checklist'!I2:I204,"Release Gate",'Master Checklist'!M2:M204,"Blocked") | G12: Decision | H12: =IF(F12>0,"DO NOT RELEASE",IF(D11>0,"TESTING INCOMPLETE","READY FOR SIGN-OFF"))
A14: Category Coverage
A15: Category | B15: Total | C15: Pass | D15: Fail | E15: Blocked | F15: Not Run | G15: N/A | H15: Progress
A16: Environment & Startup | B16: =COUNTIF('Master Checklist'!D2:D204,A16) | C16: =COUNTIFS('Master Checklist'!D2:D204,A16,'Master Checklist'!M2:M204,"Pass") | D16: =COUNTIFS('Master Checklist'!D2:D204,A16,'Master Checklist'!M2:M204,"Fail") | E16: =COUNTIFS('Master Checklist'!D2:D204,A16,'Master Checklist'!M2:M204,"Blocked") | F16: =COUNTIFS('Master Checklist'!D2:D204,A16,'Master Checklist'!M2:M204,"Not Run") | G16: =COUNTIFS('Master Checklist'!D2:D204,A16,'Master Checklist'!M2:M204,"N/A") | H16: =IF(B16=0,0,(C16+D16+E16+G16)/B16)
A17: Health & Public API | B17: =COUNTIF('Master Checklist'!D2:D204,A17) | C17: =COUNTIFS('Master Checklist'!D2:D204,A17,'Master Checklist'!M2:M204,"Pass") | D17: =COUNTIFS('Master Checklist'!D2:D204,A17,'Master Checklist'!M2:M204,"Fail") | E17: =COUNTIFS('Master Checklist'!D2:D204,A17,'Master Checklist'!M2:M204,"Blocked") | F17: =COUNTIFS('Master Checklist'!D2:D204,A17,'Master Checklist'!M2:M204,"Not Run") | G17: =COUNTIFS('Master Checklist'!D2:D204,A17,'Master Checklist'!M2:M204,"N/A") | H17: =IF(B17=0,0,(C17+D17+E17+G17)/B17)
A18: Student Catalog & Navigation | B18: =COUNTIF('Master Checklist'!D2:D204,A18) | C18: =COUNTIFS('Master Checklist'!D2:D204,A18,'Master Checklist'!M2:M204,"Pass") | D18: =COUNTIFS('Master Checklist'!D2:D204,A18,'Master Checklist'!M2:M204,"Fail") | E18: =COUNTIFS('Master Checklist'!D2:D204,A18,'Master Checklist'!M2:M204,"Blocked") | F18: =COUNTIFS('Master Checklist'!D2:D204,A18,'Master Checklist'!M2:M204,"Not Run") | G18: =COUNTIFS('Master Checklist'!D2:D204,A18,'Master Checklist'!M2:M204,"N/A") | H18: =IF(B18=0,0,(C18+D18+E18+G18)/B18)
A19: Assignment Workspace & Editor | B19: =COUNTIF('Master Checklist'!D2:D204,A19) | C19: =COUNTIFS('Master Checklist'!D2:D204,A19,'Master Checklist'!M2:M204,"Pass") | D19: =COUNTIFS('Master Checklist'!D2:D204,A19,'Master Checklist'!M2:M204,"Fail") | E19: =COUNTIFS('Master Checklist'!D2:D204,A19,'Master Checklist'!M2:M204,"Blocked") | F19: =COUNTIFS('Master Checklist'!D2:D204,A19,'Master Checklist'!M2:M204,"Not Run") | G19: =COUNTIFS('Master Checklist'!D2:D204,A19,'Master Checklist'!M2:M204,"N/A") | H19: =IF(B19=0,0,(C19+D19+E19+G19)/B19)
A20: Grading & Execution | B20: =COUNTIF('Master Checklist'!D2:D204,A20) | C20: =COUNTIFS('Master Checklist'!D2:D204,A20,'Master Checklist'!M2:M204,"Pass") | D20: =COUNTIFS('Master Checklist'!D2:D204,A20,'Master Checklist'!M2:M204,"Fail") | E20: =COUNTIFS('Master Checklist'!D2:D204,A20,'Master Checklist'!M2:M204,"Blocked") | F20: =COUNTIFS('Master Checklist'!D2:D204,A20,'Master Checklist'!M2:M204,"Not Run") | G20: =COUNTIFS('Master Checklist'!D2:D204,A20,'Master Checklist'!M2:M204,"N/A") | H20: =IF(B20=0,0,(C20+D20+E20+G20)/B20)
A21: Sandbox, Security & Privacy | B21: =COUNTIF('Master Checklist'!D2:D204,A21) | C21: =COUNTIFS('Master Checklist'!D2:D204,A21,'Master Checklist'!M2:M204,"Pass") | D21: =COUNTIFS('Master Checklist'!D2:D204,A21,'Master Checklist'!M2:M204,"Fail") | E21: =COUNTIFS('Master Checklist'!D2:D204,A21,'Master Checklist'!M2:M204,"Blocked") | F21: =COUNTIFS('Master Checklist'!D2:D204,A21,'Master Checklist'!M2:M204,"Not Run") | G21: =COUNTIFS('Master Checklist'!D2:D204,A21,'Master Checklist'!M2:M204,"N/A") | H21: =IF(B21=0,0,(C21+D21+E21+G21)/B21)
A22: Feedback & Tutoring | B22: =COUNTIF('Master Checklist'!D2:D204,A22) | C22: =COUNTIFS('Master Checklist'!D2:D204,A22,'Master Checklist'!M2:M204,"Pass") | D22: =COUNTIFS('Master Checklist'!D2:D204,A22,'Master Checklist'!M2:M204,"Fail") | E22: =COUNTIFS('Master Checklist'!D2:D204,A22,'Master Checklist'!M2:M204,"Blocked") | F22: =COUNTIFS('Master Checklist'!D2:D204,A22,'Master Checklist'!M2:M204,"Not Run") | G22: =COUNTIFS('Master Checklist'!D2:D204,A22,'Master Checklist'!M2:M204,"N/A") | H22: =IF(B22=0,0,(C22+D22+E22+G22)/B22)
A23: Solutions & Learning Progress | B23: =COUNTIF('Master Checklist'!D2:D204,A23) | C23: =COUNTIFS('Master Checklist'!D2:D204,A23,'Master Checklist'!M2:M204,"Pass") | D23: =COUNTIFS('Master Checklist'!D2:D204,A23,'Master Checklist'!M2:M204,"Fail") | E23: =COUNTIFS('Master Checklist'!D2:D204,A23,'Master Checklist'!M2:M204,"Blocked") | F23: =COUNTIFS('Master Checklist'!D2:D204,A23,'Master Checklist'!M2:M204,"Not Run") | G23: =COUNTIFS('Master Checklist'!D2:D204,A23,'Master Checklist'!M2:M204,"N/A") | H23: =IF(B23=0,0,(C23+D23+E23+G23)/B23)
A24: Instructor Assignment Studio | B24: =COUNTIF('Master Checklist'!D2:D204,A24) | C24: =COUNTIFS('Master Checklist'!D2:D204,A24,'Master Checklist'!M2:M204,"Pass") | D24: =COUNTIFS('Master Checklist'!D2:D204,A24,'Master Checklist'!M2:M204,"Fail") | E24: =COUNTIFS('Master Checklist'!D2:D204,A24,'Master Checklist'!M2:M204,"Blocked") | F24: =COUNTIFS('Master Checklist'!D2:D204,A24,'Master Checklist'!M2:M204,"Not Run") | G24: =COUNTIFS('Master Checklist'!D2:D204,A24,'Master Checklist'!M2:M204,"N/A") | H24: =IF(B24=0,0,(C24+D24+E24+G24)/B24)
A25: Authentication & Account Management | B25: =COUNTIF('Master Checklist'!D2:D204,A25) | C25: =COUNTIFS('Master Checklist'!D2:D204,A25,'Master Checklist'!M2:M204,"Pass") | D25: =COUNTIFS('Master Checklist'!D2:D204,A25,'Master Checklist'!M2:M204,"Fail") | E25: =COUNTIFS('Master Checklist'!D2:D204,A25,'Master Checklist'!M2:M204,"Blocked") | F25: =COUNTIFS('Master Checklist'!D2:D204,A25,'Master Checklist'!M2:M204,"Not Run") | G25: =COUNTIFS('Master Checklist'!D2:D204,A25,'Master Checklist'!M2:M204,"N/A") | H25: =IF(B25=0,0,(C25+D25+E25+G25)/B25)
A26: Assignment Content & Pedagogy | B26: =COUNTIF('Master Checklist'!D2:D204,A26) | C26: =COUNTIFS('Master Checklist'!D2:D204,A26,'Master Checklist'!M2:M204,"Pass") | D26: =COUNTIFS('Master Checklist'!D2:D204,A26,'Master Checklist'!M2:M204,"Fail") | E26: =COUNTIFS('Master Checklist'!D2:D204,A26,'Master Checklist'!M2:M204,"Blocked") | F26: =COUNTIFS('Master Checklist'!D2:D204,A26,'Master Checklist'!M2:M204,"Not Run") | G26: =COUNTIFS('Master Checklist'!D2:D204,A26,'Master Checklist'!M2:M204,"N/A") | H26: =IF(B26=0,0,(C26+D26+E26+G26)/B26)
A27: Responsive, Accessibility & Usability | B27: =COUNTIF('Master Checklist'!D2:D204,A27) | C27: =COUNTIFS('Master Checklist'!D2:D204,A27,'Master Checklist'!M2:M204,"Pass") | D27: =COUNTIFS('Master Checklist'!D2:D204,A27,'Master Checklist'!M2:M204,"Fail") | E27: =COUNTIFS('Master Checklist'!D2:D204,A27,'Master Checklist'!M2:M204,"Blocked") | F27: =COUNTIFS('Master Checklist'!D2:D204,A27,'Master Checklist'!M2:M204,"Not Run") | G27: =COUNTIFS('Master Checklist'!D2:D204,A27,'Master Checklist'!M2:M204,"N/A") | H27: =IF(B27=0,0,(C27+D27+E27+G27)/B27)
A28: Data, Infrastructure & Deployment | B28: =COUNTIF('Master Checklist'!D2:D204,A28) | C28: =COUNTIFS('Master Checklist'!D2:D204,A28,'Master Checklist'!M2:M204,"Pass") | D28: =COUNTIFS('Master Checklist'!D2:D204,A28,'Master Checklist'!M2:M204,"Fail") | E28: =COUNTIFS('Master Checklist'!D2:D204,A28,'Master Checklist'!M2:M204,"Blocked") | F28: =COUNTIFS('Master Checklist'!D2:D204,A28,'Master Checklist'!M2:M204,"Not Run") | G28: =COUNTIFS('Master Checklist'!D2:D204,A28,'Master Checklist'!M2:M204,"N/A") | H28: =IF(B28=0,0,(C28+D28+E28+G28)/B28)
A29: Automated Quality & Release | B29: =COUNTIF('Master Checklist'!D2:D204,A29) | C29: =COUNTIFS('Master Checklist'!D2:D204,A29,'Master Checklist'!M2:M204,"Pass") | D29: =COUNTIFS('Master Checklist'!D2:D204,A29,'Master Checklist'!M2:M204,"Fail") | E29: =COUNTIFS('Master Checklist'!D2:D204,A29,'Master Checklist'!M2:M204,"Blocked") | F29: =COUNTIFS('Master Checklist'!D2:D204,A29,'Master Checklist'!M2:M204,"Not Run") | G29: =COUNTIFS('Master Checklist'!D2:D204,A29,'Master Checklist'!M2:M204,"N/A") | H29: =IF(B29=0,0,(C29+D29+E29+G29)/B29)
A32: Open product/architecture plan

Sheet Master Checklist
A1: Checked? | B1: Check ID | C1: Scope | D1: Category | E1: Feature / Requirement | F1: Preconditions | G1: Test Steps | H1: Expected Result | I1: Priority | J1: Test Type | K1: Platform | L1: Automated? | M1: Status | N1: Defect ID | O1: Actual Result / Evidence | P1: Tester | Q1: Test Date | R1: Retest Status | S1: Notes
A2: [x] | B2: ENV-001 | C2: Current | D2: Environment & Startup | E2: Repository clone contains required source and configuration files | F2: Application dependencies are installed and the target environment is available. | G2: Clone the repository; verify backend, frontend, assignments, course_materials, Dockerfiles, Compose, README, and plan artifacts are present. | H2: Required project structure is complete and no required imported source file is missing. | I2: Release Gate | J2: Inspection | K2: Repository | L2: Partial | M2: Pass | O2: Fresh v4 local setup/install plus Flutter analyzer, 33 tests, and release web build passed on 2026-08-04. | P2: Codex SQA | Q2: 46238 | R2: Not Required
A3: [x] | B3: ENV-002 | C3: Current | D3: Environment & Startup | E3: Secrets are not committed | F3: Application dependencies are installed and the target environment is available. | G3: Run Git secret and tracked-file checks; inspect .gitignore and tracked files for .env, API keys, admin tokens, databases, and credentials. | H3: No secret, backend/.env, database, or credential value is tracked. | I3: Release Gate | J3: Security | K3: Repository | L3: Partial | M3: Pass | O3: Fresh v4 local setup/install plus Flutter analyzer, 33 tests, and release web build passed on 2026-08-04. | P3: Codex SQA | Q3: 46238 | R3: Not Required
A4: [x] | B4: ENV-003 | C4: Current | D4: Environment & Startup | E4: Python virtual environment can be created | F4: Application dependencies are installed and the target environment is available. | G4: Run python -m venv venv in a clean checkout. | H4: Virtual environment is created without errors. | I4: P1 | J4: Installation | K4: Windows | L4: No | M4: Pass | O4: Fresh v4 local setup/install plus Flutter analyzer, 33 tests, and release web build passed on 2026-08-04. | P4: Codex SQA | Q4: 46238 | R4: Not Required
A5: [x] | B5: ENV-004 | C5: Current | D5: Environment & Startup | E5: Backend dependencies install | F5: Application dependencies are installed and the target environment is available. | G5: Run .\venv\Scripts\python.exe -m pip install -r .\backend\requirements.txt. | H5: All required packages install successfully. | I5: Release Gate | J5: Installation | K5: Windows | L5: No | M5: Pass | O5: Fresh v4 local setup/install plus Flutter analyzer, 33 tests, and release web build passed on 2026-08-04. | P5: Codex SQA | Q5: 46238 | R5: Not Required
A6: [x] | B6: ENV-005 | C6: Current | D6: Environment & Startup | E6: Python dependency integrity | F6: Application dependencies are installed and the target environment is available. | G6: Run .\venv\Scripts\python.exe -m pip check. | H6: Command reports no broken requirements. | I6: Release Gate | J6: Automated | K6: Backend | L6: Yes | M6: Pass | O6: Fresh v4 local setup/install plus Flutter analyzer, 33 tests, and release web build passed on 2026-08-04. | P6: Codex SQA | Q6: 46238 | R6: Not Required
A7: [x] | B7: ENV-006 | C7: Current | D7: Environment & Startup | E7: Flutter dependencies resolve | F7: Application dependencies are installed and the target environment is available. | G7: From frontend run flutter pub get. | H7: Flutter resolves dependencies without errors. | I7: Release Gate | J7: Installation | K7: Flutter | L7: No | M7: Pass | O7: Fresh v4 local setup/install plus Flutter analyzer, 33 tests, and release web build passed on 2026-08-04. | P7: Codex SQA | Q7: 46238 | R7: Not Required
A8: [ ] | B8: ENV-007 | C8: Current | D8: Environment & Startup | E8: Backend starts locally | F8: Application dependencies are installed and the target environment is available. | G8: Run .\venv\Scripts\python.exe .\backend\run.py and observe startup. | H8: FastAPI starts on the configured host/port and remains stable. | I8: Release Gate | J8: Smoke | K8: Backend | L8: No | M8: Not Run | R8: Not Required
A9: [ ] | B9: ENV-008 | C9: Current | D9: Environment & Startup | E9: Frontend starts in Chrome | F9: Application dependencies are installed and the target environment is available. | G9: Keep backend running; from frontend run flutter run -d chrome --dart-define=API_BASE_URL=http://127.0.0.1:5000. | H9: Chrome opens the application and the catalog loads. | I9: Release Gate | J9: Smoke | K9: Web | L9: No | M9: Not Run | R9: Not Required
A10: [x] | B10: ENV-009 | C10: Current | D10: Environment & Startup | E10: OneDrive-safe Flutter build output | F10: Application dependencies are installed and the target environment is available. | G10: Build or run from the OneDrive checkout using the configured .flutter_build path. | H10: Flutter creates assets without directory deletion or shader write failures. | I10: P1 | J10: Regression | K10: Windows/Web | L10: Partial | M10: Pass | O10: Fresh v4 local setup/install plus Flutter analyzer, 33 tests, and release web build passed on 2026-08-04. | P10: Codex SQA | Q10: 46238 | R10: Not Required
A11: [x] | B11: ENV-010 | C11: Current | D11: Environment & Startup | E11: Backend URL is configurable | F11: Application dependencies are installed and the target environment is available. | G11: Build/run with a nondefault API_BASE_URL and inspect requests. | H11: Frontend sends requests to the supplied URL, including image URLs and Monaco configuration. | I11: P1 | J11: Configuration | K11: Flutter | L11: Partial | M11: Pass | O11: Fresh v4 local setup/install plus Flutter analyzer, 33 tests, and release web build passed on 2026-08-04. | P11: Codex SQA | Q11: 46238 | R11: Not Required
A12: [ ] | B12: ENV-011 | C12: Current | D12: Environment & Startup | E12: Backend environment file loads | F12: Application dependencies are installed and the target environment is available. | G12: Place nonsecret test configuration in backend/.env; restart backend; inspect /health and relevant behavior. | H12: Settings load from backend/.env while the file remains ignored. | I12: P1 | J12: Configuration | K12: Backend | L12: Partial | M12: Not Run | R12: Not Required
A13: [x] | B13: API-001 | C13: Current | D13: Health & Public API | E13: Health endpoint responds | F13: Application dependencies are installed and the target environment is available. | G13: GET /health. | H13: HTTP 200 returns status ok, API version, database type, and sandbox type. | I13: Release Gate | J13: API | K13: Backend | L13: Yes | M13: Pass | O13: 76 backend tests passed; live API health/auth/CORS/assignment/image checks passed 13/13. | P13: Codex SQA | Q13: 46238 | R13: Not Required
A14: [x] | B14: API-002 | C14: Current | D14: Health & Public API | E14: OpenAPI documentation loads | F14: Application dependencies are installed and the target environment is available. | G14: Open /docs. | H14: Interactive FastAPI documentation loads and lists supported public/admin endpoints. | I14: P1 | J14: API | K14: Backend | L14: No | M14: N/A | O14: Intentionally disabled or unnecessary for the controlled v4 professor demo. | P14: Codex SQA | Q14: 46238 | R14: Not Required | S14: Preserved for a future broader study release where applicable.
A15: [x] | B15: API-003 | C15: Current | D15: Health & Public API | E15: Assignment list endpoint | F15: Application dependencies are installed and the target environment is available. | G15: GET /assignments and GET /assignments/. | H15: HTTP 200 returns four published assignments in numeric order. | I15: Release Gate | J15: API | K15: Backend | L15: Yes | M15: Pass | O15: 76 backend tests passed; live API health/auth/CORS/assignment/image checks passed 13/13. | P15: Codex SQA | Q15: 46238 | R15: Not Required
A16: [x] | B16: API-004 | C16: Current | D16: Health & Public API | E16: Assignment detail endpoint | F16: Application dependencies are installed and the target environment is available. | G16: GET /assignments/{id} for IDs 1 through 4. | H16: Each response contains student-visible assignment data and correct stable ID/version. | I16: Release Gate | J16: API | K16: Backend | L16: Yes | M16: Pass | O16: 76 backend tests passed; live API health/auth/CORS/assignment/image checks passed 13/13. | P16: Codex SQA | Q16: 46238 | R16: Not Required
A17: [x] | B17: API-005 | C17: Current | D17: Health & Public API | E17: Unknown assignment returns JSON 404 | F17: Application dependencies are installed and the target environment is available. | G17: GET /assignments/999. | H17: HTTP 404 returns the documented JSON error. | I17: P1 | J17: Negative API | K17: Backend | L17: Yes | M17: Pass | O17: 76 backend tests passed; live API health/auth/CORS/assignment/image checks passed 13/13. | P17: Codex SQA | Q17: 46238 | R17: Not Required
A18: [x] | B18: API-006 | C18: Current | D18: Health & Public API | E18: Assignment image endpoint | F18: Application dependencies are installed and the target environment is available. | G18: GET /images/1 and inspect content type/signature. | H18: HTTP 200 returns the expected PNG image. | I18: P1 | J18: API | K18: Backend | L18: Yes | M18: Pass | O18: 76 backend tests passed; live API health/auth/CORS/assignment/image checks passed 13/13. | P18: Codex SQA | Q18: 46238 | R18: Not Required
A19: [x] | B19: API-007 | C19: Current | D19: Health & Public API | E19: Unknown image returns JSON 404 | F19: Application dependencies are installed and the target environment is available. | G19: GET /images/999. | H19: HTTP 404 returns the documented JSON error. | I19: P2 | J19: Negative API | K19: Backend | L19: Yes | M19: Pass | O19: 76 backend tests passed; live API health/auth/CORS/assignment/image checks passed 13/13. | P19: Codex SQA | Q19: 46238 | R19: Not Required
A20: [x] | B20: API-008 | C20: Current | D20: Health & Public API | E20: Legacy grading compatibility | F20: Application dependencies are installed and the target environment is available. | G20: POST valid code to /grade/{id}. | H20: Legacy route returns the current structured grading contract. | I20: P1 | J20: Compatibility | K20: Backend | L20: Yes | M20: Pass | O20: 76 backend tests passed; live API health/auth/CORS/assignment/image checks passed 13/13. | P20: Codex SQA | Q20: 46238 | R20: Not Required
A21: [x] | B21: API-009 | C21: Current | D21: Health & Public API | E21: CORS permits configured frontend | F21: Application dependencies are installed and the target environment is available. | G21: Run frontend from the allowed origin and call public endpoints. | H21: Browser requests succeed without CORS errors; unapproved origins follow configured policy. | I21: P1 | J21: Integration | K21: Web/Backend | L21: Partial | M21: Pass | O21: 76 backend tests passed; live API health/auth/CORS/assignment/image checks passed 13/13. | P21: Codex SQA | Q21: 46238 | R21: Not Required
A22: [x] | B22: API-010 | C22: Current | D22: Health & Public API | E22: Malformed JSON is rejected | F22: Application dependencies are installed and the target environment is available. | G22: POST malformed JSON to a submission endpoint. | H22: Request returns controlled HTTP 400 without server crash or stack-trace leakage. | I22: P1 | J22: Negative API | K22: Backend | L22: Yes | M22: Pass | O22: 76 backend tests passed; live API health/auth/CORS/assignment/image checks passed 13/13. | P22: Codex SQA | Q22: 46238 | R22: Not Required
A23: [ ] | B23: API-011 | C23: Current | D23: Health & Public API | E23: Request timeout behavior is bounded | F23: Application dependencies are installed and the target environment is available. | G23: Simulate an unavailable or nonresponsive backend. | H23: Frontend leaves loading state within configured timeout and shows a recovery action. | I23: P1 | J23: Resilience | K23: Flutter | L23: Partial | M23: Not Run | R23: Not Required
A24: [x] | B24: CAT-001 | C24: Current | D24: Student Catalog & Navigation | E24: Catalog header and identity | F24: Application dependencies are installed and the target environment is available. | G24: Open the landing page. | H24: Robotics Programming Lab identity and subtitle render correctly. | I24: P2 | J24: UI | K24: Web/Mobile | L24: Yes | M24: Pass | O24: 32 Flutter tests passed; live Chrome student catalog showed four ordered assignments. | P24: Codex SQA | Q24: 46238 | R24: Not Required
A25: [x] | B25: CAT-002 | C25: Current | D25: Student Catalog & Navigation | E25: Four assignment cards render | F25: Application dependencies are installed and the target environment is available. | G25: Load the catalog. | H25: Exactly four current published assignment cards render with title, number, description, and action. | I25: Release Gate | J25: UI/API | K25: Web/Mobile | L25: Partial | M25: Pass | O25: 32 Flutter tests passed; live Chrome student catalog showed four ordered assignments. | P25: Codex SQA | Q25: 46238 | R25: Not Required
A26: [x] | B26: CAT-003 | C26: Current | D26: Student Catalog & Navigation | E26: Assignment ordering | F26: Application dependencies are installed and the target environment is available. | G26: Inspect catalog order. | H26: Assignments are ordered 1, 2, 3, 4. | I26: P1 | J26: UI | K26: Web/Mobile | L26: Yes | M26: Pass | O26: 32 Flutter tests passed; live Chrome student catalog showed four ordered assignments. | P26: Codex SQA | Q26: 46238 | R26: Not Required
A27: [x] | B27: CAT-004 | C27: Current | D27: Student Catalog & Navigation | E27: Progress summary default | F27: Application dependencies are installed and the target environment is available. | G27: Open with cleared local progress. | H27: Summary shows 0 of 4 completed and 0 percent. | I27: P1 | J27: State | K27: Web/Mobile | L27: Yes | M27: Pass | O27: 32 Flutter tests passed; live Chrome student catalog showed four ordered assignments. | P27: Codex SQA | Q27: 46238 | R27: Not Required
A28: [x] | B28: CAT-005 | C28: Current | D28: Student Catalog & Navigation | E28: Progress badges | F28: Application dependencies are installed and the target environment is available. | G28: Record attempts, completion, and solution reveal; return to catalog. | H28: Cards distinguish Not started, Attempted, Completed, last score, and Solution viewed states. | I28: P1 | J28: State | K28: Web/Mobile | L28: Yes | M28: Pass | O28: 32 Flutter tests passed; live Chrome student catalog showed four ordered assignments. | P28: Codex SQA | Q28: 46238 | R28: Not Required
A29: [x] | B29: CAT-006 | C29: Current | D29: Student Catalog & Navigation | E29: Open assignment | F29: Application dependencies are installed and the target environment is available. | G29: Select Start assignment on each card. | H29: Correct assignment workspace opens without losing assignment identity. | I29: Release Gate | J29: Navigation | K29: Web/Mobile | L29: Partial | M29: Pass | O29: 32 Flutter tests passed; live Chrome student catalog showed four ordered assignments. | P29: Codex SQA | Q29: 46238 | R29: Not Required
A30: [x] | B30: CAT-007 | C30: Current | D30: Student Catalog & Navigation | E30: Return to catalog | F30: Application dependencies are installed and the target environment is available. | G30: Open an assignment and use Home/back navigation. | H30: Catalog returns and refreshed progress is visible. | I30: P1 | J30: Navigation | K30: Web/Mobile | L30: Yes | M30: Pass | O30: 32 Flutter tests passed; live Chrome student catalog showed four ordered assignments. | P30: Codex SQA | Q30: 46238 | R30: Not Required
A31: [x] | B31: CAT-008 | C31: Current | D31: Student Catalog & Navigation | E31: Catalog loading state | F31: Application dependencies are installed and the target environment is available. | G31: Throttle assignment-list response. | H31: Skeleton/loading state renders without layout breakage. | I31: P2 | J31: UI/Resilience | K31: Web/Mobile | L31: Yes | M31: Pass | O31: 32 Flutter tests passed; live Chrome student catalog showed four ordered assignments. | P31: Codex SQA | Q31: 46238 | R31: Not Required
A32: [x] | B32: CAT-009 | C32: Current | D32: Student Catalog & Navigation | E32: Catalog error and retry | F32: Application dependencies are installed and the target environment is available. | G32: Stop backend, load catalog, restart backend, select retry. | H32: Actionable error appears and retry reloads assignments successfully. | I32: P1 | J32: Resilience | K32: Web/Mobile | L32: Yes | M32: Pass | O32: 32 Flutter tests passed; live Chrome student catalog showed four ordered assignments. | P32: Codex SQA | Q32: 46238 | R32: Not Required
A33: [x] | B33: CAT-010 | C33: Current | D33: Student Catalog & Navigation | E33: Instructor entry point | F33: Application dependencies are installed and the target environment is available. | G33: Select the instructor shield icon. | H33: Instructor assignment studio opens; student progress remains unaffected. | I33: P1 | J33: Navigation | K33: Web/Mobile | L33: Partial | M33: Pass | O33: 32 Flutter tests passed; live Chrome student catalog showed four ordered assignments. | P33: Codex SQA | Q33: 46238 | R33: Not Required
A34: [x] | B34: WRK-001 | C34: Current | D34: Assignment Workspace & Editor | E34: Correct assignment header | F34: Application dependencies are installed and the target environment is available. | G34: Open every assignment. | H34: Header shows assignment number, title, progress state, Home action, and AI toggle. | I34: P1 | J34: UI | K34: Web/Mobile | L34: Partial | M34: Pass | O34: Flutter tests passed; live Assignment 1 workspace, starter code, instructions, image, and results rendered. | P34: Codex SQA | Q34: 46238 | R34: Not Required
A35: [x] | B35: WRK-002 | C35: Current | D35: Assignment Workspace & Editor | E35: Starter code loads | F35: Application dependencies are installed and the target environment is available. | G35: Open a fresh assignment with no saved draft. | H35: Version-correct starter code populates the editor. | I35: Release Gate | J35: Integration | K35: Web/Mobile | L35: Partial | M35: Pass | O35: Flutter tests passed; live Assignment 1 workspace, starter code, instructions, image, and results rendered. | P35: Codex SQA | Q35: 46238 | R35: Not Required
A36: [x] | B36: WRK-003 | C36: Current | D36: Assignment Workspace & Editor | E36: Starter code is syntactically executable | F36: Application dependencies are installed and the target environment is available. | G36: Compile and submit starter code for assignments 1 through 4. | H36: Each starter runs without unintended SyntaxError or IndentationError. | I36: Release Gate | J36: Regression | K36: Backend | L36: Yes | M36: Pass | O36: Flutter tests passed; live Assignment 1 workspace, starter code, instructions, image, and results rendered. | P36: Codex SQA | Q36: 46238 | R36: Not Required
A37: [ ] | B37: WRK-004 | C37: Current | D37: Assignment Workspace & Editor | E37: Code editing | F37: Application dependencies are installed and the target environment is available. | G37: Type, delete, paste, and indent Python code. | H37: Editor accurately reflects edits and retains Python formatting. | I37: P1 | J37: UI | K37: Web | L37: No | M37: Not Run | R37: Not Required
A38: [x] | B38: WRK-005 | C38: Current | D38: Assignment Workspace & Editor | E38: Keyboard test execution | F38: Application dependencies are installed and the target environment is available. | G38: Press Ctrl+Enter while the editor is active. | H38: Exactly one test run starts. | I38: P1 | J38: Keyboard | K38: Web/Desktop | L38: Yes | M38: Pass | O38: Flutter tests passed; live Assignment 1 workspace, starter code, instructions, image, and results rendered. | P38: Codex SQA | Q38: 46238 | R38: Not Required
A39: [x] | B39: WRK-006 | C39: Current | D39: Assignment Workspace & Editor | E39: Run button execution | F39: Application dependencies are installed and the target environment is available. | G39: Select Run tests. | H39: Button enters running state, blocks duplicate execution, then returns to enabled state. | I39: Release Gate | J39: UI/Integration | K39: Web/Mobile | L39: Yes | M39: Pass | O39: Flutter tests passed; live Assignment 1 workspace, starter code, instructions, image, and results rendered. | P39: Codex SQA | Q39: 46238 | R39: Not Required
A40: [ ] | B40: WRK-007 | C40: Current | D40: Assignment Workspace & Editor | E40: Draft autosave | F40: Application dependencies are installed and the target environment is available. | G40: Edit code; wait for debounce; leave assignment. | H40: Draft is persisted for the assignment. | I40: P1 | J40: State | K40: Web/Mobile | L40: Partial | M40: Not Run | R40: Not Required
A41: [x] | B41: WRK-008 | C41: Current | D41: Assignment Workspace & Editor | E41: Draft restore | F41: Application dependencies are installed and the target environment is available. | G41: Reopen an assignment after saving a draft. | H41: Saved draft replaces starter code only for that assignment. | I41: P1 | J41: State | K41: Web/Mobile | L41: Yes | M41: Pass | O41: Flutter tests passed; live Assignment 1 workspace, starter code, instructions, image, and results rendered. | P41: Codex SQA | Q41: 46238 | R41: Not Required
A42: [x] | B42: WRK-009 | C42: Current | D42: Assignment Workspace & Editor | E42: Independent assignment drafts | F42: Application dependencies are installed and the target environment is available. | G42: Save different code in two assignments and reopen both. | H42: Each assignment restores only its own draft. | I42: P1 | J42: State | K42: Web/Mobile | L42: Yes | M42: Pass | O42: Flutter tests passed; live Assignment 1 workspace, starter code, instructions, image, and results rendered. | P42: Codex SQA | Q42: 46238 | R42: Not Required
A43: [x] | B43: WRK-010 | C43: Current | D43: Assignment Workspace & Editor | E43: Scenario section | F43: Application dependencies are installed and the target environment is available. | G43: Inspect instructions for every assignment. | H43: Scenario content is present, readable, and belongs to the correct assignment. | I43: Release Gate | J43: Content/UI | K43: Web/Mobile | L43: Partial | M43: Pass | O43: Flutter tests passed; live Assignment 1 workspace, starter code, instructions, image, and results rendered. | P43: Codex SQA | Q43: 46238 | R43: Not Required
A44: [ ] | B44: WRK-011 | C44: Current | D44: Assignment Workspace & Editor | E44: Task and hints sections | F44: Application dependencies are installed and the target environment is available. | G44: Inspect instruction structure. | H44: Task/question and hints are organized without exposing the solution. | I44: Release Gate | J44: Content/Security | K44: Web/Mobile | L44: Partial | M44: Not Run | R44: Not Required
A45: [x] | B45: WRK-012 | C45: Current | D45: Assignment Workspace & Editor | E45: Assignment image rewriting | F45: Application dependencies are installed and the target environment is available. | G45: Run against nondefault API_BASE_URL and open assignment 1. | H45: Image URL uses the configured backend and loads successfully. | I45: P1 | J45: Integration | K45: Web/Mobile | L45: Partial | M45: Pass | O45: Flutter tests passed; live Assignment 1 workspace, starter code, instructions, image, and results rendered. | P45: Codex SQA | Q45: 46238 | R45: Not Required
A46: [x] | B46: WRK-013 | C46: Current | D46: Assignment Workspace & Editor | E46: Desktop panel focus | F46: Application dependencies are installed and the target environment is available. | G46: Use focus/maximize controls for editor, instructions, and results. | H46: Selected panel expands and restores without losing state. | I46: P2 | J46: Responsive UI | K46: Web/Desktop | L46: Yes | M46: Pass | O46: Flutter tests passed; live Assignment 1 workspace, starter code, instructions, image, and results rendered. | P46: Codex SQA | Q46: 46238 | R46: Not Required
A47: [ ] | B47: WRK-014 | C47: Current | D47: Assignment Workspace & Editor | E47: Desktop resize handle | F47: Application dependencies are installed and the target environment is available. | G47: Drag the editor/instruction divider within allowed limits. | H47: Panels resize smoothly and remain usable. | I47: P2 | J47: Responsive UI | K47: Web/Desktop | L47: No | M47: Not Run | R47: Not Required
A48: [x] | B48: WRK-015 | C48: Current | D48: Assignment Workspace & Editor | E48: Mobile workspace tabs | F48: Application dependencies are installed and the target environment is available. | G48: Open at a narrow/mobile viewport and select Code, Instructions, and Results. | H48: Each tab shows the correct panel without overflow. | I48: Release Gate | J48: Responsive UI | K48: Mobile/Web | L48: Yes | M48: Pass | O48: Flutter tests passed; live Assignment 1 workspace, starter code, instructions, image, and results rendered. | P48: Codex SQA | Q48: 46238 | R48: Not Required
A49: [ ] | B49: WRK-016 | C49: Current | D49: Assignment Workspace & Editor | E49: Workspace state survives tab changes | F49: Application dependencies are installed and the target environment is available. | G49: Edit code, switch mobile tabs, and return. | H49: Code, results, hint level, and scroll-independent state are retained. | I49: P1 | J49: State/UI | K49: Mobile/Web | L49: Partial | M49: Not Run | R49: Not Required
A50: [x] | B50: GRD-001 | C50: Current | D50: Grading & Execution | E50: Public run endpoint executes code | F50: Application dependencies are installed and the target environment is available. | G50: POST code to /assignments/{id}/run. | H50: Execution result contains only public evidence and no hidden expectations. | I50: Release Gate | J50: API/Security | K50: Backend | L50: Yes | M50: Pass | O50: 76 backend tests passed, including all four official solutions; live Run tests completed with structured evidence. | P50: Codex SQA | Q50: 46238 | R50: Not Required
A51: [x] | B51: GRD-002 | C51: Current | D51: Grading & Execution | E51: Submission endpoint executes grader | F51: Application dependencies are installed and the target environment is available. | G51: POST valid code to /assignments/{id}/submit. | H51: Structured submission response includes submission ID, assignment version, score, evidence, and pass results. | I51: Release Gate | J51: API | K51: Backend | L51: Yes | M51: Pass | O51: 76 backend tests passed, including all four official solutions; live Run tests completed with structured evidence. | P51: Codex SQA | Q51: 46238 | R51: Not Required
A52: [x] | B52: GRD-003 | C52: Current | D52: Grading & Execution | E52: Assignment 1 official solution | F52: Application dependencies are installed and the target environment is available. | G52: Submit the server-controlled official solution for assignment 1. | H52: All hidden checks pass and score is 100 percent. | I52: Release Gate | J52: Regression | K52: Backend | L52: Yes | M52: Pass | O52: 87-test local gate plus manual_sqa_answers/assignment_1_answer.py passed every grader check at 100%. | P52: Codex SQA | Q52: 46239 | R52: Not Required
A53: [x] | B53: GRD-004 | C53: Current | D53: Grading & Execution | E53: Assignment 2 official solution | F53: Application dependencies are installed and the target environment is available. | G53: Submit the server-controlled official solution for assignment 2. | H53: All hidden checks pass and score is 100 percent. | I53: Release Gate | J53: Regression | K53: Backend | L53: Yes | M53: Pass | O53: 87-test local gate plus manual_sqa_answers/assignment_2_answer.py passed every grader check at 100%. | P53: Codex SQA | Q53: 46239 | R53: Not Required
A54: [x] | B54: GRD-005 | C54: Current | D54: Grading & Execution | E54: Assignment 3 official solution | F54: Application dependencies are installed and the target environment is available. | G54: Submit the server-controlled official solution for assignment 3. | H54: All hidden checks pass and score is 100 percent. | I54: Release Gate | J54: Regression | K54: Backend | L54: Yes | M54: Pass | O54: 87-test local gate plus manual_sqa_answers/assignment_3_answer.py passed every grader check at 100%. | P54: Codex SQA | Q54: 46239 | R54: Not Required
A55: [x] | B55: GRD-006 | C55: Current | D55: Grading & Execution | E55: Assignment 4 official solution | F55: Application dependencies are installed and the target environment is available. | G55: Submit the server-controlled official solution for assignment 4. | H55: All hidden checks pass and score is 100 percent. | I55: Release Gate | J55: Regression | K55: Backend | L55: Yes | M55: Pass | O55: 87-test local gate plus manual_sqa_answers/assignment_4_answer.py passed every grader check at 100%. | P55: Codex SQA | Q55: 46239 | R55: Not Required
A56: [x] | B56: GRD-007 | C56: Current | D56: Grading & Execution | E56: Incorrect code returns useful evidence | F56: Application dependencies are installed and the target environment is available. | G56: Submit code with incorrect calculated variables. | H56: Program execution and individual calculation failures are reported without expected values. | I56: Release Gate | J56: Functional | K56: Backend/UI | L56: Yes | M56: Pass | O56: Incorrect executable code returned safe structured failing evidence without revealing expected values. | P56: Codex SQA | Q56: 46239 | R56: Not Required
A57: [x] | B57: GRD-008 | C57: Current | D57: Grading & Execution | E57: Execution error is structured | F57: Application dependencies are installed and the target environment is available. | G57: Submit code that raises a runtime exception. | H57: Response identifies execution failure safely; UI shows terminal error rather than spinning. | I57: Release Gate | J57: Negative | K57: Backend/UI | L57: Partial | M57: Pass | O57: SyntaxError and ZeroDivisionError submissions returned structured execution failures; UI recovery tests passed. | P57: Codex SQA | Q57: 46239 | R57: Not Required | S57: Automated and separate-process smoke evidence.
A58: [x] | B58: GRD-009 | C58: Current | D58: Grading & Execution | E58: Empty code handling | F58: Application dependencies are installed and the target environment is available. | G58: Submit empty code. | H58: Request is rejected with controlled client error and UI remains usable. | I58: P1 | J58: Negative | K58: Backend/UI | L58: Yes | M58: Pass | O58: 76 backend tests passed, including all four official solutions; live Run tests completed with structured evidence. | P58: Codex SQA | Q58: 46238 | R58: Not Required
A59: [x] | B59: GRD-010 | C59: Current | D59: Grading & Execution | E59: Unknown assignment submission | F59: Application dependencies are installed and the target environment is available. | G59: Submit code to assignment 999. | H59: HTTP 404 is returned with no execution attempt. | I59: P1 | J59: Negative API | K59: Backend | L59: Yes | M59: Pass | O59: 76 backend tests passed, including all four official solutions; live Run tests completed with structured evidence. | P59: Codex SQA | Q59: 46238 | R59: Not Required
A60: [x] | B60: GRD-011 | C60: Current | D60: Grading & Execution | E60: Score calculation | F60: Application dependencies are installed and the target environment is available. | G60: Submit combinations of passing and failing variables. | H60: Score and pass/fail counts exactly match structured boolean test outcomes. | I60: Release Gate | J60: Functional | K60: Backend/UI | L60: Yes | M60: Pass | O60: 76 backend tests passed, including all four official solutions; live Run tests completed with structured evidence. | P60: Codex SQA | Q60: 46238 | R60: Not Required
A61: [x] | B61: GRD-012 | C61: Current | D61: Grading & Execution | E61: Terminal stdout displayed | F61: Application dependencies are installed and the target environment is available. | G61: Submit code that prints output. | H61: Captured output appears in Terminal output and remains size-bounded. | I61: P1 | J61: Functional | K61: Backend/UI | L61: Partial | M61: Pass | O61: 76 backend tests passed, including all four official solutions; live Run tests completed with structured evidence. | P61: Codex SQA | Q61: 46238 | R61: Not Required
A62: [x] | B62: GRD-013 | C62: Current | D62: Grading & Execution | E62: Per-test details displayed | F62: Application dependencies are installed and the target environment is available. | G62: Submit an incorrect but executable solution. | H62: Every visible test has a Passed or Needs attention card and safe message. | I62: Release Gate | J62: UI/Integration | K62: Web/Mobile | L62: Yes | M62: Pass | O62: 76 backend tests passed, including all four official solutions; live Run tests completed with structured evidence. | P62: Codex SQA | Q62: 46238 | R62: Not Required
A63: [x] | B63: GRD-014 | C63: Current | D63: Grading & Execution | E63: No hidden expected values in response | F63: Application dependencies are installed and the target environment is available. | G63: Inspect public run, submission, hint, logs, and browser network responses. | H63: Hidden expected values, test implementation, grader config, and official solution are absent. | I63: Release Gate | J63: Security | K63: All | L63: Partial | M63: Pass | O63: 76 backend tests passed, including all four official solutions; live Run tests completed with structured evidence. | P63: Codex SQA | Q63: 46238 | R63: Not Required
A64: [x] | B64: GRD-015 | C64: Current | D64: Grading & Execution | E64: Submission version captured | F64: Application dependencies are installed and the target environment is available. | G64: Submit each assignment and inspect stored/returned assignment_version. | H64: Submission records the exact published version used. | I64: Release Gate | J64: Data Integrity | K64: Backend | L64: Yes | M64: Pass | O64: 76 backend tests passed, including all four official solutions; live Run tests completed with structured evidence. | P64: Codex SQA | Q64: 46238 | R64: Not Required
A65: [x] | B65: GRD-016 | C65: Current | D65: Grading & Execution | E65: Concurrent run protection in UI | F65: Application dependencies are installed and the target environment is available. | G65: Double-click Run tests and press Ctrl+Enter while running. | H65: Only one active request is started and progress returns to idle. | I65: P1 | J65: Resilience | K65: Web/Mobile | L65: Yes | M65: Pass | O65: 76 backend tests passed, including all four official solutions; live Run tests completed with structured evidence. | P65: Codex SQA | Q65: 46238 | R65: Not Required
A66: [x] | B66: GRD-017 | C66: Current | D66: Grading & Execution | E66: Grading request timeout | F66: Application dependencies are installed and the target environment is available. | G66: Force grading past the frontend timeout. | H66: UI stops waiting, displays grading-service recovery state, and permits retry. | I66: P1 | J66: Resilience | K66: Web/Mobile | L66: Yes | M66: Pass | O66: 76 backend tests passed, including all four official solutions; live Run tests completed with structured evidence. | P66: Codex SQA | Q66: 46238 | R66: Not Required
A67: [x] | B67: GRD-018 | C67: Current | D67: Grading & Execution | E67: Retry after backend recovery | F67: Application dependencies are installed and the target environment is available. | G67: Trigger a grading error, restore backend, and select Retry test run. | H67: New grading request completes and replaces the error state. | I67: P1 | J67: Resilience | K67: Web/Mobile | L67: Yes | M67: Pass | O67: 76 backend tests passed, including all four official solutions; live Run tests completed with structured evidence. | P67: Codex SQA | Q67: 46238 | R67: Not Required
A68: [x] | B68: SEC-001 | C68: Current | D68: Sandbox, Security & Privacy | E68: Oversized submission rejected | F68: Application dependencies are installed and the target environment is available. | G68: Submit more than the configured maximum characters. | H68: HTTP 413 is returned before execution. | I68: Release Gate | J68: Security | K68: Backend | L68: Yes | M68: Pass | O68: Oversized submission and request-body limits returned HTTP 413 before execution. | P68: Codex SQA | Q68: 46239 | R68: Not Required
A69: [x] | B69: SEC-002 | C69: Current | D69: Sandbox, Security & Privacy | E69: Infinite loop terminated | F69: Application dependencies are installed and the target environment is available. | G69: Submit an infinite loop. | H69: Execution is terminated within the configured timeout and backend remains healthy. | I69: Release Gate | J69: Security/Resilience | K69: Backend | L69: Yes | M69: Pass | O69: Infinite-loop submission was terminated by the configured execution timeout. | P69: Codex SQA | Q69: 46239 | R69: Not Required
... A71: [x] | B71: SEC-004 | C71: Current | D71: Sandbox, Security & Privacy | E71: Dangerous import blocked | F71: Application dependencies are installed and the target environment is available. | G71: Submit code importing os or another disallowed capability. | H71: Sandbox rejects the code or prevents unsafe capability use. | I71: Release Gate | J71: Security | K71: Backend | L71: Yes | M71: Pass | O71: Disallowed os import and unsafe file/network capabilities were rejected by sandbox policy. | P71: Codex SQA | Q71: 46239 | R71: Not Required
A72: [ ] | B72: SEC-005 | C72: Current | D72: Sandbox, Security & Privacy | E72: No host filesystem access | F72: Application dependencies are installed and the target environment is available. | G72: Attempt to read known host paths from production sandbox. | H72: Submission cannot access host or repository files. | I72: Release Gate | J72: Penetration | K72: Docker Sandbox | L72: No | M72: Partial | O72: Dedicated service has no repository/database/OpenAI secrets and file APIs/imports are blocked; live Docker host-path probe remains open. | P72: Codex SQA | Q72: 46238 | R72: Not Required | S72: Do not approve anonymous public execution.
A73: [ ] | B73: SEC-006 | C73: Current | D73: Sandbox, Security & Privacy | E73: No unrestricted network access | F73: Application dependencies are installed and the target environment is available. | G73: Attempt outbound network access from production sandbox. | H73: Network is denied unless explicitly allowed by assignment policy. | I73: Release Gate | J73: Penetration | K73: Docker Sandbox | L73: No | M73: Partial | O73: Socket/network imports are blocked by the assignment AST policy; OS-level egress-denial proof on the live container remains open. | P73: Codex SQA | Q73: 46238 | R73: Not Required | S73: Controlled classroom use only until live penetration evidence exists.
A74: [ ] | B74: SEC-007 | C74: Current | D74: Sandbox, Security & Privacy | E74: Container resource limits | F74: Application dependencies are installed and the target environment is available. | G74: Run CPU-, memory-, process-, and disk-intensive submissions. | H74: Configured resource limits terminate or constrain the workload. | I74: Release Gate | J74: Performance/Security | K74: Docker Sandbox | L74: No | M74: Partial | O74: Linux worker CPU/memory/file/process/output limits are implemented and capacity tests pass; Docker/live stress proof remains open. | P74: Codex SQA | Q74: 46238 | R74: Not Required | S74: Build and stress the deployed image before student distribution.
A75: [ ] | B75: SEC-008 | C75: Current | D75: Sandbox, Security & Privacy | E75: Sandbox temporary cleanup | F75: Application dependencies are installed and the target environment is available. | G75: Run successful, failed, and timed-out submissions; inspect temporary resources. | H75: Containers/workspaces are removed and no student code persists unexpectedly. | I75: P0 | J75: Security | K75: Docker Sandbox | L75: No | M75: Not Run | R75: Not Required
A76: [x] | B76: SEC-009 | C76: Current | D76: Sandbox, Security & Privacy | E76: Docker sandbox invalid response | F76: Application dependencies are installed and the target environment is available. | G76: Force malformed sandbox response. | H76: Backend returns controlled execution error without crashing. | I76: P1 | J76: Negative Integration | K76: Backend | L76: Partial | M76: Pass | O76: Malformed remote responses, authentication failures, and unavailable-service errors return controlled messages without backend crashes. | P76: Codex SQA | Q76: 46238 | R76: Not Required | S76: Remote sandbox negative tests pass.
A77: [x] | B77: SEC-010 | C77: Current | D77: Sandbox, Security & Privacy | E77: Admin endpoint requires configured token | F77: Application dependencies are installed and the target environment is available. | G77: Call /admin/assignments without a token, with an incorrect token, and when admin is unconfigured. | H77: Responses are 401 for incorrect/missing token and controlled 503 when unconfigured. | I77: Release Gate | J77: Security API | K77: Backend | L77: Yes | M77: Pass | O77: Backend security/authorization tests passed and live student responses excluded private grader/solution fields. | P77: Codex SQA | Q77: 46238 | R77: Not Required
A78: [ ] | B78: SEC-011 | C78: Current | D78: Sandbox, Security & Privacy | E78: Instructor token is not OpenAI key | F78: Application dependencies are installed and the target environment is available. | G78: Inspect instructor UI labels/help and submit the admin token. | H78: UI clearly requests ADMIN_API_TOKEN; OpenAI key is never requested from the client. | I78: P0 | J78: Security/UX | K78: Web/Mobile | L78: Partial | M78: Not Run | R78: Not Required
A79: [ ] | B79: SEC-012 | C79: Current | D79: Sandbox, Security & Privacy | E79: Admin token remains server-side/private | F79: Application dependencies are installed and the target environment is available. | G79: Inspect browser storage, logs, screenshots, and repository tracking. | H79: Token is used only for the active admin request flow and is not committed or logged. | I79: Release Gate | J79: Privacy | K79: All | L79: Partial | M79: Not Run | R79: Not Required
A80: [x] | B80: SEC-013 | C80: Current | D80: Sandbox, Security & Privacy | E80: Solution endpoint authorization | F80: Application dependencies are installed and the target environment is available. | G80: Attempt solution reveal without submission, with another assignment's submission, and with stale-version submission. | H80: Solution remains blocked with controlled errors. | I80: Release Gate | J80: Security | K80: Backend | L80: Yes | M80: Pass | O80: Backend security/authorization tests passed and live student responses excluded private grader/solution fields. | P80: Codex SQA | Q80: 46238 | R80: Not Required
A81: [x] | B81: SEC-014 | C81: Current | D81: Sandbox, Security & Privacy | E81: Student assignment payload excludes private fields | F81: Application dependencies are installed and the target environment is available. | G81: Inspect assignment list/detail JSON. | H81: Payload excludes grader_config, misconceptions policy internals where private, reference path, hidden tests, and solution body. | I81: Release Gate | J81: Security API | K81: Backend | L81: Yes | M81: Pass | O81: Backend security/authorization tests passed and live student responses excluded private grader/solution fields. | P81: Codex SQA | Q81: 46238 | R81: Not Required
A82: [ ] | B82: SEC-015 | C82: Current | D82: Sandbox, Security & Privacy | E82: Error responses do not leak stack traces or secrets | F82: Application dependencies are installed and the target environment is available. | G82: Trigger validation, sandbox, database, and tutor failures. | H82: Client receives controlled messages; logs contain no API key or admin token. | I82: Release Gate | J82: Security | K82: Backend | L82: Partial | M82: Partial | O82: Remote sandbox failures redact provider details and secret scans pass; database/tutor failure-log review remains open. | P82: Codex SQA | Q82: 46238 | R82: Not Required | S82: Complete the remaining failure classes before sign-off.
A83: [x] | B83: TUT-001 | C83: Current | D83: Feedback & Tutoring | E83: AI tutoring defaults off | F83: Application dependencies are installed and the target environment is available. | G83: Open every assignment in a clean session. | H83: AI tutoring switch is off. | I83: Release Gate | J83: UI/Configuration | K83: Web/Mobile | L83: Yes | M83: Pass | O83: AI remained off by default; deterministic no-AI execution completed; maintained tutor safety tests passed. | P83: Codex SQA | Q83: 46238 | R83: Not Required
A84: [x] | B84: TUT-002 | C84: Current | D84: Feedback & Tutoring | E84: AI-off grading remains complete | F84: Application dependencies are installed and the target environment is available. | G84: Leave AI off and run incorrect starter code. | H84: Score, terminal output, and test details appear without tutor delay. | I84: Release Gate | J84: Integration | K84: Web/Mobile | L84: Partial | M84: Pass | O84: AI remained off by default; deterministic no-AI execution completed; maintained tutor safety tests passed. | P84: Codex SQA | Q84: 46238 | R84: Not Required
A85: [x] | B85: TUT-003 | C85: Current | D85: Feedback & Tutoring | E85: AI-off request payload | F85: Application dependencies are installed and the target environment is available. | G85: Inspect submission request when toggle is off. | H85: use_ai_tutor is false and backend does not call OpenAI. | I85: P0 | J85: Integration | K85: Web/Backend | L85: Partial | M85: Pass | O85: AI remained off by default; deterministic no-AI execution completed; maintained tutor safety tests passed. | P85: Codex SQA | Q85: 46238 | R85: Not Required
A86: [x] | B86: TUT-004 | C86: Current | D86: Feedback & Tutoring | E86: Built-in tutoring fallback | F86: Application dependencies are installed and the target environment is available. | G86: Enable tutoring while OpenAI is unavailable or unconfigured; submit incorrect code. | H86: Submission completes and displays Built-in tutor hint. | I86: Release Gate | J86: Resilience | K86: Backend/UI | L86: Yes | M86: Pass | O86: AI remained off by default; deterministic no-AI execution completed; maintained tutor safety tests passed. | P86: Codex SQA | Q86: 46238 | R86: Not Required
A87: [x] | B87: TUT-005 | C87: Current | D87: Feedback & Tutoring | E87: OpenAI source label | F87: Application dependencies are installed and an authorized funded OpenAI key is configured. | G87: With a funded authorized test key, enable tutoring and submit incorrect code. | H87: Successful model response displays OpenAI tutor hint. | I87: P1 | J87: External Integration | K87: Backend/UI | L87: Partial | M87: Deferred | O87: AI provider behavior was intentionally excluded from this SQA cycle by project decision. | P87: Codex SQA | Q87: 46238 | R87: Not Required | S87: Current API quota may require this row to be Blocked with evidence.
A88: [x] | B88: TUT-006 | C88: Current | D88: Feedback & Tutoring | E88: Tutor request timeout and no endless spinner | F88: Application dependencies are installed and the target environment is available. | G88: Simulate model timeout. | H88: Backend falls back within the bounded timeout; Run tests stops loading. | I88: Release Gate | J88: Resilience | K88: Backend/UI | L88: Yes | M88: Pass | O88: AI remained off by default; deterministic no-AI execution completed; maintained tutor safety tests passed. | P88: Codex SQA | Q88: 46238 | R88: Not Required
A89: [x] | B89: TUT-007 | C89: Current | D89: Feedback & Tutoring | E89: Tutor input is sanitized | F89: Application dependencies are installed and the target environment is available. | G89: Capture mocked model request. | H89: Input contains student-visible evidence only; no hidden values/tests/config/solution. | I89: Release Gate | J89: Security | K89: Backend | L89: Yes | M89: Pass | O89: AI remained off by default; deterministic no-AI execution completed; maintained tutor safety tests passed. | P89: Codex SQA | Q89: 46238 | R89: Not Required
A90: [x] | B90: TUT-008 | C90: Current | D90: Feedback & Tutoring | E90: Tutor never reveals official solution | F90: Application dependencies are installed and the target environment is available. | G90: Exercise common prompt-injection and answer-request attempts. | H90: Feedback provides diagnosis/questions/hints without replacement solution or hidden evidence. | I90: Release Gate | J90: AI Safety | K90: Backend | L90: Partial | M90: Deferred | O90: AI provider behavior was intentionally excluded from this SQA cycle by project decision. | P90: Codex SQA | Q90: 46238 | R90: Not Required
A91: [x] | B91: TUT-009 | C91: Current | D91: Feedback & Tutoring | E91: Hint level 1 | F91: Application dependencies are installed and the target environment is available. | G91: Request initial tutor feedback. | H91: Response shows level 1 of 4 with an appropriate first-step hint. | I91: P1 | J91: Functional | K91: Backend/UI | L91: Yes | M91: Pass | O91: AI remained off by default; deterministic no-AI execution completed; maintained tutor safety tests passed. | P91: Codex SQA | Q91: 46238 | R91: Not Required
A92: [ ] | B92: TUT-010 | C92: Current | D92: Feedback & Tutoring | E92: Progressive hints levels 2 through 4 | F92: Application dependencies are installed and the target environment is available. | G92: Select Get another hint repeatedly. | H92: Levels increment once, content becomes progressively more specific, and level 4 disables further requests. | I92: P1 | J92: Functional | K92: Backend/UI | L92: Partial | M92: Not Run | R92: Not Required
A93: [x] | B93: TUT-011 | C93: Current | D93: Feedback & Tutoring | E93: Invalid hint levels rejected | F93: Application dependencies are installed and the target environment is available. | G93: Request levels 0 and 5. | H93: HTTP 400 validation error is returned. | I93: P1 | J93: Negative API | K93: Backend | L93: Yes | M93: Pass | O93: AI remained off by default; deterministic no-AI execution completed; maintained tutor safety tests passed. | P93: Codex SQA | Q93: 46238 | R93: Not Required
A94: [x] | B94: TUT-012 | C94: Current | D94: Feedback & Tutoring | E94: Cross-assignment hint request rejected | F94: Application dependencies are installed and the target environment is available. | G94: Use an assignment 2 submission ID for assignment 1 hint endpoint. | H94: HTTP 404 is returned and no hint interaction is stored. | I94: P1 | J94: Security API | K94: Backend | L94: Yes | M94: Pass | O94: AI remained off by default; deterministic no-AI execution completed; maintained tutor safety tests passed. | P94: Codex SQA | Q94: 46238 | R94: Not Required
A95: [ ] | B95: TUT-013 | C95: Current | D95: Feedback & Tutoring | E95: Hint error recovery | F95: Application dependencies are installed and the target environment is available. | G95: Make the hint endpoint unavailable and select Get another hint. | H95: Panel shows a retryable error and preserves the current hint. | I95: P2 | J95: Resilience | K95: Web/Mobile | L95: Partial | M95: Not Run | R95: Not Required
A96: [x] | B96: PRG-001 | C96: Current | D96: Solutions & Learning Progress | E96: Solution initially locked | F96: Application dependencies are installed and the target environment is available. | G96: Open a fresh assignment. | H96: Worked solution is locked until a current-version run/submission exists. | I96: Release Gate | J96: Security/UI | K96: Web/Mobile | L96: Yes | M96: Pass | O96: Flutter progress persistence/state tests and backend submission ownership/version tests passed. | P96: Codex SQA | Q96: 46238 | R96: Not Required
A97: [ ] | B97: PRG-002 | C97: Current | D97: Solutions & Learning Progress | E97: Solution reveals after attempt | F97: Application dependencies are installed and the target environment is available. | G97: Run tests, then select reveal solution and confirm. | H97: Current assignment solution loads from backend and is marked revealed. | I97: P1 | J97: Functional | K97: Backend/UI | L97: Partial | M97: Not Run | R97: Not Required
A98: [x] | B98: PRG-003 | C98: Current | D98: Solutions & Learning Progress | E98: Solution reveal persists | F98: Application dependencies are installed and the target environment is available. | G98: Reveal a solution, leave, and reopen the assignment. | H98: Solution-viewed state and protected solution reload correctly. | I98: P1 | J98: State | K98: Web/Mobile | L98: Yes | M98: Pass | O98: Flutter progress persistence/state tests and backend submission ownership/version tests passed. | P98: Codex SQA | Q98: 46238 | R98: Not Required
A99: [x] | B99: PRG-004 | C99: Current | D99: Solutions & Learning Progress | E99: Stale solution reveal invalidated | F99: Application dependencies are installed and the target environment is available. | G99: Reveal a solution, publish a newer assignment version, and reopen. | H99: Old reveal state clears; student must run the new version before reveal. | I99: Release Gate | J99: Versioning/Security | K99: Backend/UI | L99: Yes | M99: Pass | O99: Flutter progress persistence/state tests and backend submission ownership/version tests passed. | P99: Codex SQA | Q99: 46238 | R99: Not Required
A100: [x] | B100: PRG-005 | C100: Current | D100: Solutions & Learning Progress | E100: Attempt count persists | F100: Application dependencies are installed and the target environment is available. | G100: Run tests multiple times; reload application. | H100: Attempt count remains correct. | I100: P1 | J100: State | K100: Web/Mobile | L100: Yes | M100: Pass | O100: Flutter progress persistence/state tests and backend submission ownership/version tests passed. | P100: Codex SQA | Q100: 46238 | R100: Not Required
A101: [x] | B101: PRG-006 | C101: Current | D101: Solutions & Learning Progress | E101: Latest score persists | F101: Application dependencies are installed and the target environment is available. | G101: Record scores in sequence and reload. | H101: Latest score reflects the most recent graded attempt. | I101: P1 | J101: State | K101: Web/Mobile | L101: Yes | M101: Pass | O101: Flutter progress persistence/state tests and backend submission ownership/version tests passed. | P101: Codex SQA | Q101: 46238 | R101: Not Required
...

Sheet Assignment Matrix
A1: Checked? | B1: Assignment ID | C1: Stable ID | D1: Version | E1: Title | F1: Published | G1: Detail Loads | H1: Starter Compiles | I1: Starter Executes | J1: Official Solution | K1: Public Run | L1: Hidden Grading | M1: Evidence UI | N1: Solution Protection | O1: Hint Policy | P1: Simulation Config | Q1: Last Verified | R1: Evidence | S1: Notes
A2: [x] | B2: 1 | C2: robotics-assignment-1 | D2: 14 | E2: Obstacle Avoidance: Bug Algorithm Scenario 1 | F2: Pass | G2: Pass | H2: Pass | I2: Pass | J2: Pass | K2: Pass | L2: Pass | M2: Pass | N2: Pass | O2: Pass | P2: Pass | Q2: 46300 | R2: 2026-10-05 review fixes; see Review Fixes QA 2026-10-05 | S2: Verify consistent Euclidean/boundary distance and no embedded solution.
A3: [x] | B3: 2 | C3: robotics-assignment-2 | D3: 14 | E3: Obstacle Avoidance: Bug Algorithm Scenario 2 | F3: Pass | G3: Pass | H3: Pass | I3: Pass | J3: Pass | K3: Pass | L3: Pass | M3: Pass | N3: Pass | O3: Pass | P3: Pass | Q3: 46300 | R3: 2026-10-05 review fixes; see Review Fixes QA 2026-10-05 | S3: Verify four expected calculation variables and total path length.
A4: [x] | B4: 3 | C4: robotics-assignment-3 | D4: 15 | E4: Autonomous Robot Navigation in a Multi-Floor Office | F4: Pass | G4: Pass | H4: Pass | I4: Pass | J4: Pass | K4: Pass | L4: Pass | M4: Pass | N4: Pass | O4: Pass | P4: Pass | Q4: 46300 | R4: 2026-10-05 review fixes; see Review Fixes QA 2026-10-05 | S4: Verify movable obstacle activates the configured half-circle detour.
A5: [x] | B5: 4 | C5: robotics-assignment-4 | D5: 14 | E5: Selecting a Direction with a Simplified VFH | F5: Pass | G5: Pass | H5: Pass | I5: Pass | J5: Pass | K5: Pass | L5: Pass | M5: Pass | N5: Pass | O5: Pass | P5: Pass | Q5: 46300 | R5: 2026-10-05 review fixes; see Review Fixes QA 2026-10-05 | S5: Verify histogram and optimal-sector calculations.
A6: [x] | B6: 5 | C6: ros2-drive-forward | D6: 9 | E6: Drive Forward and Stop with ROS 2 | F6: Pass | G6: Pass | H6: Pass | I6: Pass | J6: Pass | K6: Pass | L6: Pass | M6: Pass | N6: Pass | O6: Pass | P6: Pass | Q6: 46300 | R6: 2026-10-05 review fixes; see Review Fixes QA 2026-10-05 | S6: Only controller.py is editable; the project tree and locked support files remain visible.
A7: [x] | B7: 6 | C7: ros2-obstacle-stop | D7: 9 | E7: Stop for an Obstacle with ROS 2 | F7: Pass | G7: Pass | H7: Pass | I7: Pass | J7: Pass | K7: Pass | L7: Pass | M7: Pass | N7: Pass | O7: Pass | P7: Pass | Q7: 46300 | R7: 2026-10-05 review fixes; see Review Fixes QA 2026-10-05 | S7: Only controller.py is editable; the project tree and locked support files remain visible.

Sheet Defect Log
A1: Defect ID | B1: Title | C1: Severity | D1: Category | E1: Environment | F1: Steps to Reproduce | G1: Expected | H1: Actual | I1: Status | J1: Owner | K1: Found Date | L1: Fix Version / Commit | M1: Retest Result | N1: Retest Date | O1: Evidence Link / Path | P1: Notes
P2: Enter the first real v4 defect here. No new product defect was found in the 2026-08-04 SQA run.
A3: SR-01 | B3: Safe math.dist wrongly blocked | C3: P1 | D3: Sandbox | E3: Local staging | F3: Use math.dist for a correct route | G3: 100% for equivalent correct method | H3: Blocked import attribute | I3: Fixed | J3: Development | K3: 46295.5 | L3: Uncommitted | M3: PASS | N3: 46295.5 | O3: STUDENT-2026-09-30 | P3: Safe math allowlist and equivalent-method tests
A4: SR-02 | B4: Extra return values earned full credit | C4: P1 | D4: Grading | E4: Local staging | F4: Return five values from four-value route function | G4: Invalid contract rejected | H4: 100% accepted | I4: Fixed | J4: Development | K4: 46295.5 | L4: Uncommitted | M4: PASS | N4: 46295.5 | O4: STUDENT-2026-09-30 | P4: Exact return-count validation and regression tests
A5: SR-03 | B5: Grading routes did not match valid Bug2 geometry | C5: P1 | D5: Assignment | E5: Local staging | F5: Review alternate grading scenarios | G5: M-line hit/leave and valid boundary segments | H5: Invalid route geometry | I5: Fixed | J5: Development | K5: 46295.5 | L5: Uncommitted | M5: PASS | N5: 46295.5 | O5: STUDENT-2026-09-30 | P5: Corrected scenarios, independently calculated expected values, version bump
A6: SR-04 | B6: Swapped approach and departure could pass | C6: P1 | D6: Grading | E6: Local staging | F6: Swap first and third return values | G6: Wrong order loses affected credit | H6: Equal lengths masked swap | I6: Fixed | J6: Development | K6: 46295.5 | L6: Uncommitted | M6: PASS | N6: 46295.5 | O6: STUDENT-2026-09-30 | P6: Distinct-distance scenario and all return permutations
A7: SR-05 | B7: Built-in hints criticized passing work | C7: P2 | D7: Tutor | E7: Local staging | F7: Request hint after all checks passed | G7: Acknowledge successful checks | H7: Failure-oriented advice | I7: Fixed | J7: Development | K7: 46295.5 | L7: Uncommitted | M7: PASS | N7: 46295.5 | O7: STUDENT-2026-09-30 | P7: Success and missing-evidence handling
A8: SR-06 | B8: Unsupported misconception labels | C8: P1 | D8: Research | E8: Local staging | F8: Request hints at different levels or AI feedback | G8: Only evidence-supported tags | H8: Hint level or model guess became a label | I8: Fixed | J8: Development | K8: 46295.5 | L8: Uncommitted | M8: PASS | N8: 46295.5 | O8: STUDENT-2026-09-30 | P8: Removed unsupported labels from built-in and AI feedback
A9: SR-07 | B9: Built-in hint UI absent with AI off | C9: P2 | D9: UI/API | E9: Local staging | F9: Run incomplete work with AI disabled | G9: Hint and progression available | H9: Only test details shown | I9: Fixed | J9: Development | K9: 46295.5 | L9: Uncommitted | M9: PASS | N9: 46295.5 | O9: STUDENT-2026-09-30 | P9: Initial deterministic hint without paid call or invented hint-request event
A10: SR-08 | B10: AI advised removing diagnostic prints | C10: P1 | D10: Tutor | E10: Local staging | F10: Ask about an extra return value | G10: Distinguish prints from return contract | H10: Wrong advice to remove prints | I10: Fixed | J10: Development | K10: 46295.5 | L10: Uncommitted | M10: PASS | N10: 46295.5 | O10: STUDENT-2026-09-30 | P10: Clarified tutor instructions; real request 9 retested
A11: SR-09 | B11: Scoring scope insufficiently explicit | C11: P2 | D11: Instructions | E11: Local staging | F11: Read assignments 1 and 2 as a new student | G11: Explain 25% weights and supplied-route scope | H11: Scoring across scenarios and scope unclear | I11: Fixed | J11: Development | K11: 46295.5 | L11: Uncommitted | M11: PASS | N11: 46295.5 | O11: STUDENT-2026-09-30 | P11: Added scope, partial-credit, return, numeric and AI rules
A12: OR-01 | B12: Hardcoded sector count accepted | C12: P1 | D12: Grading | E12: Local staging | F12: A4 return constant 360 | G12: Affected count check fails | H12: 100% before fix | I12: Fixed | J12: Development | K12: 46295.5 | L12: Reviewed staging changes | M12: PASS | N12: 46295.5 | O12: REMAINING-2026-09-30 | P12: Varied fill/seed counts and density ties; real regression
A13: OR-02 | B13: Late ROS stop accepted | C13: P1 | D13: Grading | E13: Local staging | F13: A5 stop after six seconds | G13: Safe-stop and hold checks fail | H13: 100% before fix | I13: Fixed | J13: Development | K13: 46295.5 | L13: Reviewed staging changes | M13: PASS | N13: 46295.5 | O13: REMAINING-2026-09-30 | P13: Command-relative clock; actual Docker result 70%
A14: OR-03 | B14: Incorrect ROS stop threshold accepted | C14: P1 | D14: Grading | E14: Local staging | F14: A6 threshold 0.50 or moves at 0.75 | G14: Obstacle criterion fails | H14: 100% before fix | I14: Fixed | J14: Development | K14: 46295.5 | L14: Reviewed staging changes | M14: PASS | N14: 46295.5 | O14: REMAINING-2026-09-30 | P14: Exact and near-threshold scans; actual result 80%
... A46: SQ-03 | B46: Default instructor password on shared staging and in docs | C46: High | D46: Security | E46: Neon staging | F46: Sign in to staging with the formerly published default instructor password | G46: Default credentials rejected | H46: Default credentials accepted | I46: Fixed | J46: Project owner | K46: 46297.5 | L46: 49e27f8 (guard and docs); staging account reset 2026-10-02 | M46: Pass | N46: 46297.75 | O46: Staging QA 2026-10-02 | P46: Guard and docs fixed; shared staging instructor password reset with owner approval; default rejected (401). Student account still uses the old default (separate follow-up)
A47: SQ-04 | B47: Demo session calls the research API and receives 409 | C47: Low | D47: Frontend | E47: Local staging | F47: Use the student demo and watch network requests | G47: Demo skips research tracking | H47: POST /research/sessions returns 409 per event | I47: Deferred | J47: Project owner | K47: 46297.5 | M47: Not Run | O47: Staging QA 2026-10-02 | P47: Server correctly rejects; no data stored. Deferred by owner (Phase 1)
A48: AR-01 | B48: A4 hidden cases passed readings as a list, so dict-copy solutions scored 0% | C48: Critical | D48: Grading | E48: Local staging (Windows) | F48: See the 2026-10-05 Assignments 1-6 review | G48: Fair, consistent assignment and grading | H48: A4 hidden cases passed readings as a list, so dict-copy solutions scored 0% | I48: Fixed | J48: Development | K48: 46300 | L48: e939dc3b | M48: Pass | N48: 46300 | O48: Assignment Review QA 2026-10-05
A49: AR-02 | B49: Sandbox errors showed worker line numbers; sandbox limits undocumented | C49: Medium | D49: Grading | E49: Local staging (Windows) | F49: See the 2026-10-05 Assignments 1-6 review | G49: Fair, consistent assignment and grading | H49: Sandbox errors showed worker line numbers; sandbox limits undocumented | I49: Fixed | J49: Development | K49: 46300 | L49: e939dc3b | M49: Pass | N49: 46300 | O49: Assignment Review QA 2026-10-05
A50: AR-03 | B50: A5 never-moving node earned 50% (straight-motion credit) | C50: High | D50: Grading | E50: Local staging (Windows) | F50: See the 2026-10-05 Assignments 1-6 review | G50: Fair, consistent assignment and grading | H50: A5 never-moving node earned 50% (straight-motion credit) | I50: Fixed | J50: Development | K50: 46300 | L50: e939dc3b | M50: Pass | N50: 46300 | O50: Assignment Review QA 2026-10-05
A51: AR-04 | B51: A6 always-stopped node earned 75% (stop and straight credit) | C51: High | D51: Grading | E51: Local staging (Windows) | F51: See the 2026-10-05 Assignments 1-6 review | G51: Fair, consistent assignment and grading | H51: A6 always-stopped node earned 75% (stop and straight credit) | I51: Fixed | J51: Development | K51: 46300 | L51: e939dc3b | M51: Pass | N51: 46300 | O51: Assignment Review QA 2026-10-05
A52: AR-05 | B52: VFH course page exposed instructor notes; practice pages conflicted with graded versions | C52: High | D52: Content | E52: Local staging (Windows) | F52: See the 2026-10-05 Assignments 1-6 review | G52: Fair, consistent assignment and grading | H52: VFH course page exposed instructor notes; practice pages conflicted with graded versions | I52: Fixed | J52: Development | K52: 46300 | L52: e939dc3b | M52: Pass | N52: 46300 | O52: Assignment Review QA 2026-10-05
A53: AR-06 | B53: A3 half-circle detour model geometrically misleading; barrier undescribed | C53: Medium | D53: Content | E53: Local staging (Windows) | F53: See the 2026-10-05 Assignments 1-6 review | G53: Fair, consistent assignment and grading | H53: A3 half-circle detour model geometrically misleading; barrier undescribed | I53: Fixed | J53: Development | K53: 46300 | L53: e939dc3b | M53: Pass | N53: 46300 | O53: Assignment Review QA 2026-10-05
A54: AR-07 | B54: A6 LaserScan infinity semantics and scan field of view unexplained | C54: Medium | D54: Content | E54: Local staging (Windows) | F54: See the 2026-10-05 Assignments 1-6 review | G54: Fair, consistent assignment and grading | H54: A6 LaserScan infinity semantics and scan field of view unexplained | I54: Fixed | J54: Development | K54: 46300 | L54: e939dc3b | M54: Pass | N54: 46300 | O54: Assignment Review QA 2026-10-05
A55: AR-08 | B55: A1/A2 objectives not assessed; turn-direction and diagram glyph issues | C55: Low | D55: Content | E55: Local staging (Windows) | F55: See the 2026-10-05 Assignments 1-6 review | G55: Fair, consistent assignment and grading | H55: A1/A2 objectives not assessed; turn-direction and diagram glyph issues | I55: Fixed | J55: Development | K55: 46300 | L55: e939dc3b | M55: Pass | N55: 46300 | O55: Assignment Review QA 2026-10-05
A56: AR-09 | B56: Untouched A5/A6 starters earned 20% and 10%; no ROS 2 primer | C56: Medium | D56: Grading | E56: Local staging (Windows) | F56: See the 2026-10-05 Assignments 1-6 review | G56: Fair, consistent assignment and grading | H56: Untouched A5/A6 starters earned 20% and 10%; no ROS 2 primer | I56: Fixed | J56: Development | K56: 46300 | L56: 40de925c | M56: Pass | N56: 46300 | O56: Assignment Review QA 2026-10-05
A57: AR-10 | B57: Sandbox rejected common numpy and Python spellings (np.deg2rad, np.array, np.where, math.pow, dict.update, _) | C57: Medium | D57: Grading | E57: Local staging (Windows) | F57: See the 2026-10-05 in-depth assignment review | G57: Fair, clear grading and instructions | H57: Sandbox rejected common numpy and Python spellings (np.deg2rad, np.array, np.where, math.pow, dict.update, _) | I57: Fixed | J57: Development | K57: 46300 | L57: 1af50897 | M57: Pass | N57: 46300 | O57: Review Fixes QA 2026-10-05
A58: AR-11 | B58: ROS crash text was raw rclpy traceback naming the grader instrumentation file | C58: High | D58: Grading | E58: Local staging (Windows) | F58: See the 2026-10-05 in-depth assignment review | G58: Fair, clear grading and instructions | H58: ROS crash text was raw rclpy traceback naming the grader instrumentation file | I58: Fixed | J58: Development | K58: 46300 | L58: 1af50897 | M58: Pass | N58: 46300 | O58: Review Fixes QA 2026-10-05
A59: AR-12 | B59: ROS checks showed no points; scaffold pass looked contradictory with 0% | C59: Low | D59: Frontend | E59: Local staging (Windows) | F59: See the 2026-10-05 in-depth assignment review | G59: Fair, clear grading and instructions | H59: ROS checks showed no points; scaffold pass looked contradictory with 0% | I59: Fixed | J59: Development | K59: 46300 | L59: 1af50897 | M59: Pass | N59: 46300 | O59: Review Fixes QA 2026-10-05
... A64: AR-17 | B64: Instruction layout and wording issues across A1-A6 and the VFH lesson | C64: Low | D64: Content | E64: Local staging (Windows) | F64: See the 2026-10-05 in-depth assignment review | G64: Fair, clear grading and instructions | H64: Instruction layout and wording issues across A1-A6 and the VFH lesson | I64: Fixed | J64: Development | K64: 46300 | L64: 1af50897 | M64: Pass | N64: 46300 | O64: Review Fixes QA 2026-10-05

Sheet Release Sign-off
A1: Release Sign-off
A2: Sign only after the Release Dashboard is complete, all Release Gate checks are resolved, and defects have retest evidence.
A4: Gate | B4: Required Evidence | C4: Status | D4: Owner | E4: Date | F4: Comments
A5: Automated backend tests | B5: pytest output | C5: Pass | D5: SQA | E5: 46296.833 | F5: 423 backend tests;65 focused Windows and Ubuntu22 checks; dependency/compile checks; actual Neon restart, shared analytics and historical-source reconciliation pass. Frontend unchanged.
A6: Flutter analysis/tests/build | B6: Command output | C6: Pass | D6: SQA | E6: 46296.5 | F6: Windows and Ubuntu22/24: Flutter analysis clean,91 tests passed, release builds passed.
A7: All published assignments validate | B7: Validation report | C7: Pass | D7: SQA | E7: 46296.5 | F7: All six versioned assignments remain published. Versions9,9,10,9,5,5.
A8: All official solutions pass | B8: Per-assignment evidence | C8: Pass | D8: SQA | E8: 46296.5 | F8: All six maintained answers100% on Windows API and Ubuntu22 graders.
A9: Desktop/mobile critical path | B9: Screenshots or test record | C9: Partial | D9: SQA | E9: 46296.5 | F9: All-six Windows rendered diagrams and A6 AI-panel behavior checked. Ubuntu containers pass stack/build checks; physical Ubuntu browser/hardware remains untested.
A10: Sandbox security checks | B10: Timeout/import/output/resource evidence | C10: Pass | D10: SQA | E10: 46296.5 | F10: Existing sandbox error/resource regression passes; actual isolated ROS answers and duplicate probes verified.
A11: Instructor workflow | B11: Account and assignment evidence | C11: Pass | D11: SQA | E11: 46262 | F11: Instructor APIs and UI support student/instructor create, edit, reset, activate, and deactivate flows.
A12: Authentication and account management | B12: Role, password, account, and isolation evidence | C12: Pass | D12: SQA | E12: 46262 | F12: Default student restored; Dave retained with zero progress; persistent browser progress is scoped by user ID.
A13: Secrets and source diff review | B13: Git evidence | C13: Pass | D13: SQA | E13: 46296.5 | F13: Scoped Git publication only. Secrets/configuration and unrelated user PDF moves excluded.
A14: Defect retest complete | B14: Defect IDs and retest evidence | C14: Partial | D14: SQA | E14: 46296.5 | F14: AI grounding and early-hint quality remain mitigated/PARTIAL. Other new defects have focused retest evidence. See AI-UBUNTU-2026-10-01.
A16: Approvals
A17: Role | B17: Name | C17: Decision | D17: Date | E17: Signature / Evidence | F17: Comments
A18: SQA Lead | C18: Pending
A19: Development Lead | C19: Pending
A20: Instructor / Curriculum Owner | C20: Pending
A21: Security / Platform Reviewer | C21: Pending
A22: Product / Research Lead | C22: Pending

Sheet Runbook
A1: SQA Execution Runbook
A2: Run commands from the repository root unless a different working directory is shown. Never put API keys or instructor tokens into the workbook.
A4: Section | B4: Purpose | C4: Command / Procedure | D4: Expected Result
A5: Install | B5: Create Python environment | C5: python -m venv venv | D5: venv directory is created
A6: Install | B6: Install backend packages | C6: .\venv\Scripts\python.exe -m pip install -r .\backend\requirements.txt | D6: Installation succeeds
A7: Install | B7: Install Flutter packages | C7: Set-Location .\frontend; flutter pub get; Set-Location .. | D7: Dependency resolution succeeds
A8: Run | B8: Start backend (Terminal 1) | C8: .\venv\Scripts\python.exe .\backend\run.py | D8: Backend remains running at http://127.0.0.1:5000
A9: Run | B9: Start frontend (Terminal 2) | C9: Set-Location .\frontend; flutter run -d chrome --dart-define=API_BASE_URL=http://127.0.0.1:5000 | D9: Chrome opens the catalog
A10: Backend QA | B10: Run backend tests | C10: Set-Location .\backend; ..\venv\Scripts\python.exe -m pytest -q | D10: All maintained tests pass
A11: Backend QA | B11: Check package integrity | C11: Set-Location .\backend; ..\venv\Scripts\python.exe -m pip check | D11: No broken requirements
A12: Backend QA | B12: Compile Python modules | C12: Set-Location .\backend; ..\venv\Scripts\python.exe -m compileall -q . | D12: No compilation errors
A13: Frontend QA | B13: Static analysis | C13: Set-Location .\frontend; flutter analyze | D13: No issues found
A14: Frontend QA | B14: Widget/state tests | C14: Set-Location .\frontend; flutter test | D14: All tests pass
A15: Frontend QA | B15: Release web build | C15: Set-Location .\frontend; flutter build web --dart-define=API_BASE_URL=http://127.0.0.1:5000 | D15: Build succeeds in .flutter_build\web
... A43: Production | B43: Promote an approved immutable release | C43: .\scripts\promote-release.ps1 -ReleaseTag v4.0.0 -ConfirmProduction | D43: After explicit approval, the exact staging SHA and tag reach production atomically
A44: Severity and Status Definitions
A45: Value | B45: Meaning | C45: Release Effect | D45: Required Action
A46: Critical | B46: Security compromise, data loss, unsafe execution, or platform unavailable | C46: Immediate stop | D46: Fix before any release
A47: High | B47: Critical workflow incorrect or inaccessible with no acceptable workaround | C47: Blocks release | D47: Fix and retest
A48: Medium | B48: Important behavior incorrect with limited workaround | C48: Risk decision required | D48: Plan fix and document
A49: Low | B49: Minor presentation, usability, or documentation issue | C49: Usually does not block | D49: Track and prioritize
A50: Not Run | B50: Test has not been executed | C50: Release incomplete for current scope | D50: Execute or justify N/A
A51: Pass | B51: Actual result matches expected result | C51: Contributes to readiness | D51: Attach evidence
A52: Fail | B52: Actual result does not match expected result | C52: Release Gate failures block | D52: Create defect and fix
A53: Blocked | B53: External/environment condition prevents execution | C53: Release Gate blocks unless explicitly waived | D53: Document blocker and owner
A54: N/A | B54: Test does not apply to this release/environment | C54: Excluded with justification | D54: Explain in Notes
A55: Deferred | B55: Planned future capability not in current release | C55: Excluded from current completion | D55: Review during planning
A57: Single QA workbook policy
A58: Master Checklist | B58: Current checklist | C58: Update affected cases and attach evidence | D58: Do not replace historical results
A59: QA Run History | B59: Imported historical check rows | C59: Append new dated checks with commit, environment, expected / actual and reason | D59: Use PASS, FAIL, PARTIAL, BLOCKED or NOT RUN
A60: QA Report Index | B60: Original report identifiers and hashes | C60: Find the report ID and archive start row | D60: Original paths are provenance, not file links
A61: QA Report Archive | B61: Complete historical report text | C61: Filter by Report ID; lines retain original order | D61: Historical results are not a new QA run
A62: Consolidation 2026-09-30 | B62: 29 reports; 736 recorded check rows; 2220 source lines | C62: No application tests rerun for documentation consolidation | D62: No commit or push performed

Sheet Lists
A1: Status | B1: Priority | C1: Automation | D1: Check | E1: Retest | F1: Defect Status | G1: Severity | H1: Decision | I1: Scope | J1: Test Type
A2: Not Run | B2: Release Gate | C2: Yes | D2: [ ] | E2: Not Required | F2: Open | G2: Critical | H2: Pending | I2: Current | J2: Automated
A3: Pass | B3: P0 | C3: Partial | D3: [x] | E3: Pass | F3: In Progress | G3: High | H3: Approved | I3: Future | J3: API
A4: Fail | B4: P1 | C4: No | E4: Fail | F4: Fixed | G4: Medium | H4: Rejected | J4: Integration
A5: Blocked | B5: P2 | E5: Blocked | F5: Closed | G5: Low | H5: Conditional | J5: Manual
A6: N/A | E6: Not Run | F6: Deferred | J6: Security
A7: Deferred | J7: Accessibility
J8: Performance
J9: Content Review
J10: Process

Sheet V5.2 Neon & Accounts
A1: V5.2 Neon and Account Management - SQA Evidence
A2: Windows local staging verification | 2026-08-28 | Implementation: staging main v5.3; final QA follow-up local
A4: Check ID | B4: Area | C4: Verification | D4: Expected | E4: Result | F4: Evidence | G4: Limitation
A5: V52-001 | B5: Neon | C5: Dedicated staging database | D5: Use robotics_lab_staging without altering old neondb | E5: PASS | F5: Launcher selected dedicated Neon database; old database was preserved. | G5: Internet and Neon availability are required.
A6: V52-002 | B6: Migration | C6: Local-to-Neon transfer | D6: All application records migrate | E6: PASS | F6: 376 rows migrated across 10 application tables. | G6: Migration report remains private.
A7: V52-003 | B7: Persistence | C7: Neon restart | D7: Counts and study history survive restart | E7: PASS | F7: 3 users, 6 assignments, 65 submissions, 2 activities, 44 events, and 22 sessions before and after restart. | G7: No public deployment was performed.
A8: V52-004 | B8: Accounts | C8: Default student credential | D8: Required prototype credential verifies | E8: PASS | F8: Password hash verified without writing plaintext to the workbook. | G8: Change before a real classroom study.
A9: V52-005 | B9: Accounts | C9: Dave retained | D9: Account active with no inherited work | E9: PASS | F9: 0 attempts and 0 completed assignments in Neon. | G9: A stale browser page must refresh after frontend update.
A10: V52-006 | B10: Progress | C10: Cross-account isolation | D10: One student cannot inherit another student's local progress | E10: PASS | F10: Dedicated user-ID storage regression test passed. | G10: Legacy data migrates only to the default prototype student.
A11: V52-007 | B11: Instructor Studio | C11: Manage both roles | D11: Create/list/edit/reset/activate/deactivate students and instructors | E11: PASS | F11: Backend role flows and Flutter UI regression tests passed. | G11: Deletion is intentionally replaced with deactivation.
A12: V52-008 | B12: Safety | C12: Instructor lockout prevention | D12: Cannot self-disable or disable the last active instructor | E12: PASS | F12: Focused API test passed. | G12: A second instructor is required before deactivating the first.
A13: V52-009 | B13: JSON | C13: Tracked password-free account roster | D13: Every clone receives account metadata while passwords and hashes remain outside Git | E13: PASS | F13: backend/data/study_accounts.json contains metadata only; backend rejects temporary passwords in the canonical roster. | G13: Create and reset passwords through Instructor Studio; hashes remain in Neon.
A14: V52-010 | B14: Neon | C14: Neon-only database runtime | D14: Startup requires the authorized Neon staging database; no local PostgreSQL, dump restore, backup worker, or device lock remains | E14: PASS | F14: Windows start/stop, private-config validation, Alembic migration, runtime-state, and service health checks passed. Internet and Neon availability are required. | G14: Requires internet access and Neon availability; no offline database mode remains.
A15: V52-011 | B15: Backend | C15: Full Python gate | D15: Tests, dependencies, compilation pass | E15: PASS | F15: 179 tests after retiring obsolete database-transfer coverage and adding tracked-roster password protection; pip check clean; compileall clean. | G15: None observed.
... A18: V52-014 | B18: Ubuntu | C18: Bash/ShellCheck on current host | D18: Scripts parse and lint | E18: NOT RUN | F18: Current Windows host has no Bash/WSL or ShellCheck runtime. | G18: Physical Ubuntu lab-computer smoke test remains required.

Sheet Neon Architecture
A1: Neon-Only Database Architecture — SQA
A3: Area | B3: Verification | C3: Result | D3: Evidence | E3: Remaining limitation
A4: Runtime selection | B4: Launcher accepts only the configured Neon staging URL | C4: PASS | D4: Windows startup and runtime-state verification | E4: Internet and Neon service required
A5: Local fallback removal | B5: PostgreSQL Compose service, dump transfer, backup worker, device lock, and SQLite runtime switches removed | C5: PASS | D5: Repository and launcher inspection | E5: Historical SQA reports remain labeled as superseded evidence
A6: Private configuration | B6: One ignored repository-root .env; account roster is tracked separately without passwords | C6: PASS | D6: verify-private-config.ps1 and backend password-rejection test | E6: The .env must be provisioned securely on each authorized computer
A7: Backend regression | B7: 179 backend tests and pip dependency check | C7: PASS | D7: Local automated gate on 2026-08-28 | E7: None observed
A8: Flutter regression | B8: Static analysis, 51 tests, and release web build | C8: PASS | D8: Local automated gate on 2026-08-28 | E8: None observed
A9: Service health | B9: Frontend, backend, sandbox, Alembic migration, and Neon selection | C9: PASS | D9: Local Windows runtime on ports 8180/5100/5101 | E9: Physical Ubuntu lab-computer smoke test not repeated

Sheet Grading Integrity QA
A1: Assignment grading integrity repair
A2: Test date | B2: 46288.792 | C2: Branch | D2: fix/grading-integrity | E2: Release state | F2: Local only; not committed or pushed
A3: Scope | B3: Assignments 1-6 grading, scoring, feedback, instructor validation, Flutter compatibility, and real ROS 2 execution
A5: Check ID | B5: Area | C5: Result | D5: Evidence | E5: Issue repaired | F5: Remaining limitation
A6: GI-001 | B6: Run endpoint | C6: Pass | D6: Run and Submit now use the same assignment grader. | E6: Executable code can no longer receive an automatic 100% Run result. | F6: None
A7: GI-002 | B7: Assignment 1 | C7: Pass | D7: Official 100%; mixed 25%; displayed constants rejected. | E7: Grades a reusable Bug2 function across hidden coordinate scenarios. | F7: Hidden cases remain server-only.
A8: GI-003 | B8: Assignment 2 | C8: Pass | D8: Official 100%; mixed 25%; displayed constants rejected. | E8: Grades a reusable Bug route function across hidden coordinate scenarios. | F8: Hidden cases remain server-only.
A9: GI-004 | B9: Assignment 3 | C9: Pass | D9: Official 100%; mixed 50%; displayed constants rejected. | E9: Grades all eight route outputs across cases where either elevator can win. | F9: Eight 12.5% checks display as a rounded whole percentage.
A10: GI-005 | B10: Assignment 4 | C10: Pass | D10: Official 100%; mixed 60%; displayed constants rejected. | E10: Expanded grading from two 50% checks to five 20% checks. | F10: None
A11: GI-006 | B11: Assignment 5 ROS 2 | C11: Pass | D11: Real Docker ROS grader passed 7 of 7 checks. | E11: Rubric weights now match the behavior-harness weights. | F11: Docker Desktop Linux containers are required.
A12: GI-007 | B12: Assignment 6 ROS 2 | C12: Pass | D12: Real Docker ROS grader passed 9 of 9 checks. | E12: Rubric weights now match the behavior-harness weights. | F12: Docker Desktop Linux containers are required.
A13: GI-008 | B13: Instructor validation | C13: Pass | D13: Function-grader assignments validate, edit, and publish in automated tests. | E13: Assignment Studio recognizes and validates the new grader configuration. | F13: None
A14: GI-009 | B14: Backend regression | C14: Pass | D14: Final backend regression gate passed all 200 tests. | E14: No backend regression detected. | F14: None
A15: GI-010 | B15: Python dependencies | C15: Pass | D15: pip check reported no broken requirements. | E15: No dependency conflict detected. | F15: None
A16: GI-011 | B16: Flutter client | C16: Pass | D16: Static analysis passed; 52 tests passed; release web build completed. | E16: Updated assignment criteria and instructions remain client-compatible. | F16: No physical mobile-device test was required.
... A21: GI-016 | B21: Frontend regression | C21: Pass | D21: Flutter analyze passed; 52 tests passed; release web build passed; narrow-screen feedback test passed | E21: Student-facing score and stale-result changes were regression checked | F21: No physical mobile-device test was performed

Sheet V6.2 Workbench
A1: V6.2 Learning Workbench QA | B1: 2026-09-28 | C1: Staging only
A2: Check | B2: Result | C2: Evidence | D2: Scope / limitation | E2: Follow-up
A3: Backend regression | B3: PASS | C3: 215 tests passed; 80.65 seconds | D3: Exact staged release snapshot; no paid AI calls
A4: Python dependencies | B4: PASS | C4: pip check: no broken requirements | D4: Existing pinned Python environment
A5: Flutter analysis | B5: PASS | C5: No issues found | D5: Approved frontend source only
A6: Flutter regression | B6: PASS | C6: 89 tests passed | D6: Widgets, APIs, contrast, keyboard and responsive states
A7: Release web build | B7: PASS | C7: Build completed; 52.3 seconds | D7: Local API at port 5100
A8: ROS assignment 5 | B8: PASS | C8: Maintained answer: 7/7 checks | D8: Real pinned Docker image
A9: ROS assignment 6 | B9: PASS | C9: Maintained answer: 9/9 checks | D9: Real pinned Docker image
A10: Persistent student records | B10: PASS | C10: Student login, saved assignment and quiz progress, study analytics visible | D10: Read-only browser checks; existing records preserved
A11: Lesson reading and outline | B11: PASS | C11: Readable bounded text; outline jump to VFH verified in browser | D11: Authored HTML retained; anchor behavior also widget-tested
A12: Visual contrast and metadata | B12: PASS | C12: New tinted surfaces meet tested 4.5:1 text contrast; attempt/best/latest badges | D12: No grading calculations changed
A13: Results dock | B13: PASS | C13: Desktop opening, drag resizing, minimize/reopen covered by widget tests | D13: Browser smoke evidence in Markdown report
A14: Recovery states | B14: PASS | C14: 401 session-expired message tested; generic retry preserved | D14: No automatic account or session mutation
A15: Production / paid AI | B15: NOT RUN | C15: No deployment or OpenAI request made | D15: Not authorized as part of staging visual release | E15: Separate future gate
A16: Physical Ubuntu / hardware | B16: NOT RUN | C16: No second-device test performed | D16: Source UI change only; existing setup scripts unchanged | E16: Separate device smoke test
A17: Unrelated user file moves | B17: EXCLUDED | C17: Answer and reference moves plus content-builder edit not staged | D17: Backend gate ran exported Git index, not dirty answer paths | E17: User work remains local
A18: Instructor browser smoke | B18: PASS | C18: Instructor sign-in, six published assignments in studio and classroom dashboard loaded | D18: Read-only; no account or assignment changes
A19: Demo grading browser smoke | B19: PASS | C19: Assignment 1 starter 0/4; complete solution 4/4; editing beside dock and responsive drawer verified | D19: Temporary demo only; AI remained off

Sheet Staging QA 2026-10-02
A1: Staging quality, ROS, and Ubuntu QA | B1: 2026-10-02 | C1: Staging only; code commit 49e27f8
A2: Check | B2: Result | C2: Evidence | D2: Scope / limitation | E2: Follow-up
A3: Windows complete gate | B3: PASS | C3: verify-local.ps1 on 49e27f8: 461 backend tests, pip check, compileall, Flutter analyze clean, 95 Flutter tests, release web build, release-source and fresh-clone checks, service health | D3: scripts/verify-local.ps1 on branch staging-ops-hardening, Windows 11
A4: Ubuntu fresh-clone script flow | B4: PASS | C4: Fresh clone of 49e27f8 in a disposable ubuntu:24.04 container: setup-local.sh, run-local.sh, run-browser-tests.sh 2/2, verify-local.sh (461 backend tests, Flutter analyze clean, 95 Flutter tests, release build), check-ros2-local.sh, stop-local.sh | D4: Container on Windows Docker Desktop with the host Docker engine; not a physical Ubuntu laptop or lab computer | E4: Physical lab-computer smoke test
A5: Bash lint (ShellCheck) | B5: PASS | C5: koalaman/shellcheck:stable -x -S warning: 0 findings in 7 Bash scripts | D5: verify-local.sh skips ShellCheck when it is not installed
A6: ROS 2 grader image rebuild | B6: PASS | C6: check-ros2-local.ps1 -Build rebuilt robotics-lab-ros2-grader:jazzy-v1; A5 7/7, A6 9/9; duplicate commands rejected for both; two consecutive clean runs; Ubuntu run also passed | D6: One earlier run failed the A5 duplicate-rejection check while another image build saturated the same Docker engine | E6: Watch timing under load before hosted ROS
A7: ROS runner output and timeout bounds | B7: PASS | C7: Unit tests run real processes: timeout, 1 MB output cap, early stop, docker rm --force after timeout/overflow, no removal after normal exit | D7: Container-level timeout not forced in the real image
A8: Browser flows | B8: PASS | C8: run-browser-tests: student demo (fail, hint, maintained answer 100%, refresh resets) and instructor studio/dashboard/sign-out; 2/2 on Windows (repeated) and Ubuntu | D8: Instructor sign-in writes normal session and audit rows
A9: Run tests load race (SQ-01) | B9: PASS | C9: Run tests disabled until code loads; 5/5 immediate-click browser attempts graded normally; widget tests for disabled and loaded states | D9: Fixed in 8731a37
A10: Redirected PowerShell launch (SQ-02) | B10: PASS | C10: run-local.ps1 *> log started all services; check-ros2-local.ps1 passed under redirection | D10: Fixed in 0ebcba4
A11: Production demo-password guard (SQ-03) | B11: PASS | C11: Production refuses default or <12-character demo passwords; 5 new config tests; credentials removed from READMEs and .env.example | D11: Fixed in 49e27f8
A12: Staging instructor password rotation (SQ-03) | B12: BLOCKED | C12: Not changed: rotating the shared Neon staging credential requires the project owner | D12: Account still uses the formerly published default | E12: Owner: reset via Manage accounts
A13: Local release-build serving | B13: PASS | C13: Launcher serves the Vercel-equivalent build: ready in 0.8 s with 13 requests (was ~500) | D13: -DebugFrontend keeps hot reload
A14: AI evaluation dataset | B14: PASS | C14: 27 cases; prompt-injection, hallucination, provider-failure stubs rejected by tutor guards | D14: Offline harness only; no paid AI calls
A15: Instructor review of AI cases | B15: NOT RUN | C15: 27 cases remain draft; listed by instructor_dataset.py --review-queue | D15: Requires a named instructor reviewer | E15: Owner: instructor review
A16: Production deployment | B16: NOT RUN | C16: No production change | D16: Not authorized
A17: Staging instructor password rotation retest (SQ-03) | B17: PASS | C17: Owner-approved reset via the app's change_password: 32-character random value stored only in the ignored .env; existing instructor sessions revoked; default password returns 401; new password signs in; browser tests 2/2 | D17: Neon staging only; value never printed or committed | E17: Owner: share the new .env value with other devices privately

Sheet UI Refresh QA 2026-10-02
A1: Professional UI and UX refresh QA | B1: 2026-10-02 | C1: Staging only; code commit 8071420
A2: Check | B2: Result | C2: Evidence | D2: Scope / limitation | E2: Follow-up
A3: Windows complete gate | B3: PASS | C3: verify-local.ps1 on 8071420: 461 backend tests, Flutter analyze clean, 97 Flutter tests, release web build, release-source and fresh-clone checks, service health | D3: Windows 11 staging checkout; frontend-only change
A4: Browser flows | B4: PASS | C4: run-browser-tests: student demo (fail, hint, maintained answer 100%, refresh resets) and instructor studio, research dashboard, sign-out: 2/2 | D4: Local stack restarted through run-local.ps1
A5: Fresh-browser regression checks | B5: PASS | C5: 18/18 at 1440px and 390px: no demo credentials on login, learning-path hero and Up next, no instructor studio for students, AI off by default, Ctrl+Enter grades, built-in hint with AI off, refresh resets demo, no unexpected console or HTTP errors | D5: Known demo research 409 (SQ-04) excluded as deferred
A6: Design system and contrast | B6: PASS | C6: Explicit brand, neutral, and AI colors; contrast tests cover body text, brand tint, AI badge, AI container, secondary and neutral chips at 4.5:1 or better | D6: Automated color-pair checks; no manual screen-reader pass | E6: Optional screen-reader review
A7: Screen coverage | B7: PASS | C7: Before/after screenshots of login, home, contents, lesson, workspace, results, studio, research, accounts, and assignment editor at desktop and phone widths | D7: Visual review by the developer
A8: AI feedback labeling | B8: PASS | C8: OpenAI hints and responses use the reserved AI color with an AI-generated badge; widget test asserts the badge on AI responses | D8: AI provider not called; offline widget tests only
A9: Results overlay invariant | B9: PASS | C9: Results remains a minimizable right-side overlay; existing results-panel widget tests pass | D9: No layout docking change
A10: Production deployment | B10: NOT RUN | C10: No production change | D10: Not authorized

Sheet Failure View QA 2026-10-02
A1: Failure view and Try inputs playground QA | B1: 2026-10-02 | C1: Staging only; code commit 075a5e2
A2: Check | B2: Result | C2: Evidence | D2: Scope / limitation | E2: Follow-up
A3: Backend suite | B3: PASS | C3: pytest with ENVIRONMENT=testing and SQLite (CI settings): 502 passed; compileall and pip check clean | D3: Run on the rebased commit; disposable SQLite only
A4: Failure reasons and points | B4: PASS | C4: Grader tests cover passed, wrong_all_inputs, wrong_some_inputs, error_on_some_inputs, unsupported_type, and not_checked with rubric weights; evidence keys stay limited to the documented fields | D4: Function assignments 1-4 only; ROS and variable graders unchanged
A5: Protected-case safety | B5: PASS | C5: API test confirms playground responses contain no configured expected values; reasons never include case data | D5: Automated check
A6: Playground input safety | B6: PASS | C6: Literal-only parser rejects code, names, arithmetic, starred or keyword arguments, non-finite numbers, more than 20 inputs, and inputs over 2000 characters | D6: Execution still bounded by the existing sandbox limits
A7: No persistence from playground | B7: PASS | C7: API test for persistent and demo students: submission, hint, study-session, audit, learning-event, and activity row counts unchanged | D7: Automated check
A8: Authorization and errors | B8: PASS | C8: Unauthenticated 401; ROS assignment 422; blank code 400; oversized code 413; invalid inputs 422 with student-readable message | D8: Automated check
A9: Flutter gate | B9: PASS | C9: flutter analyze clean; 115 tests passed (11 new); release web build succeeded | D9: OneDrive-safe copy under LocalAppData
A10: Browser flows | B10: PASS | C10: Playwright in Chrome: existing demo flow plus new flow (Try inputs on Assignment 1, labelled values, printed output, graded cards show points and failure guidance): 2 passed, instructor flow skipped | D10: Local stack with ENVIRONMENT=testing and throwaway SQLite; Neon staging not used | E10: Run instructor flow with E2E credentials when convenient
A11: Desktop and phone layout | B11: PASS | C11: Screenshots at 1280px, 390px, and 360px: dialog, results cards, and compact phone toolbar button fit without overflow | D11: Visual review by the developer; no physical device
A12: Assignments 3 and 4 live playground | B12: PASS | C12: Demo session calls with waypoint lists and an integer-keyed sensor dict returned 8/8 and 5/5 labelled values, graded false | D12: Starter code only
A13: Windows verify-local.ps1 and Neon staging | B13: NOT RUN | C13: Launcher requires the canonical checkout's private .env and environment; the worktree was verified with CI settings instead | D13: No schema or seed change in this commit | E13: Owner: run verify-local.ps1 in the canonical checkout
A14: Production deployment | B14: NOT RUN | C14: No production change | D14: Not authorized

Sheet v6.3 Playground QA 2026-10-05
A1: v6.3-playground: Try inputs diagrams and example inputs QA | B1: 2026-10-05 | C1: Staging only; code commit 99f4360
A2: Check | B2: Result | C2: Evidence | D2: Scope / limitation | E2: Follow-up
A3: Design decision | B3: PASS | C3: Fable 5.1 consulted: static 2D diagram (Level 1) chosen over a time-step simulator because a simulator would compute answers; example inputs taken from the instructions' public example call | D3: Design review; no runtime effect
A4: Backend suite | B4: PASS | C4: pytest with ENVIRONMENT=testing and SQLite (CI settings): 548 passed; compileall and pip check clean | D4: Run on the rebased commit with no other load on the machine
A5: Diagram contract | B5: PASS | C5: SimulationConfig.diagram and playground.sample_arguments validated (index-only references, unknown points, star misuse, ray sources, checks, extra fields, unparseable samples rejected); assignments 5 and 6 keep their stored shape | D5: Automated
A6: No answer leakage | B6: PASS | C6: Diagram configs contain only argument and value indices; no grading case values; app never computes distances, densities, or optimal angles; hints compare only the student's own returned values | D6: Automated plus code review
A7: Example inputs | B7: PASS | C7: Each A1-A4 sample parses, matches the function's parameter count, and runs on starter code with the expected return count; empty box prefills; Use example inputs restores after edits | D7: Samples equal the instructions' displayed example inputs
A8: Partial drawing | B8: PASS | C8: Owner-reported input (0,0), 2, 3, (4,5), (10,5) now draws S, L, G and the L to G path and names hit and corner as not drawn; paths with a missing point are left out | D8: Automated and browser screenshot
A9: Flutter gate | B9: PASS | C9: flutter analyze clean; 140 tests passed; release web build succeeded | D9: OneDrive-safe copy under LocalAppData
A10: Browser flows | B10: PASS | C10: Playwright in Chrome: demo grading flow plus Try inputs flow (one-click example run, diagram image with screen-reader name, graded failure guidance): 2 passed, instructor flow skipped | D10: Local stack with ENVIRONMENT=testing and throwaway SQLite; Neon staging not used | E10: Run instructor flow with E2E credentials
A11: Desktop and phone visuals | B11: PASS | C11: Screenshots of A1-A4 diagrams at 1280px and A3/A4 at 360px using maintained answers read locally: to scale, legend, rounded map labels, no overflow | D11: Visual review by the developer; no physical device
A12: Assignment versions | B12: PASS | C12: A1-A4 at 11, 11, 12, 11 with matching AI evaluation cases; A5-A6 unchanged at 8, 8 | D12: Older-version drafts no longer load by design | E12: Tell students to copy unfinished work before this reaches a class
A13: Windows verify-local.ps1 and Neon staging | B13: NOT RUN | C13: Launcher needs the canonical checkout's private .env; worktree verified with CI settings instead | D13: No database schema change | E13: Owner: run verify-local.ps1 in the canonical checkout
A14: Production deployment | B14: NOT RUN | C14: No production change | D14: Not authorized

Sheet v6.4 Playground QA 2026-10-05
A1: v6.4-playground: labelled field per input QA | B1: 2026-10-05 | C1: Staging only; code commit dcccba6
A2: Check | B2: Result | C2: Evidence | D2: Scope / limitation | E2: Follow-up
A3: Design decision | B3: PASS | C3: Fable 5.1 chose one labelled field per parameter (Option B) with an Edit as one line toggle; learning aid, not an assessment shortcut, because hints compare only the student's own values; research logging and predict-before-run deferred to a reviewed release | D3: Design review | E3: Phase 3: playground_run event, prediction box
A4: Backend suite | B4: PASS | C4: pytest with ENVIRONMENT=testing and SQLite (CI settings): 563 passed; compileall clean | D4: Run with no other load on the machine
A5: Parameter contract | B5: PASS | C5: PlaygroundParameter validated (kind, name pattern, label, example parsed and kind-checked, unique names, extra fields rejected); v6.3 sample_arguments accepted and dropped; A1-A4 parameter names equal the function signature in order | D5: Automated
A6: Server kind checks | B6: PASS | C6: point, number, integer, list_of_points, angle_map, and text accept only their shapes; wrong inputs return 400 with details entries carrying parameter_index; count mismatch returns parameter_index null | D6: Automated
A7: Flutter gate | B7: PASS | C7: flutter analyze clean; 154 tests passed (labelled fields, per-field errors, empty-field check, one-line round trip, example restore, groups at 360px, hints switch); release web build succeeded | D7: OneDrive-safe copy under LocalAppData
A8: Browser flows | B8: PASS | C8: Playwright in Chrome: demo grading flow plus Try inputs flow with labelled fields (Hit point field visible, one-click example run, diagram image): 2 passed, instructor flow skipped | D8: Local stack with ENVIRONMENT=testing and throwaway SQLite; Neon staging not used | E8: Run instructor flow with E2E credentials
A9: Visual checks | B9: PASS | C9: Screenshots: A1 labelled fields at 1280px; owner's earlier input shows red messages on exactly Hit point and Corner; A3 at 360px with Robot, Elevators, Map headings and no overflow | D9: Visual review by the developer; no physical device
A10: Assignment versions | B10: PASS | C10: A1-A4 at 12, 12, 13, 12 with matching AI evaluation cases; A5-A6 unchanged at 8, 8 | D10: Older-version drafts no longer load by design
A11: Windows verify-local.ps1 and Neon staging | B11: NOT RUN | C11: Launcher needs the canonical checkout's private .env; worktree verified with CI settings instead | D11: No database schema change | E11: Owner: run verify-local.ps1 in the canonical checkout
A12: Production deployment | B12: NOT RUN | C12: No production change | D12: Not authorized

Sheet v6.5 Playground QA 2026-10-05
A1: v6.5-playground: presets, run history, instant checks QA | B1: 2026-10-05 | C1: Staging only; code commit e805d46
A2: Check | B2: Result | C2: Evidence | D2: Scope / limitation | E2: Follow-up
A3: Design decision | B3: PASS | C3: Fable 5.1 selected scenario presets, run history, advisory client kind checks, and Ctrl+Enter; research logging and predict-before-run deferred again; focus linking and point labels excluded | D3: Design review | E3: Phase 3 in its own reviewed release
A4: Backend suite | B4: PASS | C4: pytest with ENVIRONMENT=testing and SQLite (CI settings): 579 passed; compileall clean | D4: Run with no other load on the machine
A5: Scenario contract | B5: PASS | C5: Scenarios need exactly one valid value per parameter; missing or extra parameters, wrong kinds, unparseable values, extra keys such as expected, bad ids, duplicates, and more than 8 rejected | D5: Automated
A6: Presets are safe and runnable | B6: PASS | C6: Every A1-A4 preset runs on the starter code and the maintained answer with the expected return count; preset labels and descriptions quote no grading value | D6: Maintained answers read only inside tests
A7: Flutter gate | B7: PASS | C7: flutter analyze clean; 166 tests passed (kind check table mirroring server rules, preset dropdown, Custom switching, example button fallback, server answer replacing instant check, three-run history with highlight and eviction, reopen history, Ctrl+Enter, 360px fit); release web build succeeded | D7: OneDrive-safe copy under LocalAppData
A8: Browser flows | B8: PASS | C8: Playwright in Chrome: demo grading flow plus Try inputs flow (labelled fields, example run, diagram, preset Hit right after start, run comparison table): 2 passed, instructor flow skipped | D8: Local stack with ENVIRONMENT=testing and throwaway SQLite; Neon staging not used | E8: Run instructor flow with E2E credentials
A9: Visual checks | B9: PASS | C9: Screenshots at 1280px: preset with guiding prompt, instant kind warning with Custom selection, comparison table with the changed Hit point highlighted; 360px preset view (helper text wrap fixed after review) | D9: Visual review by the developer; no physical device
A10: Assignment versions | B10: PASS | C10: A1-A4 at 13, 13, 14, 13 with matching AI evaluation cases; A5-A6 unchanged at 8, 8 | D10: Older-version drafts no longer load by design
A11: Windows verify-local.ps1 and Neon staging | B11: NOT RUN | C11: Launcher needs the canonical checkout's private .env; worktree verified with CI settings instead | D11: No database schema change | E11: Owner: run verify-local.ps1 in the canonical checkout
A12: Production deployment | B12: NOT RUN | C12: No production change | D12: Not authorized

Sheet Draft Persistence QA 2026-10-05
A1: Student draft persistence QA | B1: 2026-10-05 | C1: Staging only; code commit b9b4906
A2: Check | B2: Result | C2: Evidence | D2: Scope / limitation | E2: Follow-up
A3: Back home and reopen | B3: PASS | C3: Persistent student typed a unique marker, went back home, reopened Assignment 1: same code | D3: Playwright in Chrome; throwaway SQLite stack
A4: Browser refresh | B4: PASS | C4: Refresh inside /app kept the session; reopening showed the same code | D4: Opening the front address still asks to sign in by design
A5: Sign out and in | B5: PASS | C5: Signed out, signed in again, reopened: same code; sign-out never clears device drafts | D5: Automated browser test
A6: Another computer | B6: PASS | C6: Fresh browser profile with no device copy: home showed Continue assignment, workspace showed In progress, editor showed the server copy | D6: Automated browser test
A7: Tab closed right after typing | B7: PASS | C7: Tab closed before the server save; reopening on the same device restored the device copy | D7: Automated browser test
A8: Connection lost while typing | B8: PASS | C8: Offline edits restored on return and then reached the server, confirmed from a second fresh profile | D8: Automated browser test
A9: Saved-work status | B9: PASS | C9: Fixed: workspace header said Not started despite saved work; list now reports has_saved_draft from one query; demo and other accounts never see it | D9: Backend and Flutter unit tests
A10: Backend suite | B10: PASS | C10: pytest with ENVIRONMENT=testing and SQLite (CI settings): 581 passed; compileall clean | D10: Run with no other load on the machine
A11: Flutter gate | B11: PASS | C11: flutter analyze clean; 170 tests passed; release web build succeeded | D11: OneDrive-safe copy under LocalAppData
A12: Browser flows | B12: PASS | C12: 5 passed: demo grading, Try inputs, instructor studio, and both persistent-student draft tests | D12: Student and instructor flows used throwaway test accounts | E12: Run the student flows with a dedicated test account before the study
A13: Assignment versions | B13: PASS | C13: No assignment configuration changed; no version bump, so no draft reset
A14: Windows verify-local.ps1 and Neon staging | B14: NOT RUN | C14: Launcher needs the canonical checkout's private .env; worktree verified with CI settings instead | D14: No database schema change | E14: Owner: run verify-local.ps1 in the canonical checkout
A15: Production deployment | B15: NOT RUN | C15: No production change | D15: Not authorized

Sheet Editor Terminal QA 2026-10-14
A1: Terminal under the code editor QA | B1: 2026-10-14 | C1: Staging only; code commit e049187
A2: Check | B2: Result | C2: Evidence | D2: Scope / limitation | E2: Follow-up
A3: Normal run | B3: PASS | C3: Terminal shows the command, printed output, and the Tests finished summary (for example 0 of 4 checks passed) | D3: Playwright in Chrome on the demo; widget tests
A4: Run with an error | B4: PASS | C4: Shows output printed before the error, the File/line location, the student's own failing line, the error message, and Tests did not finish | D4: Location parsed from the existing error text; no backend change
A5: Jump to line | B5: PASS | C5: The Go to line button moves the editor cursor to the failing line and is its own screen-reader button | D5: Browser test clicks it
A6: Accessibility | B6: PASS | C6: Terminal lines read as text (a per-line selectable version read as empty boxes and was replaced); header buttons labelled | D6: Accessibility tree checked; no manual screen-reader pass | E6: Optional screen-reader review
A7: Controls and layout | B7: PASS | C7: Collapse, clear, copy, and drag-resize (96 to 480 px) tested; editor monospace font; fits 360 and 390 px phones | D7: Widget tests and screenshots
A8: Results overlay unchanged | B8: PASS | C8: The Results drawer still opens on each run; the terminal adds to it (AGENTS.md records the owner approval)
A9: Flutter gate | B9: PASS | C9: flutter analyze clean; 190 tests passed (13 new); release web build succeeded | D9: OneDrive-safe copy under LocalAppData
A10: Browser flows | B10: PASS | C10: 6 of 6 passed three runs in a row: demo grading, Try inputs, instructor studio, two persistent-student draft checks, terminal | D10: Throwaway SQLite stack with test accounts
A11: Draft browser checks hardened | B11: PASS | C11: Typing is confirmed through the browser draft copy with retries, and the closed-tab case blocks the server save; on staging main without this change these checks failed intermittently | D11: Synthetic keystrokes were sometimes dropped before Flutter focus; app saving verified separately
A12: Backend suite | B12: NOT RUN | C12: No backend file changed in this commit | D12: Last full run: 581 passed on f63a874c
A13: Windows verify-local.ps1 and Neon staging | B13: NOT RUN | C13: The launcher needs the canonical checkout's private .env; the worktree was verified with CI settings instead | E13: Owner: run verify-local.ps1 in the canonical checkout
A14: Production deployment | B14: NOT RUN | C14: No production change | D14: Not authorized

Sheet VS Code Terminal QA 2026-10-14
A1: VS Code style terminal follow-up QA | B1: 2026-10-14 | C1: Staging only; code commit 7be6a23
A2: Check | B2: Result | C2: Evidence | D2: Scope / limitation | E2: Follow-up
A3: Python traceback | B3: PASS | C3: Error runs print Traceback (most recent call last) with every student frame, outermost first, each with the student's line and a jump button | D3: Browser test, widget tests, and screenshots
A4: Frames stay safe | B4: PASS | C4: Worker returns only student frames (line and function name, max 20); sanitized in the grader; none for syntax errors, rejected code, or hidden-scenario failures | D4: Backend tests including a hidden-scenario failure
A5: Research data | B5: PASS | C5: evidence.error_frames documented in the data dictionary; research exports read specific fields and never include it | D5: Code review of export paths
A6: Terminal open by default | B6: PASS | C6: The workspace opens with the terminal expanded and a ready message | D6: Browser test and screenshot
A7: Visible next to Results | B7: PASS | C7: Results slide in without dimming the editor; screenshot shows the traceback beside the feedback and hints | D7: Desktop width
A8: Backend suite | B8: PASS | C8: pytest with ENVIRONMENT=testing and SQLite (CI settings): 613 passed; compileall clean | D8: Run with no other load on the machine
A9: Flutter gate | B9: PASS | C9: flutter analyze clean; 193 tests passed; release web build succeeded | D9: OneDrive-safe copy under LocalAppData
A10: Browser flows | B10: PASS | C10: 6 of 6 passed three runs in a row | D10: Throwaway SQLite stack with test accounts
A11: Windows verify-local.ps1 and Neon staging | B11: NOT RUN | C11: The launcher needs the canonical checkout's private .env; the worktree was verified with CI settings instead | E11: Owner: run verify-local.ps1 in the canonical checkout
A12: Production deployment | B12: NOT RUN | C12: No production change | D12: Not authorized

Sheet Traceback QA 2026-10-14
A1: Terminal traceback for grading calls and ROS QA | B1: 2026-10-14 | C1: Staging only; code commit 61f1c7c8
A2: Check | B2: Result | C2: Evidence | D2: Scope / limitation | E2: Follow-up
A3: Crash inside a grading call (A1 to A4) | B3: PASS | C3: A bug only a grading test reaches now prints Traceback with the student's own frames, their failing line, and NameError: name 'missing_name' is not defined; the line opens in the editor | D3: Browser test on Assignment 1 and screenshot; widget tests
A4: Hidden inputs stay hidden | B4: PASS | C4: The grader's call line is dropped; messages are kept only for NameError/UnboundLocalError naming an identifier the student wrote and fixed ZeroDivisionError/RecursionError text; a KeyError echoing an input shows only its class | D4: Backend tests including an input-echo attempt
A5: ROS node error (A5, A6) | B5: PASS | C5: The existing ROS error text (controller.py, line N, in name) prints as a Traceback with a clickable controller.py line; command shows python controller.py | D5: Widget test on the reported text format; frontend only, no image change | E5: Owner: confirm once on a ROS run with the Docker image
A6: Research data | B6: PASS | C6: Data dictionary updated for grading-call frames and the safe message rule
A7: Backend suite | B7: PASS | C7: pytest with ENVIRONMENT=testing and SQLite (CI settings): 617 passed
A8: Flutter gate | B8: PASS | C8: flutter analyze clean; 196 tests passed; release web build succeeded | D8: OneDrive-safe copy under LocalAppData
A9: Browser flows | B9: PASS | C9: 6 of 6 passed, including the new grading-call traceback step | D9: Throwaway SQLite stack with test accounts
A10: ROS end to end in Docker | B10: NOT RUN | C10: The ROS image was not rebuilt or run; the backend text it produces is unchanged | E10: Owner: optional ROS run
A11: Windows verify-local.ps1 and Neon staging | B11: NOT RUN | C11: The launcher needs the canonical checkout's private .env; the worktree was verified with CI settings instead | E11: Owner: run verify-local.ps1 in the canonical checkout
A12: Production deployment | B12: NOT RUN | C12: No production change | D12: Not authorized

Sheet Assignment Review QA 2026-10-05
A1: Assignments 1-6 review fixes QA | B1: 2026-10-05 | C1: Staging only; code commits e939dc3b and 40de925c
A2: Check | B2: Result | C2: Evidence | D2: Scope / limitation | E2: Follow-up
A3: Backend suite (verify-local) | B3: PASS | C3: Canonical checkout at 40de925c: 506 passed; pip check and compileall passed | D3: Windows; disposable test databases
A4: Flutter gate | B4: PASS | C4: flutter analyze clean; 118 tests passed; release web build succeeded | D4: OneDrive-safe copy under LocalAppData
A5: Release source and fresh-clone checks | B5: PASS | C5: check-release.ps1 and fresh-clone completeness (six assignments, solutions, migrations) passed | D5: Local only
A6: Starters and maintained answers | B6: PASS | C6: Python grader probe: starters 0% (A1-A4), answers 100%. Running app as demo: A5 and A6 starters 0% with scaffold-credit explanation | D6: Demo session; memory-only
A7: A4 dict readings (AR-01) | B7: PASS | C7: seed_readings.copy(), {**...}, .items() and dict() all score 100% (were 0%) | D7: Automated regression test
A8: Sandbox line numbers and limits (AR-02) | B8: PASS | C8: Rejections and runtime errors report the student's own line; limits documented in A1-A4 | D8: Automated regression test
A9: ROS never-moving loopholes (AR-03, AR-04) | B9: PASS | C9: Docker: never-moving A5 node 40% (was 50%); always-stopped A6 node 35% (was 75%); verify_ros2_assignments.py regressions pass | D9: Local Docker grader image
A10: ROS repeated runs | B10: PARTIAL | C10: verify_ros2_assignments.py: 4 of 5 runs passed. Run 1 hit the 20 s limit while the backend suite and a Flutter build ran concurrently | D10: Load-dependent timeout, not a behavior failure | E10: Resolved: owner approved a 30 s limit; see the retest row
A11: ROS 30 s limit retest | B11: PASS | C11: Owner-approved limit raised from 20 s to 30 s for Assignments 5 and 6 (version 8). verify_ros2_assignments.py passed 2 of 2 runs while the full backend suite ran concurrently (the load that caused the earlier timeout); backend suite 506 passed | D11: Browser client waits up to 90 s, above the 30 s + 5 s grace; in-container build and test limits unchanged
A12: Course pages (AR-05) | B12: PASS | C12: Instructor-note sections hidden at build; each practice page points to its graded assignment; served VFH page verified through the API | D12: Rebuild changed only the intended pages
A13: Served assignments and diagram | B13: PASS | C13: API returns versions 10, 10, 11, 10, 7, 7 without grader_config; served image1.png equals the fixed file | D13: Flutter canvas rendering not inspected visually
A14: Browser flows | B14: PARTIAL | C14: Playwright in Chrome against Neon staging stack: 2 student demo flows passed; instructor flow skipped | D14: Instructor flow needs E2E instructor credentials | E14: Owner: run run-browser-tests.ps1 -InstructorLogin when convenient
A15: Production deployment | B15: NOT RUN | C15: No production change | D15: Not authorized

Sheet Review Fixes QA 2026-10-05
A1: Assignments 1-6 in-depth review fixes QA | B1: 2026-10-05 | C1: Staging only; code commit 1af50897
A2: Check | B2: Result | C2: Evidence | D2: Scope / limitation | E2: Follow-up
A3: Backend suite | B3: PASS | C3: pytest with ENVIRONMENT=testing and disposable SQLite: 595 passed | D3: Windows host
A4: Flutter gate | B4: PASS | C4: flutter analyze clean; 173 tests passed; release web build succeeded | D4: OneDrive-safe copy under LocalAppData
A5: ROS maintained answers (Docker) | B5: PASS | C5: Rebuilt grader image; verify_ros2_assignments.py: A5 7/7 and A6 9/9, duplicate and never-moving rejections pass | D5: Local Docker image
A6: ROS student error text (AR-11) | B6: PASS | C6: Crashed node now shows only controller.py frames plus the exception; clean exit explains rclpy.spin(); no /grader path or ROS warning lines | D6: Docker probes: publisher None, SystemExit, empty-scan crash
A7: ROS per-check points (AR-12) | B7: PASS | C7: ROS evidence carries weight; untouched A5 starter shows 0 of 10 for passed scaffold checks | D7: Docker probe and widget test
A8: Cancelled timer message (AR-13) | B8: PASS | C8: timer.cancel() at 5 s: first failure now says publishing stopped about 5.6 s after start | D8: Docker probe
A9: Sandbox numpy spellings (AR-10) | B9: PASS | C9: np.deg2rad, np.array, np.min, np.where, np.argmin, math.pow, dict.update, and a lone _ now run; np.save, np.fromfile, __import__, str.format stay blocked | D9: Sandbox tests and student probes
A10: A4 zero half width (AR-14) | B10: PASS | C10: Rule states search_half_width may be 0; content test confirms a hidden case uses 0 | D10: Exclusive-window code still scores 0% by design
A11: Printed output on failure (AR-15) | B11: PASS | C11: Results panel shows 'Your printed output' under an execution error | D11: Widget test
A12: Misconception tags (AR-16) | B12: PASS | C12: A1-A4 criteria name configured tags; evidence carries a tag only for wrong values, not crashes | D12: Grader test; ROS tags intentionally not mapped
A13: Instruction wording and layout (AR-17) | B13: PASS | C13: Rules/scoring/checks grouped in one card with headings; neutral feedback; grid units; rectangle first in A2; LiDAR spelling; ROS grading sentence; A6 duplicate ROS terms removed; reveal dialog wording; VFH+ and VFH* in lesson | D13: Content tests; visual check by owner pending | E13: Owner: manual walkthrough
A14: Accessibility of Scenario card (X-5) | B14: PASS | C14: Scenario text and diagram alt text are present as aria-labels in the live semantics tree | D14: Earlier report was a capture artifact; no code change
A15: Live staging app | B15: NOT RUN | C15: Running stack not restarted; another session owns it | D15: New versions 14/14/15/14/9/9 apply on next restart | E15: Owner: stop-local and run-local, then check manually
A16: Production deployment | B16: NOT RUN | C16: No production change | D16: Not authorized

Sheet QA Report Index
A1: Report ID | B1: Report title | C1: Historical scope | D1: Original report path | E1: Source SHA-256 | F1: Archive first row | G1: Source line count
A2: QA-001 | B2: Local AI tutor repair — 2026-09-24 | C2: Dated evidence; not a current release verdict | D2: docs/sqa/AI_TUTOR_LOCAL_FIX_2026-09-24.md | E2: b964bd9f3d05f6bd9e3cf426c0b2ff6ca1b95f102e03db9f831a1aa105ded067 | F2: 2 | G2: 42
A3: QA-002 | B3: Automatic Local Database Backup SQA Report | C3: Dated evidence; not a current release verdict | D3: docs/sqa/AUTOMATIC_LOCAL_DATABASE_BACKUP_SQA_REPORT_2026-08-26.md | E3: e86ef6c196a923430d71442bf6955e92fd3cec6ffd013c3687e91802219168f2 | F3: 44 | G3: 42
A4: QA-003 | B4: Unified Local Handoff Package SQA Report | C4: Dated evidence; not a current release verdict | D4: docs/sqa/COPYABLE_LOCAL_HANDOFF_PACKAGE_SQA_REPORT_2026-08-25.md | E4: 8eb34c14d3b8551386c177747bd74b4af379022e9c430e24c515b8eb521c2fe9 | F4: 86 | G4: 94
A5: QA-004 | B5: Course content library — staging QA | C5: Dated evidence; not a current release verdict | D5: docs/sqa/COURSE_CONTENT_LIBRARY_QA.md | E5: 2931709136e418d895dbd8b7f1dae6dc20305831ce01c751f927cfbc6cfc9646 | F5: 180 | G5: 139
A6: QA-005 | B6: Python Editor Upgrade SQA Report | C6: Dated evidence; not a current release verdict | D6: docs/sqa/EDITOR_UPGRADE_SQA_REPORT_2026-09-24.md | E6: 028428c77fbdf0ce61da68964f2781dcb1b3871d35e735972391d9c726fc2463 | F6: 319 | G6: 67
A7: QA-006 | B7: Assignment Grading Integrity SQA Report | C7: Dated evidence; not a current release verdict | D7: docs/sqa/GRADING_INTEGRITY_SQA_REPORT_2026-09-23.md | E7: bc1155b7b7b1e126270d408315eaccca2fdc9efaa07c6970803622a967bddcec | F7: 386 | G7: 95
A8: QA-007 | B8: Local PostgreSQL OneDrive Handoff SQA Report | C8: Dated evidence; not a current release verdict | D8: docs/sqa/LOCAL_POSTGRES_ONEDRIVE_HANDOFF_SQA_REPORT_2026-08-24.md | E8: 5b76acff9b40ab89bd6458731cb108430c8e6df74d9c690a4b0f8e15e43509cd | F8: 481 | G8: 131
A9: QA-008 | B9: Neon and Account Management SQA Report | C9: Dated evidence; not a current release verdict | D9: docs/sqa/NEON_ACCOUNT_MANAGEMENT_SQA_REPORT_2026-08-28.md | E9: 482c065442e43769a4f40043f677f1192768486a72439eaf7e7c99c7de756137 | F9: 612 | G9: 69
A10: QA-009 | B10: Neon-Only Database Architecture SQA Report | C10: Dated evidence; not a current release verdict | D10: docs/sqa/NEON_ONLY_DATABASE_SQA_REPORT_2026-08-28.md | E10: 25906992e2574ec18194c39a3ea2b22207b9012ff512f6e02cacd8659564e1c5 | F10: 681 | G10: 56
A11: QA-010 | B11: Repository cleanup SQA report | C11: Dated evidence; not a current release verdict | D11: docs/sqa/REPOSITORY_CLEANUP_SQA_REPORT_2026-08-24.md | E11: b3cc6e57f6374fed91edbbbbc637b016527bc170c65d0324a6f58c7264bfa512 | F11: 737 | G11: 81
A12: QA-011 | B12: Results drawer and account-label SQA | C12: Dated evidence; not a current release verdict | D12: docs/sqa/RESULTS_DRAWER_ACCOUNT_LABEL_SQA_2026-09-25.md | E12: babfeb9651300b80ce6bfb76bb9bca950469d55d45047be5dc8c95511eec3d0f | F12: 818 | G12: 27
A13: QA-012 | B13: Isolated Results Panel Correction | C13: Dated evidence; not a current release verdict | D13: docs/sqa/RESULTS_PANEL_CORRECTION_QA.md | E13: b48e5bfbd40948099f3cb97a40d6df1afa7d101c9c386d2ef070a4089a530d15 | F13: 845 | G13: 42
... A30: QA-029 | B30: V5 Staging SQA Report | C30: Archived at consolidation | D30: docs/archive/sqa/V5_STAGING_SQA_REPORT.md | E30: 7a9a3846885332da806980f0d1e736f50f3e5aaf5df9db6e2025ed6dd035c528 | F30: 2148 | G30: 74

Sheet QA Run History
A1: Report ID | B1: Source line | C1: Recorded check | D1: Recorded result | E1: Recorded evidence / limitation
A2: QA-001 | B2: 25 | C2: Ordinary launch | D2: PASS | E2: `run-local.ps1` with no AI flag | Three services healthy; AI available but off | All services ready; AI available `True`, off until assignment switch
A3: QA-001 | B3: 26 | C3: AI off | D3: PASS | E3: Demo `POST /assignments/1/submit`, `use_ai_tutor=false` | No tutor feedback | No tutor feedback
A4: QA-001 | B4: 27 | C4: AI on | D4: PASS | E4: Same demo submission with `use_ai_tutor=true` | OpenAI feedback; grading still returns | Tutor source `openai`
A5: QA-001 | B5: 28 | C5: Follow-up question | D5: PASS | E5: Demo `POST /assignments/1/tutor` | Nonempty OpenAI answer | Source `openai`; answer nonempty
A6: QA-001 | B6: 29 | C6: Tutor regressions | D6: PASS | E6: `python -m pytest tests/test_tutor.py tests/test_tutor_evaluations.py -q` | Tests pass | 31 passed
A7: QA-001 | B7: 30 | C7: Windows launcher syntax | D7: PASS | E7: PowerShell parser | No parse errors | No parse errors
A8: QA-001 | B8: 31 | C8: Ubuntu launcher syntax | D8: PASS | E8: Git Bash `bash -n scripts/run-local.sh` | No parse errors | No parse errors
A9: QA-001 | B9: 32 | C9: Manual Flutter click-through | D9: NOT RUN | E9: Log in, toggle AI, run and ask in browser | OpenAI result visible | Not performed; API flow and UI wiring checked instead
A10: QA-001 | B10: 33 | C10: Physical Ubuntu run | D10: NOT RUN | E10: Launch and exercise on Ubuntu | Same behavior | No Ubuntu machine used
A11: QA-002 | B11: 24 | C11: PowerShell syntax | D11: PASS | E11: Database module, launcher, worker, and stop scripts parsed without errors | None
A12: QA-002 | B12: 25 | C12: Managed worker startup | D12: PASS | E12: Runtime state recorded `database-backup`; worker produced a verified dump | Requires Docker PostgreSQL mode
A13: QA-002 | B13: 26 | C13: Scheduled cycle | D13: PASS | E13: One-minute test interval produced a second worker log entry | Normal default is 10 minutes
... A88: QA-005 | B88: 26 | C88: Responsive editor toolbar | D88: Pass | E88: Desktop split view and narrow/mobile layouts render without overflow in widget tests
A89: QA-005 | B89: 32 | C89: Backend dependency check | D89: Pass — no broken requirements
A90: QA-005 | B90: 33 | C90: Backend tests | D90: Pass — 205 tests
A91: QA-005 | B91: 34 | C91: Focused editor and API tests | D91: Pass
A92: QA-005 | B92: 35 | C92: Flutter analysis | D92: Pass — no issues
A93: QA-005 | B93: 36 | C93: Flutter tests | D93: Pass — 61 tests
A94: QA-005 | B94: 37 | C94: Flutter release web build | D94: Pass
A95: QA-005 | B95: 38 | C95: PostgreSQL migration | D95: Pass — staging Neon upgraded from `0004` to `0005_code_drafts`
A96: QA-005 | B96: 44 | C96: Student login | D96: Pass
A97: QA-005 | B97: 45 | C97: Assignment 1 editor opens | D97: Pass
A98: QA-005 | B98: 46 | C98: Editor tools are visible | D98: Pass
A99: QA-005 | B99: 47 | C99: Manual formatter responds | D99: Pass
A100: QA-005 | B100: 48 | C100: Restore-starter confirmation and cleanup | D100: Pass
... A103: QA-005 | B103: 51 | C103: Local API, sandbox, frontend, and database startup | D103: Pass
A104: QA-006 | B104: 17 | C104: GI-001 | D104: Pass | E104: The Run endpoint awarded 100% to any executable Python submission | Run and Submit now use the same assignment-specific grader | API contract tests
A105: QA-006 | B105: 18 | C105: GI-002 | D105: Pass | E105: Assignments 1–4 could pass with hardcoded displayed values | Added the modular PythonFunctionGrader and multiple hidden parameter scenarios | Official, partial, hardcoded, syntax, and runtime tests
A106: QA-006 | B106: 19 | C106: GI-003 | D106: Pass | E106: Python-assignment feedback was too generic | Added criterion-specific failure guidance without exposing hidden inputs or answers | Grader feedback tests
A107: QA-006 | B107: 20 | C107: GI-004 | D107: Pass | E107: Assignment 4 allowed only 0%, 50%, or 100% | Expanded the rubric to five independently checked 20% criteria | Mixed answer scored 60%
A108: QA-006 | B108: 21 | C108: GI-005 | D108: Pass | E108: Assignment 3 used 12.5% criteria but displayed integer scores without explanation | Instructions now state that the final total is rounded to the nearest whole percent | Instruction and score tests
A109: QA-006 | B109: 22 | C109: GI-006 | D109: Pass | E109: ROS rubrics did not match the behavior-harness weights | Aligned Assignment 5 to 20/20/30/30 and Assignment 6 to 15/20/20/35/10 | Derived rubric-to-harness regression test
A110: QA-006 | B110: 23 | C110: GI-007 | D110: Pass | E110: Instructor validation rejected the new function grader | Added configuration validation for function name, criteria, cases, arguments, and expected outputs | Assignment Studio validate/edit/publish tests
A111: QA-006 | B111: 24 | C111: GI-008 | D111: Pass | E111: Editing code after a successful run left the old 100% result visible | Hide the Results panel after an edit and label the saved value as `Previous score` until the student runs again | Manual Chrome QA and Flutter widget tests
A112: QA-006 | B112: 25 | C112: GI-009 | D112: Pass | E112: The Flutter client recalculated scores as passed checks divided by total checks | Use the backend's authoritative weighted score and show the unweighted check pass rate separately | Weighted-score widget regression test
A113: QA-006 | B113: 31 | C113: Assignment | D113: Passed | E113: Mutation | Score | Execution completed | Passed checks | Result
A114: QA-006 | B114: 33 | C114: 1 | D114: Pass | E114: Commented out the distance helper | 0% | No | No (`NameError`) | 0/4
A115: QA-006 | B115: 34 | C115: 2 | D115: Pass | E115: Commented out the distance helper | 0% | No | No | 0/4
... A175: QA-007 | B175: 88 | C175: AI default | D175: PASS | E175: Launcher reported AI disabled
A176: QA-007 | B176: 94 | C176: Focused database-transfer tests | D176: PASS, 3 tests
A177: QA-007 | B177: 95 | C177: Backend regression | D177: PASS, 174 tests
A178: QA-007 | B178: 96 | C178: Python dependency integrity | D178: PASS, no broken requirements
A179: QA-007 | B179: 97 | C179: Python compilation | D179: PASS
A180: QA-007 | B180: 98 | C180: PowerShell parser checks | D180: PASS, five database/run/verification scripts
A181: QA-007 | B181: 99 | C181: Docker Compose configuration | D181: PASS
A182: QA-007 | B182: 100 | C182: Isolated handoff integration | D182: PASS, migrate/backup/checksum/lock/reset/same-device restore/clean-device restore/reconcile
A183: QA-007 | B183: 101 | C183: Flutter analysis | D183: PASS, no issues
A184: QA-007 | B184: 102 | C184: Flutter tests | D184: PASS, 49 tests
A185: QA-007 | B185: 103 | C185: Flutter web release build | D185: PASS
A186: QA-007 | B186: 104 | C186: Git whitespace check | D186: PASS
A187: QA-007 | B187: 105 | C187: Managed API and sandbox health | D187: PASS
A188: QA-007 | B188: 111 | C188: Older Assignment 1 code appeared in the v5 workspace | D188: PASS | E188: Browser drafts were stored only by assignment ID, so a v4 draft could be loaded after the assignment advanced to v5 | Persist the draft's assignment version and load it only for an exact ID/version match; preserve but ignore legacy unversioned drafts | Focused six-test state suite, full 49-test Flutter suite, analyzer, release build, and same-profile browser restart showed the corrected v5 starter code
A189: QA-007 | B189: 117 | C189: Physical laptop handoff | D189: NOT RUN | E189: Stop on desktop, wait for OneDrive, start on laptop, verify accounts/submissions, then return through the same procedure
A190: QA-007 | B190: 119 | C190: Backup encryption | D190: BLOCKED FOR REAL STUDY | E190: Prototype dump is not encrypted; approve encrypted storage or managed PostgreSQL before collecting real participant data
A191: QA-007 | B191: 120 | C191: OneDrive availability/merge guarantee | D191: PARTIAL | E191: Checksums detect incomplete/tampered copies, but OneDrive itself cannot provide a database transaction protocol; always wait for **Up to date**
A192: QA-007 | B192: 121 | C192: Master Excel SQA workbook | D192: BLOCKED | E192: The required standalone spreadsheet artifact runtime was unavailable in this session; it cannot be safely edited with the mandated workbook tooling. This Markdown report is the current evidence and the workbook still needs the same PostgreSQL and versioned-draft rows added
A193: QA-007 | B193: 122 | C193: Production/live repository | D193: NOT RUN | E193: This change is staging-only; no production authorization was given
A194: QA-008 | B194: 24 | C194: Dedicated Neon database | D194: PASS | E194: The launcher selected `robotics_lab_staging`; the older Neon `neondb` database was not overwritten.
A195: QA-008 | B195: 25 | C195: Local-to-Neon migration | D195: PASS | E195: 376 application rows migrated across users, assignments, submissions, activities, events, sessions, hints, audits, and auth records.
A196: QA-008 | B196: 26 | C196: Core analytics reconciliation | D196: PASS | E196: Neon contains 3 users, 6 assignments, 65 submissions, 2 assignment-activity rows, 44 learning events, and 22 study sessions before and after restart.
A197: QA-008 | B197: 27 | C197: Dave account retained | D197: PASS | E197: Dave remains active with 0 submissions and 0 completed assignments.
A198: QA-008 | B198: 28 | C198: Default student account restored | D198: PASS | E198: The active default student password hash verifies against the required prototype password. No password is recorded in this report.
A199: QA-008 | B199: 29 | C199: Versioned account roster | D199: PASS | E199: `backend/data/study_accounts.json` contains password-free account metadata and is eligible for Git tracking. Password hashes remain in Neon.
... A275: QA-011 | B275: 16 | C275: Complete local gate | D275: Pass | E275: 206 backend tests, dependency and Python checks, 67 Flutter tests, analysis, release web build, fresh-clone source check, and managed service health
A276: QA-012 | B276: 12 | C276: Desktop overlay, no bottom dock; instructions retain original size | D276: PASS: browser at 1280x720; widget test compares instruction size before/after opening
A277: QA-012 | B277: 13 | C277: Minimize/reopen and AI off by default | D277: PASS: widget regression and browser; retained 0% score, terminal output and four failed-check details after reopening
A278: QA-012 | B278: 14 | C278: Automatic opening after Run tests | D278: PASS: instructor preview, untouched Assignment 1 starter returns 0%; panel opens for loading and results
A279: QA-012 | B279: 15 | C279: Narrow-screen panel and existing workspace shortcuts | D279: PASS: browser at 390x844; responsive workspace and shortcut widget regressions
A280: QA-012 | B280: 16 | C280: Flutter analysis | D280: PASS: no issues
A281: QA-012 | B281: 17 | C281: Flutter tests | D281: PASS: all 89 tests
A282: QA-012 | B282: 18 | C282: Release web build | D282: PASS: API_BASE_URL=http://127.0.0.1:5100
A283: QA-013 | B283: 33 | C283: Screenshot-style globals and partial code | D283: PASS | E283: Executes, prints 4.0 4.0 0.0 0.0; score 0%; explanatory feedback
A284: QA-013 | B284: 34 | C284: Same two components using parameters | D284: PASS | E284: Same example output; score 50%, two passed criteria
A285: QA-013 | B285: 35 | C285: Contradictory AI output | D285: PASS | E285: Four name-error phrasings across diagnosis, answer, hint and debugging steps fall back safely
A286: QA-013 | B286: 36 | C286: Grounded explanation / actual NameError | D286: PASS | E286: Valid global-input explanation and actual failed-execution NameError remain accepted
A287: QA-013 | B287: 37 | C287: Focused tutor, instructor-case and function-grader tests | D287: PASS | E287: 56 passed
A288: QA-013 | B288: 38 | C288: API and authentication regressions | D288: PASS | E288: 67 passed
A289: QA-013 | B289: 39 | C289: Running local API with temporary demo session | D289: PASS | E289: At API 5100, both variants returned 0% / 50%, successful execution and the new explanatory message; AI off
A290: QA-013 | B290: 40 | C290: Paid OpenAI model validation | D290: NOT RUN | E290: Injectable fake responses exercised the request and response checks; no paid request authorized
A291: QA-013 | B291: 41 | C291: Professor's computer / physical Ubuntu / live deployment | D291: NOT RUN | E291: Local staging repair only
A292: QA-014 | B292: 21 | C292: Source backup | D292: PASS | E292: Remote `backup-v5` resolves exactly to `7976caa8eb764c3452ab9f3021ddc875a5631e36` | None
A293: QA-014 | B293: 22 | C293: Bash syntax | D293: PASS | E293: Every maintained `.sh` file parsed with Bash on Ubuntu | None
A294: QA-014 | B294: 23 | C294: ShellCheck | D294: PASS | E294: ShellCheck completed with no findings | None
... A334: QA-015 | B334: 56 | C334: Incorrect ROS behavior | D334: PASS | E334: ROS assignment tests rejected nonconforming observable behavior
A335: QA-015 | B335: 67 | C335: Backend regression after final fix | D335: PASS, 179 tests
A336: QA-015 | B336: 68 | C336: Python dependencies | D336: PASS, no broken requirements
A337: QA-015 | B337: 69 | C337: Python compilation | D337: PASS
A338: QA-015 | B338: 70 | C338: Fresh PostgreSQL migration | D338: PASS through `0004_basic_research_analytics`
A339: QA-015 | B339: 71 | C339: Populated database migration | D339: PASS; existing attempts unchanged
A340: QA-015 | B340: 72 | C340: PostgreSQL backup/checksum/restart restore | D340: PASS; all application table counts reconciled
A341: QA-015 | B341: 73 | C341: Real ROS 2 Docker answers | D341: PASS, Assignments 5 and 6
A342: QA-015 | B342: 74 | C342: Flutter analysis | D342: PASS, no issues
A343: QA-015 | B343: 75 | C343: Flutter tests | D343: PASS, 50 tests
A344: QA-015 | B344: 76 | C344: Flutter release web build | D344: PASS
A345: QA-015 | B345: 77 | C345: Git whitespace check | D345: PASS
A346: QA-015 | B346: 78 | C346: Repository source-safety check | D346: PASS after the owner-approved backup-folder consolidation; legacy dumps are preserved inside ignored `local_handoff_package/history`
A347: QA-015 | B347: 84 | C347: Login and six-assignment catalog | D347: PASS | E347: Student and instructor password accounts opened the current six-assignment application
A348: QA-015 | B348: 85 | C348: Student overview | D348: PASS | E348: Completion, attempts, best score, and active time rendered
A349: QA-015 | B349: 86 | C349: Student assignment analytics | D349: PASS | E349: All six current assignment versions plus historical versions rendered separately
...

Sheet QA Report Archive
A1: Report ID | B1: Source line | C1: Original report text
A2: QA-001 | B2: 1 | C2: # Local AI tutor repair — 2026-09-24
A3: QA-001 | B3: 2
A4: QA-001 | B4: 3 | C4: Environment: Windows staging checkout, base commit `2252bcf` plus uncommitted
A5: QA-001 | B5: 4 | C5: repair; managed local frontend `127.0.0.1:8180`, API `127.0.0.1:5100`, and
A6: QA-001 | B6: 5 | C6: sandbox `127.0.0.1:5101`. Production was not changed. The API checks used a
A7: QA-001 | B7: 6 | C7: temporary demo session, not a persistent student account.
A8: QA-001 | B8: 7
A9: QA-001 | B9: 8 | C9: ## Confirmed causes
A10: QA-001 | B10: 9
A11: QA-001 | B11: 10 | C11: 1. The ordinary local launchers cleared `OPENAI_API_KEY` before starting the
A12: QA-001 | B12: 11 | C12: backend. The assignment switch could request AI, but the backend had no key.
A13: QA-001 | B13: 12 | C13: 2. With the key available, submission feedback sometimes fell back because the
A14: QA-001 | B14: 13 | C14: 420-token response limit truncated the required structured JSON. A tutor
A15: QA-001 | B15: 14 | C15: question using the same key succeeded.
A16: QA-001 | B16: 15
A17: QA-001 | B17: 16 | C17: The launchers now keep the server-side key available while the assignment
A18: QA-001 | B18: 17 | C18: switch stays off by default. The optional `-EnableAi` / `--enable-ai` flags
A19: QA-001 | B19: 18 | C19: validate key presence at startup. The tutor now requests concise fields with a
A20: QA-001 | B20: 19 | C20: 1000-token output limit. Neither change makes AI part of grading.
A21: QA-001 | B21: 20
A22: QA-001 | B22: 21 | C22: ## Checks
A23: QA-001 | B23: 22
A24: QA-001 | B24: 23 | C24: | Requirement | Exact check / user flow | Expected | Actual | Result |
A25: QA-001 | B25: 24 | C25: |---|---|---|---|---|
A26: QA-001 | B26: 25 | C26: | Ordinary launch | `run-local.ps1` with no AI flag | Three services healthy; AI available but off | All services ready; AI available `True`, off until assignment switch | PASS |
A27: QA-001 | B27: 26 | C27: | AI off | Demo `POST /assignments/1/submit`, `use_ai_tutor=false` | No tutor feedback | No tutor feedback | PASS |
A28: QA-001 | B28: 27 | C28: | AI on | Same demo submission with `use_ai_tutor=true` | OpenAI feedback; grading still returns | Tutor source `openai` | PASS |
A29: QA-001 | B29: 28 | C29: | Follow-up question | Demo `POST /assignments/1/tutor` | Nonempty OpenAI answer | Source `openai`; answer nonempty | PASS |
A30: QA-001 | B30: 29 | C30: | Tutor regressions | `python -m pytest tests/test_tutor.py tests/test_tutor_evaluations.py -q` | Tests pass | 31 passed | PASS |
A31: QA-001 | B31: 30 | C31: | Windows launcher syntax | PowerShell parser | No parse errors | No parse errors | PASS |
A32: QA-001 | B32: 31 | C32: | Ubuntu launcher syntax | Git Bash `bash -n scripts/run-local.sh` | No parse errors | No parse errors | PASS |
A33: QA-001 | B33: 32 | C33: | Manual Flutter click-through | Log in, toggle AI, run and ask in browser | OpenAI result visible | Not performed; API flow and UI wiring checked instead | NOT RUN |
A34: QA-001 | B34: 33 | C34: | Physical Ubuntu run | Launch and exercise on Ubuntu | Same behavior | No Ubuntu machine used | NOT RUN |
A35: QA-001 | B35: 34
A36: QA-001 | B36: 35 | C36: The two NOT RUN checks need a manual browser pass on this build and an Ubuntu
A37: QA-001 | B37: 36 | C37: device respectively before claiming those environments were exercised. OpenAI
A38: QA-001 | B38: 37 | C38: availability also depends on the configured key, account credit, network, and
A39: QA-001 | B39: 38 | C39: service status; deterministic grading remains usable when AI is unavailable.
A40: QA-001 | B40: 39
A41: QA-001 | B41: 40 | C41: `AGENTS.md` was reviewed. No durable repository or release rule changed, so it
A42: QA-001 | B42: 41 | C42: did not need an edit. This was a staging-only repair; production was not changed.
A43: QA-001 | B43: 42
A44: QA-002 | B44: 1 | C44: # Automatic Local Database Backup SQA Report
A45: QA-002 | B45: 2
A46: QA-002 | B46: 3 | C46: Date: 2026-08-26
A47: QA-002 | B47: 4
A48: QA-002 | B48: 5 | C48: Environment: canonical Windows staging checkout on `PONKOJ-PC`
A49: QA-002 | B49: 6
A50: QA-002 | B50: 7 | C50: Scope: managed local PostgreSQL backup lifecycle only
A51: QA-002 | B51: 8
A52: QA-002 | B52: 9 | C52: ## Result
A53: QA-002 | B53: 10
A54: QA-002 | B54: 11 | C54: The local launcher now starts a managed backup worker. It creates a verified
A55: QA-002 | B55: 12 | C55: PostgreSQL dump immediately after startup and every 10 minutes thereafter when
A56: QA-002 | B56: 13 | C56: the database has changed. The explicit stop command terminates that worker
A57: QA-002 | B57: 14 | C57: before creating the final handoff backup and releasing the device lock.
A58: QA-002 | B58: 15
A59: QA-002 | B59: 16 | C59: Closing a browser tab does not stop local services. Therefore, automatic
A60: QA-002 | B60: 17 | C60: backups continue while the managed stack remains running, but a clean
A61: QA-002 | B61: 18 | C61: `stop-local.ps1` remains mandatory before changing computers.
A62: QA-002 | B62: 19
A63: QA-002 | B63: 20 | C63: ## QA evidence
A64: QA-002 | B64: 21
A65: QA-002 | B65: 22 | C65: | Check | Evidence | Result | Remaining limitation |
A66: QA-002 | B66: 23 | C66: | --- | --- | --- | --- |
A67: QA-002 | B67: 24 | C67: | PowerShell syntax | Database module, launcher, worker, and stop scripts parsed without errors | PASS | None |
A68: QA-002 | B68: 25 | C68: | Managed worker startup | Runtime state recorded `database-backup`; worker produced a verified dump | PASS | Requires Docker PostgreSQL mode |
A69: QA-002 | B69: 26 | C69: | Scheduled cycle | One-minute test interval produced a second worker log entry | PASS | Normal default is 10 minutes |
A70: QA-002 | B70: 27 | C70: | Unchanged database | Consecutive cycle reported `Database unchanged; automatic backup skipped` | PASS | PostgreSQL-only optimization |
A71: QA-002 | B71: 28 | C71: | Changed database | Controlled temporary-table change produced a new dump and SHA-256 manifest | PASS | Temporary probe was removed before final backup |
A72: QA-002 | B72: 29 | C72: | Backup validation | Dump creation ran `pg_restore --list`; manifest recorded checksum, schema, system ID, and WAL position | PASS | None |
A73: QA-002 | B73: 30 | C73: | Clean shutdown | Worker stopped first; final verified dump was saved; state and device-lock files were removed | PASS | User must run the stop command before device handoff |
A74: QA-002 | B74: 31 | C74: | Active services | Backend, sandbox, frontend, and PostgreSQL started successfully; backend health returned `ok` | PASS | Browser-close detection is intentionally not used |
A75: QA-002 | B75: 32 | C75: | Folder consolidation | Four older August 25 backups were preserved under `local_handoff_package/history/legacy-2026-08-25`; duplicate folder removed | PASS | History remains private and ignored by Git |
A76: QA-002 | B76: 33 | C76: | Isolated handoff regression | Automated backup, unchanged skip, checksum rejection, device lock, same-device recovery, and simulated clean-device restore preserved all table counts | PASS | Physical second-device operation was not repeated |
A77: QA-002 | B77: 34 | C77: | Complete local gate | 179 backend tests, dependency check, migrations, database handoff, Flutter analysis, 50 Flutter tests, release web build, and source-safety check | PASS | Existing unrelated V5.2 working-tree changes remain uncommitted |
A78: QA-002 | B78: 35
A79: QA-002 | B79: 36 | C79: ## Operator rule
A80: QA-002 | B80: 37
A81: QA-002 | B81: 38 | C81: For another computer, copy only the complete `local_handoff_package` folder.
A82: QA-002 | B82: 39 | C82: Do not copy a Python environment, Docker volume, cache, or an obsolete
A83: QA-002 | B83: 40 | C83: `local_database_backups` folder. Stop the source stack and wait for OneDrive or
A84: QA-002 | B84: 41 | C84: the copy operation to finish before starting on the destination device.
A85: QA-002 | B85: 42
A86: QA-003 | B86: 1 | C86: # Unified Local Handoff Package SQA Report
A87: QA-003 | B87: 2
A88: QA-003 | B88: 3 | C88: **Date:** 2026-08-25
A89: QA-003 | B89: 4
A90: QA-003 | B90: 5 | C90: **Repository:** `CS-Ponkoj/Robotics-Programming-Lab-Staging`
A91: QA-003 | B91: 6
A92: QA-003 | B92: 7 | C92: **Branch:** `main`
A93: QA-003 | B93: 8
A94: QA-003 | B94: 9 | C94: **Tested state:** local staging candidate based on `f3789b2720376e566a0183d9cf22dda4da58df6e`
A95: QA-003 | B95: 10
A96: QA-003 | B96: 11 | C96: ## Outcome
A97: QA-003 | B97: 12
A98: QA-003 | B98: 13 | C98: The project now uses one ignored folder for portable private local state:
A99: QA-003 | B99: 14
A100: QA-003 | B100: 15 | C100: ```text
...
